Workbook
Name ColumnTitle1: Invoice[[#Headers],[DESCRIPTION]]
Name ColumnTitle1: Invoice[[#Headers],[DESCRIPTION]]
Name ColumnTitleRegion1..B11.1: DN!$A$7
Name Company_Name: DN!$A$1
Name DDDD: '[1]MASTER LIST'!$1:$1048576
Name Masterlist: 'MASTER LIST'!$1:$1048576
Name NameList: 'MASTER LIST'!#REF!
Name NameList2: 'MASTER LIST'!#REF!
Name RowTitleRegion1..E5: DN!$H$2
Name s: '[2]MASTER LIST'!$1:$1048576
Name SSS: #REF!
Name Store_Name: Table118[STORES]
Name Store_Name: Table118[STORES]

Sheet CK_HF
A1: Nº | B1: DATE | C1: Month | D1: Week Num2 | E1: PO Number | F1: Document Number | G1: Delivered From/To | H1: BARCODE | I1: ITEM CODE | J1: ITEM NAME | K1: PACKING SIZE | L1: PURCHASE Uom | M1: QUANTITY | N1: Master List Prices | O1: INV Prices | P1: PRICE (USD) | Q1: TOTAL PRICE (USD) | R1: LAST TOTAL PRICE (USD) | S1: EXPRIED DATE | T1: ALERT | U1: REMARK | V1: Transaction Type | W1: Category | X1: Sub Category | Y1: H1
A2: 1 | B2: 45901 | C2: 9 | D2: Week 01 | G2: HEALTHY FOOD | H2: 0 | I2: REV-FOOD | J2: Revenue Food | K2: 0 | L2: 0 | M2: 1 | N2: 0 | O2: 173.38 | R2: 173.38 | V2: Sold | W2: FOOD | X2: FOOD | Y2: 0
A3: 2 | B3: 45901 | C3: 9 | D3: Week 01 | G3: HEALTHY FOOD | H3: 0 | I3: REV-NON ALCOHOL | J3: Revenue Non Alcohol | K3: 0 | L3: 0 | M3: 1 | N3: 0 | O3: 39.47 | R3: 39.47 | V3: Sold | W3: BEVERAGE NON-ALOCOHOL | X3: BEVERAGE NON-ALOCOHOL | Y3: 0
A4: 3 | B4: 45902 | C4: 9 | D4: Week 01 | G4: HEALTHY FOOD | H4: 0 | I4: REV-FOOD | J4: Revenue Food | K4: 0 | L4: 0 | M4: 1 | N4: 0 | O4: 114.75 | R4: 114.75 | V4: Sold | W4: FOOD | X4: FOOD | Y4: 0
A5: 4 | B5: 45902 | C5: 9 | D5: Week 01 | G5: HEALTHY FOOD | H5: 0 | I5: REV-NON ALCOHOL | J5: Revenue Non Alcohol | K5: 0 | L5: 0 | M5: 1 | N5: 0 | O5: 42 | R5: 42 | V5: Sold | W5: BEVERAGE NON-ALOCOHOL | X5: BEVERAGE NON-ALOCOHOL | Y5: 0
A6: 5 | B6: 45903 | C6: 9 | D6: Week 01 | G6: HEALTHY FOOD | H6: 0 | I6: REV-FOOD | J6: Revenue Food | K6: 0 | L6: 0 | M6: 1 | N6: 0 | O6: 74.37 | R6: 74.37 | V6: Sold | W6: FOOD | X6: FOOD | Y6: 0
A7: 6 | B7: 45903 | C7: 9 | D7: Week 01 | G7: HEALTHY FOOD | H7: 0 | I7: REV-NON ALCOHOL | J7: Revenue Non Alcohol | K7: 0 | L7: 0 | M7: 1 | N7: 0 | O7: 57.07 | R7: 57.07 | V7: Sold | W7: BEVERAGE NON-ALOCOHOL | X7: BEVERAGE NON-ALOCOHOL | Y7: 0
A8: 7 | G8: HEALTHY FOOD | H8: 0 | I8: REV-FOOD | J8: Revenue Food | K8: 0 | L8: 0 | M8: 1 | N8: 0 | R8: 0 | V8: Sold | W8: FOOD | X8: FOOD | Y8: 0
A9: 8 | G9: HEALTHY FOOD | H9: 0 | I9: REV-NON ALCOHOL | J9: Revenue Non Alcohol | K9: 0 | L9: 0 | M9: 1 | N9: 0 | R9: 0 | V9: Sold | W9: BEVERAGE NON-ALOCOHOL | X9: BEVERAGE NON-ALOCOHOL | Y9: 0
A10: 9 | G10: HEALTHY FOOD | H10: 0 | I10: REV-FOOD | J10: Revenue Food | K10: 0 | L10: 0 | M10: 1 | N10: 0 | R10: 0 | V10: Sold | W10: FOOD | X10: FOOD | Y10: 0
A11: 10 | G11: HEALTHY FOOD | H11: 0 | I11: REV-NON ALCOHOL | J11: Revenue Non Alcohol | K11: 0 | L11: 0 | M11: 1 | N11: 0 | R11: 0 | V11: Sold | W11: BEVERAGE NON-ALOCOHOL | X11: BEVERAGE NON-ALOCOHOL | Y11: 0
A12: 11 | G12: HEALTHY FOOD | H12: 0 | I12: REV-FOOD | J12: Revenue Food | K12: 0 | L12: 0 | M12: 1 | N12: 0 | R12: 0 | V12: Sold | W12: FOOD | X12: FOOD | Y12: 0
A13: 12 | G13: HEALTHY FOOD | H13: 0 | I13: REV-NON ALCOHOL | J13: Revenue Non Alcohol | K13: 0 | L13: 0 | M13: 1 | N13: 0 | R13: 0 | V13: Sold | W13: BEVERAGE NON-ALOCOHOL | X13: BEVERAGE NON-ALOCOHOL | Y13: 0
A14: 13 | G14: HEALTHY FOOD | H14: 0 | I14: REV-FOOD | J14: Revenue Food | K14: 0 | L14: 0 | M14: 1 | N14: 0 | R14: 0 | V14: Sold | W14: FOOD | X14: FOOD | Y14: 0
A15: 14 | G15: HEALTHY FOOD | H15: 0 | I15: REV-NON ALCOHOL | J15: Revenue Non Alcohol | K15: 0 | L15: 0 | M15: 1 | N15: 0 | R15: 0 | V15: Sold | W15: BEVERAGE NON-ALOCOHOL | X15: BEVERAGE NON-ALOCOHOL | Y15: 0
A16: 15 | G16: HEALTHY FOOD | H16: 0 | I16: REV-FOOD | J16: Revenue Food | K16: 0 | L16: 0 | M16: 1 | N16: 0 | R16: 0 | V16: Sold | W16: FOOD | X16: FOOD | Y16: 0
A17: 16 | G17: HEALTHY FOOD | H17: 0 | I17: REV-NON ALCOHOL | J17: Revenue Non Alcohol | K17: 0 | L17: 0 | M17: 1 | N17: 0 | R17: 0 | V17: Sold | W17: BEVERAGE NON-ALOCOHOL | X17: BEVERAGE NON-ALOCOHOL | Y17: 0
A18: 17 | G18: HEALTHY FOOD | H18: 0 | I18: REV-FOOD | J18: Revenue Food | K18: 0 | L18: 0 | M18: 1 | N18: 0 | R18: 0 | V18: Sold | W18: FOOD | X18: FOOD | Y18: 0
A19: 18 | G19: HEALTHY FOOD | H19: 0 | I19: REV-NON ALCOHOL | J19: Revenue Non Alcohol | K19: 0 | L19: 0 | M19: 1 | N19: 0 | R19: 0 | V19: Sold | W19: BEVERAGE NON-ALOCOHOL | X19: BEVERAGE NON-ALOCOHOL | Y19: 0
... A61: 60 | G61: HEALTHY FOOD | H61: 0 | I61: REV-NON ALCOHOL | J61: Revenue Non Alcohol | K61: 0 | L61: 0 | M61: 1 | N61: 0 | R61: 0 | V61: Sold | W61: BEVERAGE NON-ALOCOHOL | X61: BEVERAGE NON-ALOCOHOL | Y61: 0
A62: 61 | G62: HEALTHY FOOD | H62: 0 | I62: REV-FOOD | J62: Revenue Food | K62: 0 | L62: 0 | M62: 1 | N62: 0 | R62: 0 | W62: FOOD | X62: FOOD | Y62: 0
A63: 62 | G63: HEALTHY FOOD | H63: 0 | I63: REV-NON ALCOHOL | J63: Revenue Non Alcohol | K63: 0 | L63: 0 | M63: 1 | N63: 0 | R63: 0 | W63: BEVERAGE NON-ALOCOHOL | X63: BEVERAGE NON-ALOCOHOL | Y63: 0
A64: 1 | B64: 45901 | C64: 9 | D64: Week 01 | E64: PO30955 | F64: DN-010901 | G64: E-MART24 BKK1 | H64: F0103010009 | I64: CSW-0001 | J64: Tuna & Egg Sandwich | K64: 1BOX*2PCS | L64: BOX | M64: 2 | O64: 1.5 | R64: 3 | V64: Sold | W64: FOOD | X64: Sandwich | Y64: PO309551
A65: 2 | B65: 45901 | C65: 9 | D65: Week 01 | E65: PO30955 | F65: DN-010901 | G65: E-MART24 BKK1 | H65: F0103010010 | I65: CSW-0002 | J65: Ham & Corn Sandwich | K65: 1BOX*2PCS | L65: BOX | M65: 2 | O65: 1.5 | R65: 3 | V65: Sold | W65: FOOD | X65: Sandwich | Y65: PO309552
A66: 3 | B66: 45901 | C66: 9 | D66: Week 01 | E66: PO30955 | F66: DN-010901 | G66: E-MART24 BKK1 | H66: F0103010011 | I66: CSW-0003 | J66: Sausage & Freid Egg Sandwich | K66: 1BOX*2PCS | L66: BOX | M66: 2 | O66: 1.5 | R66: 3 | W66: FOOD | X66: Sandwich | Y66: PO309553
A67: 4 | B67: 45901 | C67: 9 | D67: Week 01 | E67: PO30955 | F67: DN-010901 | G67: E-MART24 BKK1 | H67: F0103010012 | I67: CSW-0004 | J67: Chicken Sandwich | K67: 1BOX*2PCS | L67: BOX | M67: 2 | O67: 1.5 | R67: 3 | V67: Sold | W67: FOOD | X67: Sandwich | Y67: PO309554
A68: 5 | B68: 45901 | C68: 9 | D68: Week 01 | E68: PO30955 | F68: DN-010901 | G68: E-MART24 BKK1 | H68: F0101010017 | I68: KL-0001 | J68: Bulgogi Dosirak-KL-0001 | K68: 1BOX*1Portion | L68: BOX | M68: 2 | O68: 2.2 | R68: 4.4 | V68: Sold | W68: FOOD | X68: Korean Lunch Box | Y68: PO309555
A69: 6 | B69: 45901 | C69: 9 | D69: Week 01 | E69: PO30955 | F69: DN-010901 | G69: E-MART24 BKK1 | H69: F0101010015 | I69: KL-0003 | J69: Japchae Dakgangjeong Dosirak-KL-0003 | K69: 1BOX*1Portion | L69: BOX | M69: 2 | O69: 2.6 | R69: 5.2 | V69: Sold | W69: FOOD | X69: Korean Lunch Box | Y69: PO309556
A70: 7 | B70: 45901 | C70: 9 | D70: Week 01 | E70: PO30955 | F70: DN-010901 | G70: E-MART24 BKK1 | H70: F0101010016 | I70: KL-0002 | J70: Stir Fried Spicy Pork Dosirak-KL-0002 | K70: 1BOX*1Portion | L70: BOX | M70: 2 | O70: 2.38 | R70: 4.76 | V70: Sold | W70: FOOD | X70: Korean Lunch Box | Y70: PO309557
A71: 8 | B71: 45901 | C71: 9 | D71: Week 01 | E71: PO30955 | F71: DN-010901 | G71: E-MART24 BKK1 | H71: F0103010013 | I71: SS-0002 | J71: Maki Crab & Chicken Egg | K71: 1BOX*6PCS | L71: Box | M71: 2 | O71: 1.21 | R71: 2.42 | V71: Sold | W71: FOOD | X71: Sushi | Y71: PO309558
A72: 9 | B72: 45901 | C72: 9 | D72: Week 01 | E72: PO30955 | F72: DN-010901 | G72: E-MART24 BKK1 | H72: F0103010014 | I72: SS-0004 | J72: Maki Cali & Tuna Roll | K72: 1BOX*3PCS | L72: Box | M72: 2 | O72: 1.21 | R72: 2.42 | V72: Sold | W72: FOOD | X72: Sushi | Y72: PO309559
A73: 10 | B73: 45901 | C73: 9 | D73: Week 01 | E73: PO30959 | F73: DN-010902 | G73: E-MART24 BKK1 | H73: 900029 | I73: HF-0001 | J73: BEEF LOK LAK WITH RICE (បាយ​ ឡុកឡាក់សាច់គោ) | K73: 1BOX*1Portion | L73: BOX | M73: 2 | O73: 1.668 | R73: 3.336 | V73: Sold | W73: FOOD | X73: Khmer Food | Y73: PO309591
A74: 11 | B74: 45901 | C74: 9 | D74: Week 01 | E74: PO30959 | F74: DN-010902 | G74: E-MART24 BKK1 | H74: 900027 | I74: HF-0002 | J74: STIR FRIED MINCED PORK HOT BASIL WITH RICE (បាយ សាច់ជ្រូកចិញ្រ្ចាំឆាម្រះព្រៅ) | K74: 1BOX*1Portion | L74: BOX | M74: 2 | O74: 1.2024 | R74: 2.4048 | V74: Sold | W74: FOOD | X74: Khmer Food | Y74: PO309592
A75: 12 | B75: 45901 | C75: 9 | D75: Week 01 | E75: PO30959 | F75: DN-010902 | G75: E-MART24 BKK1 | H75: 900031 | I75: HF-0008 | J75: ROASTED DUCK WITH RICE (បាយ ទាខ្វៃ) | K75: 1BOX*1Portion | L75: BOX | M75: 2 | O75: 1.4784 | R75: 2.9568 | V75: Sold | W75: FOOD | X75: Khmer Food | Y75: PO309593
A76: 13 | B76: 45901 | C76: 9 | D76: Week 01 | E76: PO30959 | F76: DN-010902 | G76: E-MART24 BKK1 | H76: 900032 | I76: HF-0004 | J76: STIR FRIED MINCED CHICKEN HOT BASIL WITH RICE (បាយ​ សាច់មាន់ចិញ្រ្ចាំឆាម្រះព្រៅ) | K76: 1BOX*1Portion | L76: BOX | M76: 2 | O76: 1.2984 | R76: 2.5968 | V76: Sold | W76: FOOD | X76: Khmer Food | Y76: PO309594
A77: 14 | B77: 45901 | C77: 9 | D77: Week 01 | E77: PO30959 | F77: DN-010902 | G77: E-MART24 BKK1 | H77: 900028 | I77: HF-0005 | J77: STIR FRIED MINCED PORK EGGPLANT WITH RICE (បាយ សាច់ជ្រូកចិញ្ច្រាំឆាត្រប់វែង) | K77: 1BOX*1Portion | L77: BOX | M77: 2 | O77: 1.0104 | R77: 2.0208 | V77: Sold | W77: FOOD | X77: Khmer Food | Y77: PO309595
A78: 15 | B78: 45901 | C78: 9 | D78: Week 01 | E78: PO30959 | F78: DN-010902 | G78: E-MART24 BKK1 | H78: 900038 | I78: HF-0010 | J78: ROATED PORK BELLY WITH RICE (បាយ សាច់ជ្រូក៣ជាន់) | K78: 1BOX*1Portion | L78: BOX | M78: 2 | O78: 1.092 | R78: 2.184 | V78: Sold | W78: FOOD | X78: Khmer Food | Y78: PO309596
... A82: 19 | B82: 45901 | C82: 9 | D82: Week 01 | E82: PO30959 | F82: DN-010902 | G82: E-MART24 BKK1 | H82: F0101010018 | I82: HF-0027 | J82: Salmon Fried Rice (បា​យឆា សាលម៉ុន) | K82: 1BOX*1Portion | L82: BOX | M82: 1 | O82: 1.6 | R82: 1.6 | V82: Sold | W82: FOOD | X82: Khmer Food | Y82: PO3095910
A83: 20 | B83: 45901 | C83: 9 | D83: Week 01 | E83: PO30959 | F83: DN-010902 | G83: E-MART24 BKK1 | H83: F0101010019 | I83: HF-0028 | J83: Crab Fried Rice (បាយឆា ក្ដាម) | K83: 1BOX*1Portion | L83: BOX | M83: 1 | O83: 1.6 | R83: 1.6 | W83: FOOD | X83: Khmer Food | Y83: PO3095911
A84: 21 | B84: 45901 | C84: 9 | D84: Week 01 | E84: PO30959 | F84: DN-010902 | G84: E-MART24 BKK1 | H84: 900152 | I84: V-0102 | J84: Lettuce Iceberg | K84: KG | L84: KG | M84: 1 | O84: 3.12 | R84: 3.12 | W84: FOOD | X84: Fruits & Veggies / Veggies | Y84: PO3095912
A85: 22 | B85: 45901 | C85: 9 | D85: Week 01 | E85: PO30959 | F85: DN-010902 | G85: E-MART24 BKK1 | H85: 900153 | I85: V-0038 | J85: White Radish (Daikon) | K85: KG | L85: KG | M85: 1 | O85: 0.84 | R85: 0.84 | W85: FOOD | X85: Fruits & Veggies / Veggies | Y85: PO3095913
A86: 23 | B86: 45901 | C86: 9 | D86: Week 01 | E86: PO30959 | F86: DN-010902 | G86: E-MART24 BKK1 | H86: 900268 | I86: I-0001 | J86: White Sugar (Bag*50Kg) | K86: 1BAG*50KG | L86: KG | M86: 50 | O86: 0.96 | R86: 48 | W86: FOOD | X86: Ingredients | Y86: PO3095914
A87: 24 | B87: 45901 | C87: 9 | D87: Week 01 | E87: PO30959 | F87: DN-010902 | G87: E-MART24 BKK1 | H87: 900295 | I87: P-0033 | J87: Kelly Cling Wrap (ហ្វីមរុំម្ហូប) | K87: 1ROLL*600M*45CM | L87: ROLL | M87: 2 | O87: 21.6 | R87: 43.2 | W87: NON-FOOD | X87: NON-FOOD | Y87: PO3095915
A88: 25 | B88: 45901 | C88: 9 | D88: Week 01 | E88: PO30959 | F88: DN-010902 | G88: E-MART24 BKK1 | H88: 900296 | I88: P-0041 | J88: Baking Paper | K88: 1ROLL*600M*45CM | L88: ROLL | M88: 1 | O88: 22.8 | R88: 22.8 | W88: NON-FOOD | X88: NON-FOOD | Y88: PO3095916
A89: 26 | B89: 45901 | C89: 9 | D89: Week 01 | E89: PO30959 | F89: DN-010902 | G89: E-MART24 BKK1 | H89: 900271 | I89: I-0212 | J89: Best Food Mayonniase 3.5KG | K89: 1CTN*4TUB*3.5KG | L89: TUB | M89: 2 | O89: 22.8 | R89: 45.6 | W89: FOOD | X89: Ingredients | Y89: PO3095917
A90: 27 | B90: 45901 | C90: 9 | D90: Week 01 | E90: PO30956 | F90: DN-010903 | G90: E-MART24 BKK3 | H90: F0103010009 | I90: CSW-0001 | J90: Tuna & Egg Sandwich | K90: 1BOX*2PCS | L90: BOX | M90: 1 | O90: 1.5 | R90: 1.5 | W90: FOOD | X90: Sandwich | Y90: PO309561
A91: 28 | B91: 45901 | C91: 9 | D91: Week 01 | E91: PO30956 | F91: DN-010903 | G91: E-MART24 BKK3 | H91: F0103010010 | I91: CSW-0002 | J91: Ham & Corn Sandwich | K91: 1BOX*2PCS | L91: BOX | M91: 1 | O91: 1.5 | R91: 1.5 | W91: FOOD | X91: Sandwich | Y91: PO309562
A92: 29 | B92: 45901 | C92: 9 | D92: Week 01 | E92: PO30956 | F92: DN-010903 | G92: E-MART24 BKK3 | H92: F0103010011 | I92: CSW-0003 | J92: Sausage & Freid Egg Sandwich | K92: 1BOX*2PCS | L92: BOX | M92: 1 | O92: 1.5 | R92: 1.5 | W92: FOOD | X92: Sandwich | Y92: PO309563
A93: 30 | B93: 45901 | C93: 9 | D93: Week 01 | E93: PO30956 | F93: DN-010903 | G93: E-MART24 BKK3 | H93: F0103010012 | I93: CSW-0004 | J93: Chicken Sandwich | K93: 1BOX*2PCS | L93: BOX | M93: 1 | O93: 1.5 | R93: 1.5 | W93: FOOD | X93: Sandwich | Y93: PO309564
A94: 31 | B94: 45901 | C94: 9 | D94: Week 01 | E94: PO30956 | F94: DN-010903 | G94: E-MART24 BKK3 | H94: F0101010017 | I94: KL-0001 | J94: Bulgogi Dosirak-KL-0001 | K94: 1BOX*1Portion | L94: BOX | M94: 1 | O94: 2.2 | R94: 2.2 | W94: FOOD | X94: Korean Lunch Box | Y94: PO309565
... A188: 125 | B188: 45901 | C188: 9 | D188: Week 01 | E188: PO30964 | F188: DN-010912 | G188: E-MART ANLONG KNGAN (TK) | H188: 900278 | I188: C-0023 | J188: Latex Glove (Top) ស្រោមដៃពេទ្យ | K188: 1PKT*100PCS | L188: PKT | M188: 10 | O188: 5.16 | R188: 51.6 | W188: NON-FOOD | X188: NON-FOOD | Y188: PO3096415
A189: 126 | B189: 45901 | C189: 9 | D189: Week 01 | E189: PO30964 | F189: DN-010912 | G189: E-MART ANLONG KNGAN (TK) | H189: 900269 | I189: I-0017 | J189: Cooking Oil 18LTR (ប្រេងឆា) | K189: TIN*18LTR | L189: TIN | M189: 5 | N189: 36 | O189: 36 | R189: 180 | W189: FOOD | X189: Ingredients | Y189: PO3096416
A190: 127 | B190: 45901 | C190: 9 | D190: Week 01 | E190: PO30964 | F190: DN-010912 | G190: E-MART ANLONG KNGAN (TK) | H190: 900271 | I190: I-0212 | J190: Best Food Mayonniase 3.5KG | K190: 1CTN*4TUB*3.5KG | L190: TUB | M190: 2 | O190: 22.8 | R190: 45.6 | W190: FOOD | X190: Ingredients | Y190: PO3096417
A191: 128 | B191: 45901 | C191: 9 | D191: Week 01 | E191: PO30966 | F191: DN-010913 | G191: E-MART24 BKK1 | H191: C0101010536 | I191: KF-0026 | J191: Semi Chicken Sweet & Spicy Korean Sauce | K191: 1PKT*1KG | L191: KG | M191: 1 | O191: 6.924 | R191: 6.924 | W191: FOOD | X191: Semi-Product | Y191: PO309661
A192: 129 | B192: 45901 | C192: 9 | D192: Week 01 | E192: PO30967 | F192: DN-010914 | G192: E-MART24 BKK1 | H192: C0101010534 | I192: RF-0001 | J192: Raw Frozen Chicken Drumstick | K192: 1PKT*1KG | L192: KG | M192: 3 | O192: 4.74 | R192: 14.22 | W192: FOOD | X192: Semi-Product | Y192: PO309671
A193: 130 | B193: 45901 | C193: 9 | D193: Week 01 | E193: PO30967 | F193: DN-010914 | G193: E-MART24 BKK1 | H193: C0101010535 | I193: RF-0002 | J193: Raw Frozen Chicken Middle Wing | K193: 1PKT*1KG | L193: KG | M193: 2 | O193: 7.38 | R193: 14.76 | W193: FOOD | X193: Semi-Product | Y193: PO309672
A194: 131 | B194: 45901 | C194: 9 | D194: Week 01 | E194: PO30967 | F194: DN-010914 | G194: E-MART24 BKK1 | H194: 900114 | I194: KF-0001 | J194: Raw Bulgogi Pork | K194: 1PKT*1KG | L194: PKT | M194: 3 | O194: 5.76 | R194: 17.28 | W194: FOOD | X194: Semi-Product | Y194: PO309673
A195: 132 | B195: 45901 | C195: 9 | D195: Week 01 | E195: PO30967 | F195: DN-010914 | G195: E-MART24 BKK1 | H195: 900117 | I195: KF-0004 | J195: Raw Deep Fried Chicken | K195: 1PKT*1KG | L195: PKT | M195: 5 | N195: 6 | O195: 6 | R195: 30 | W195: FOOD | X195: Semi-Product | Y195: PO309674
A196: 133 | B196: 45901 | C196: 9 | D196: Week 01 | E196: PO30967 | F196: DN-010914 | G196: E-MART24 BKK1 | H196: 900116 | I196: KF-0003 | J196: Raw Fried Japchae | K196: 1PKT*1KG | L196: PKT | M196: 1 | O196: 3.6 | R196: 3.6 | W196: FOOD | X196: Semi-Product | Y196: PO309675
A197: 134 | B197: 45901 | C197: 9 | D197: Week 01 | E197: PO30967 | F197: DN-010914 | G197: E-MART24 BKK1 | H197: 900121 | I197: KF-0008 | J197: Raw Sausage Corn Dog | K197: 1PKT*6PCS*100G | L197: PKT | M197: 10 | O197: 3.67 | R197: 36.7 | W197: FOOD | X197: Semi-Product | Y197: PO309676
A198: 135 | B198: 45901 | C198: 9 | D198: Week 01 | E198: PO30967 | F198: DN-010914 | G198: E-MART24 BKK1 | H198: 900125 | I198: KF-0012 | J198: Raw Spicy Mayo Sauce | K198: 1PKT*1KG | L198: PKT | M198: 1 | O198: 7.8 | R198: 7.8 | W198: FOOD | X198: Semi-Product | Y198: PO309677
A199: 136 | B199: 45901 | C199: 9 | D199: Week 01 | E199: PO30967 | F199: DN-010914 | G199: E-MART24 BKK1 | H199: 900122 | I199: KF-0009 | J199: Raw Sriracha Mayo Sauce | K199: 1PKT*1KG | L199: PKT | M199: 1 | O199: 7.2 | R199: 7.2 | W199: FOOD | X199: Semi-Product | Y199: PO309678
A200: 137 | B200: 45901 | C200: 9 | D200: Week 01 | E200: PO30967 | F200: DN-010914 | G200: E-MART24 BKK1 | H200: 900118 | I200: KF-0005 | J200: Raw Stir Fried Kimchi | K200: 1PKT*1KG | L200: PKT | M200: 3 | O200: 5.76 | R200: 17.28 | W200: FOOD | X200: Semi-Product | Y200: PO309679
A201: 138 | B201: 45901 | C201: 9 | D201: Week 01 | E201: PO30967 | F201: DN-010914 | G201: E-MART24 BKK1 | H201: 900123 | I201: KF-0010 | J201: Raw Sweet & Spicy Sauce (Yangyum Sauce) | K201: 1PKT*1KG | L201: PKT | M201: 1 | O201: 5.16 | R201: 5.16 | W201: FOOD | X201: Semi-Product | Y201: PO3096710
A202: 139 | B202: 45901 | C202: 9 | D202: Week 01 | E202: PO30967 | F202: DN-010914 | G202: E-MART24 BKK1 | H202: 900126 | I202: KF-0013 | J202: Raw Teriyaki Sauce | K202: 1PKT*1KG | L202: PKT | M202: 1 | O202: 9.72 | R202: 9.72 | W202: FOOD | X202: Semi-Product | Y202: PO3096711
A203: 140 | B203: 45901 | C203: 9 | D203: Week 01 | E203: PO30967 | F203: DN-010914 | G203: E-MART24 BKK1 | H203: C0101010537 | I203: KF-0027 | J203: Fried Chicken Flour | K203: 1PKT*1KG | L203: KG | M203: 1 | O203: 7.455 | R203: 7.455 | W203: FOOD | X203: Semi-Product | Y203: PO3096712
A204: 141 | B204: 45901 | C204: 9 | D204: Week 01 | E204: PO30967 | F204: DN-010914 | G204: E-MART24 BKK1 | H204: 8852043005014 | I204: O-0164 | J204: SMOKED COCKTAIL SAUSAGE DELUXE 1KG | K204: 1CTN*11PKT*1KG | L204: PKT | M204: 1 | O204: 6.96 | R204: 6.96 | W204: FOOD | X204: Froozen Food | Y204: PO3096713
A205: 142 | B205: 45901 | C205: 9 | D205: Week 01 | E205: PO30967 | F205: DN-010914 | G205: E-MART24 BKK1 | H205: 0 | I205: O-0163 | J205: JUMBO GOLD SAUSAGE 16PCS 1KG | K205: 1CTN*11PKT*1KG | L205: PKT | M205: 1 | O205: 4.644 | R205: 4.644 | W205: FOOD | X205: Froozen Food | Y205: PO3096714
A206: 143 | B206: 45901 | C206: 9 | D206: Week 01 | E206: PO30968 | F206: DN-010915 | G206: E-MART24 BKK3 | H206: C0101010534 | I206: RF-0001 | J206: Raw Frozen Chicken Drumstick | K206: 1PKT*1KG | L206: KG | M206: 1 | O206: 4.74 | R206: 4.74 | W206: FOOD | X206: Semi-Product | Y206: PO309681
A207: 144 | B207: 45901 | C207: 9 | D207: Week 01 | E207: PO30968 | F207: DN-010915 | G207: E-MART24 BKK3 | H207: 900114 | I207: KF-0001 | J207: Raw Bulgogi Pork | K207: 1PKT*1KG | L207: PKT | M207: 3 | O207: 5.76 | R207: 17.28 | W207: FOOD | X207: Semi-Product | Y207: PO309682
A208: 145 | B208: 45901 | C208: 9 | D208: Week 01 | E208: PO30968 | F208: DN-010915 | G208: E-MART24 BKK3 | H208: 900117 | I208: KF-0004 | J208: Raw Deep Fried Chicken | K208: 1PKT*1KG | L208: PKT | M208: 10 | N208: 6 | O208: 6 | R208: 60 | W208: FOOD | X208: Semi-Product | Y208: PO309683
A209: 146 | B209: 45901 | C209: 9 | D209: Week 01 | E209: PO30968 | F209: DN-010915 | G209: E-MART24 BKK3 | H209: 900115 | I209: KF-0002 | J209: Raw Stir Fried Spicy Pork | K209: 1PKT*1KG | L209: PKT | M209: 3 | N209: 6 | O209: 6 | R209: 18 | W209: FOOD | X209: Semi-Product | Y209: PO309684
A210: 147 | B210: 45901 | C210: 9 | D210: Week 01 | E210: PO30968 | F210: DN-010915 | G210: E-MART24 BKK3 | H210: C0101010537 | I210: KF-0027 | J210: Fried Chicken Flour | K210: 1PKT*1KG | L210: KG | M210: 2 | O210: 7.455 | R210: 14.91 | W210: FOOD | X210: Semi-Product | Y210: PO309685
A211: 148 | B211: 45901 | C211: 9 | D211: Week 01 | E211: PO30969 | F211: DN-010916 | G211: E-MART24 CAMKO | H211: C0101010536 | I211: KF-0026 | J211: Semi Chicken Sweet & Spicy Korean Sauce | K211: 1PKT*1KG | L211: KG | M211: 10 | O211: 6.924 | R211: 69.24 | W211: FOOD | X211: Semi-Product | Y211: PO309691
A212: 149 | B212: 45901 | C212: 9 | D212: Week 01 | E212: PO30970 | F212: DN-010917 | G212: E-MART24 CAMKO | H212: C0101010534 | I212: RF-0001 | J212: Raw Frozen Chicken Drumstick | K212: 1PKT*1KG | L212: KG | M212: 5 | O212: 4.74 | R212: 23.7 | W212: FOOD | X212: Semi-Product | Y212: PO309701
A213: 150 | B213: 45901 | C213: 9 | D213: Week 01 | E213: PO30970 | F213: DN-010917 | G213: E-MART24 CAMKO | H213: C0101010535 | I213: RF-0002 | J213: Raw Frozen Chicken Middle Wing | K213: 1PKT*1KG | L213: KG | M213: 4 | O213: 7.38 | R213: 29.52 | W213: FOOD | X213: Semi-Product | Y213: PO309702
A214: 151 | B214: 45901 | C214: 9 | D214: Week 01 | E214: PO30970 | F214: DN-010917 | G214: E-MART24 CAMKO | H214: 900114 | I214: KF-0001 | J214: Raw Bulgogi Pork | K214: 1PKT*1KG | L214: PKT | M214: 15 | O214: 5.76 | R214: 86.4 | W214: FOOD | X214: Semi-Product | Y214: PO309703
A215: 152 | B215: 45901 | C215: 9 | D215: Week 01 | E215: PO30970 | F215: DN-010917 | G215: E-MART24 CAMKO | H215: 900120 | I215: KF-0007 | J215: Raw Cheese Corn Dog | K215: 1PKT*6PCS*100G | L215: PKT | M215: 5 | O215: 4.9 | R215: 24.5 | W215: FOOD | X215: Semi-Product | Y215: PO309704
A216: 153 | B216: 45901 | C216: 9 | D216: Week 01 | E216: PO30970 | F216: DN-010917 | G216: E-MART24 CAMKO | H216: 900117 | I216: KF-0004 | J216: Raw Deep Fried Chicken | K216: 1PKT*1KG | L216: PKT | M216: 7 | N216: 6 | O216: 6 | R216: 42 | W216: FOOD | X216: Semi-Product | Y216: PO309705
A217: 154 | B217: 45901 | C217: 9 | D217: Week 01 | E217: PO30970 | F217: DN-010917 | G217: E-MART24 CAMKO | H217: 900116 | I217: KF-0003 | J217: Raw Fried Japchae | K217: 1PKT*1KG | L217: PKT | M217: 5 | O217: 3.6 | R217: 18 | W217: FOOD | X217: Semi-Product | Y217: PO309706
A218: 155 | B218: 45901 | C218: 9 | D218: Week 01 | E218: PO30970 | F218: DN-010917 | G218: E-MART24 CAMKO | H218: 900121 | I218: KF-0008 | J218: Raw Sausage Corn Dog | K218: 1PKT*6PCS*100G | L218: PKT | M218: 4 | O218: 3.67 | R218: 14.68 | W218: FOOD | X218: Semi-Product | Y218: PO309707
A219: 156 | B219: 45901 | C219: 9 | D219: Week 01 | E219: PO30970 | F219: DN-010917 | G219: E-MART24 CAMKO | H219: 900125 | I219: KF-0012 | J219: Raw Spicy Mayo Sauce | K219: 1PKT*1KG | L219: PKT | M219: 10 | O219: 7.8 | R219: 78 | W219: FOOD | X219: Semi-Product | Y219: PO309708
A220: 157 | B220: 45901 | C220: 9 | D220: Week 01 | E220: PO30970 | F220: DN-010917 | G220: E-MART24 CAMKO | H220: 900118 | I220: KF-0005 | J220: Raw Stir Fried Kimchi | K220: 1PKT*1KG | L220: PKT | M220: 10 | O220: 5.76 | R220: 57.6 | W220: FOOD | X220: Semi-Product | Y220: PO309709
A221: 158 | B221: 45901 | C221: 9 | D221: Week 01 | E221: PO30970 | F221: DN-010917 | G221: E-MART24 CAMKO | H221: 900115 | I221: KF-0002 | J221: Raw Stir Fried Spicy Pork | K221: 1PKT*1KG | L221: PKT | M221: 10 | N221: 6 | O221: 6 | R221: 60 | W221: FOOD | X221: Semi-Product | Y221: PO3097010
A222: 159 | B222: 45901 | C222: 9 | D222: Week 01 | E222: PO30970 | F222: DN-010917 | G222: E-MART24 CAMKO | H222: 900126 | I222: KF-0013 | J222: Raw Teriyaki Sauce | K222: 1PKT*1KG | L222: PKT | M222: 2 | O222: 9.72 | R222: 19.44 | W222: FOOD | X222: Semi-Product | Y222: PO3097011
A223: 160 | B223: 45901 | C223: 9 | D223: Week 01 | E223: PO30970 | F223: DN-010917 | G223: E-MART24 CAMKO | H223: 8852043005014 | I223: O-0164 | J223: SMOKED COCKTAIL SAUSAGE DELUXE 1KG | K223: 1CTN*11PKT*1KG | L223: PKT | M223: 20 | O223: 6.96 | R223: 139.2 | W223: FOOD | X223: Froozen Food | Y223: PO3097012
A224: 161 | B224: 45901 | C224: 9 | D224: Week 01 | E224: PO30970 | F224: DN-010917 | G224: E-MART24 CAMKO | H224: 0 | I224: O-0163 | J224: JUMBO GOLD SAUSAGE 16PCS 1KG | K224: 1CTN*11PKT*1KG | L224: PKT | M224: 40 | O224: 4.644 | R224: 185.76 | W224: FOOD | X224: Froozen Food | Y224: PO3097013
A225: 162 | B225: 45901 | C225: 9 | D225: Week 01 | E225: PO30970 | F225: DN-010917 | G225: E-MART24 CAMKO | H225: 0 | I225: M-0099 | J225: Smoked Bacon 1kg | K225: 1PKT*1KG | L225: KG | M225: 5 | O225: 15.6 | R225: 78 | W225: FOOD | X225: Froozen Food | Y225: PO3097014
A226: 163 | B226: 45901 | C226: 9 | D226: Week 01 | E226: PO30971 | F226: DN-010918 | G226: E-MART24 CKD | H226: C0101010534 | I226: RF-0001 | J226: Raw Frozen Chicken Drumstick | K226: 1PKT*1KG | L226: KG | M226: 5 | O226: 4.74 | R226: 23.7 | W226: FOOD | X226: Semi-Product | Y226: PO309711
A227: 164 | B227: 45901 | C227: 9 | D227: Week 01 | E227: PO30971 | F227: DN-010918 | G227: E-MART24 CKD | H227: 900114 | I227: KF-0001 | J227: Raw Bulgogi Pork | K227: 1PKT*1KG | L227: PKT | M227: 3 | O227: 5.76 | R227: 17.28 | W227: FOOD | X227: Semi-Product | Y227: PO309712
A228: 165 | B228: 45901 | C228: 9 | D228: Week 01 | E228: PO30971 | F228: DN-010918 | G228: E-MART24 CKD | H228: 900120 | I228: KF-0007 | J228: Raw Cheese Corn Dog | K228: 1PKT*6PCS*100G | L228: PKT | M228: 3 | O228: 4.9 | R228: 14.7 | W228: FOOD | X228: Semi-Product | Y228: PO309713
A229: 166 | B229: 45901 | C229: 9 | D229: Week 01 | E229: PO30971 | F229: DN-010918 | G229: E-MART24 CKD | H229: 900117 | I229: KF-0004 | J229: Raw Deep Fried Chicken | K229: 1PKT*1KG | L229: PKT | M229: 10 | N229: 6 | O229: 6 | R229: 60 | W229: FOOD | X229: Semi-Product | Y229: PO309714
A230: 167 | B230: 45901 | C230: 9 | D230: Week 01 | E230: PO30971 | F230: DN-010918 | G230: E-MART24 CKD | H230: 900122 | I230: KF-0009 | J230: Raw Sriracha Mayo Sauce | K230: 1PKT*1KG | L230: PKT | M230: 2 | O230: 7.2 | R230: 14.4 | W230: FOOD | X230: Semi-Product | Y230: PO309715
A231: 168 | B231: 45901 | C231: 9 | D231: Week 01 | E231: PO30971 | F231: DN-010918 | G231: E-MART24 CKD | H231: 8852043005014 | I231: O-0164 | J231: SMOKED COCKTAIL SAUSAGE DELUXE 1KG | K231: 1CTN*11PKT*1KG | L231: PKT | M231: 10 | O231: 6.96 | R231: 69.6 | W231: FOOD | X231: Froozen Food | Y231: PO309716
A232: 169 | B232: 45901 | C232: 9 | D232: Week 01 | E232: PO30971 | F232: DN-010918 | G232: E-MART24 CKD | H232: 0 | I232: O-0163 | J232: JUMBO GOLD SAUSAGE 16PCS 1KG | K232: 1CTN*11PKT*1KG | L232: PKT | M232: 19 | O232: 4.644 | R232: 88.236 | W232: FOOD | X232: Froozen Food | Y232: PO309717
A233: 170 | B233: 45901 | C233: 9 | D233: Week 01 | E233: PO03977 | F233: DN-010919 | G233: E-MART ANLONG KNGAN (OLP) | H233: C0101010534 | I233: RF-0001 | J233: Raw Frozen Chicken Drumstick | K233: 1PKT*1KG | L233: KG | M233: 10 | O233: 4.74 | R233: 47.4 | W233: FOOD | X233: Semi-Product | Y233: PO039771
A234: 171 | B234: 45901 | C234: 9 | D234: Week 01 | E234: PO03977 | F234: DN-010919 | G234: E-MART ANLONG KNGAN (OLP) | H234: C0101010535 | I234: RF-0002 | J234: Raw Frozen Chicken Middle Wing | K234: 1PKT*1KG | L234: KG | M234: 10 | O234: 7.38 | R234: 73.8 | W234: FOOD | X234: Semi-Product | Y234: PO039772
A235: 172 | B235: 45901 | C235: 9 | D235: Week 01 | E235: PO03977 | F235: DN-010919 | G235: E-MART ANLONG KNGAN (OLP) | H235: 900120 | I235: KF-0007 | J235: Raw Cheese Corn Dog | K235: 1PKT*6PCS*100G | L235: PKT | M235: 20 | O235: 4.9 | R235: 98 | W235: FOOD | X235: Semi-Product | Y235: PO039773
A236: 173 | B236: 45901 | C236: 9 | D236: Week 01 | E236: PO03977 | F236: DN-010919 | G236: E-MART ANLONG KNGAN (OLP) | H236: 900117 | I236: KF-0004 | J236: Raw Deep Fried Chicken | K236: 1PKT*1KG | L236: PKT | M236: 30 | N236: 6 | O236: 6 | R236: 180 | W236: FOOD | X236: Semi-Product | Y236: PO039774
A237: 174 | B237: 45901 | C237: 9 | D237: Week 01 | E237: PO03977 | F237: DN-010919 | G237: E-MART ANLONG KNGAN (OLP) | H237: 900121 | I237: KF-0008 | J237: Raw Sausage Corn Dog | K237: 1PKT*6PCS*100G | L237: PKT | M237: 20 | O237: 3.67 | R237: 73.4 | W237: FOOD | X237: Semi-Product | Y237: PO039775
...

Sheet MASTER LIST
A1: Nº | B1: Item Code | C1: Barcode | D1: Item Name | E1: ITEM NAME in Khmer | F1: Supplier Name | G1: Category | H1: Sub Category | I1: UOM | J1: Packing Size | K1: Unit Cost | L1: Invoice Price | M1: Lead Times | N1: Par Stock | O1: NUB | P1: Nub2 | Q1: Name | R1: Data Search | S1: Master Name | U1: Date | W1: NUB | X1: Nub2 | Y1: Supplied Name | Z1: Data Search | AA1: Master Name | AC1: NUB | AD1: Nub2 | AE1: Location | AF1: Data Search | AG1: Master Name | AI1: Using Period | AJ1: Reason
A2: {=ROW(1:1)} -> 1 | B2: C-0022 | C2: 900277 | D2: Plastic Glove (ស្រោមដៃថង់) | F2: CENTRAL KITCHEN | G2: NON-FOOD | H2: NON-FOOD | I2: PKT | J2: PKT*100PCS | K2: 0.72 | M2: 1 | N2: 10 | O2: =IF(ISNUMBER(SEARCH('Data Entry'!$J$3,$Q2)),MAX($O$1:$O1)+1,0) -> 0 | P2: =IF(ISNUMBER(SEARCH('Data Entry'!$J$3,$Q2)),MAX($P$1:$P1)+1,0) -> 0 | Q2: =Table2[[#This Row],[Item Name ]] -> Plastic Glove (ស្រោមដៃថង់) | R2: =IFERROR(VLOOKUP(ROWS($R$2:$R2),Table2[[Nub2]:[Name]],2,0),"") -> Set Plastic Spoon & Fork (ឈុតស្លាបព្រា សម) | W2: =IF(ISNUMBER(SEARCH('Data Entry'!$J$3,$Y2)),MAX($W$1:$W1)+1,0) -> 0 | X2: =IF(ISNUMBER(SEARCH('Data Entry'!$J$3,$Y2)),MAX($X$1:$X1)+1,0) -> 0 | Y2: 168 Curtain Beauty | Z2: =IFERROR(VLOOKUP(ROWS($Z$2:$Z2),Table4[[Nub2]:[Supplied Name]],2,0),"") | AA2: =OFFSET($Z$2,,,COUNTIF($Z$2:$Z$25,"?*")) -> #REF! | AC2: =IF(ISNUMBER(SEARCH('Data Entry'!$J$3,$AE2)),MAX($AC$1:$AC1)+1,0) -> 0 | AD2: =IF(ISNUMBER(SEARCH('Data Entry'!$J$3,$AE2)),MAX($AD$1:$AD1)+1,0) -> 0 | AE2: Catering | AF2: =IFERROR(VLOOKUP(ROWS($Z$2:$Z2),Table5[[#All],[Nub2]:[Location ]],2,0),"") | AG2: =OFFSET($AF$2,,,COUNTIF($AF$2:$AF$25,"?*")) -> #REF! | AI2: 1 Day | AJ2: Expried
A3: {=ROW(2:2)} -> 2 | B3: C-0023 | C3: 900278 | D3: Latex Glove (Top) ស្រោមដៃពេទ្យ | F3: CENTRAL KITCHEN | G3: NON-FOOD | H3: NON-FOOD | I3: PKT | J3: 1PKT*100PCS | K3: 5.16 | M3: 1 | N3: 10 | O3: =IF(ISNUMBER(SEARCH('Data Entry'!$J$3,$Q3)),MAX($O$1:$O2)+1,0) -> 0 | P3: =IF(ISNUMBER(SEARCH('Data Entry'!$J$3,$Q3)),MAX($P$1:$P2)+1,0) -> 0 | Q3: =Table2[[#This Row],[Item Name ]] -> Latex Glove (Top) ស្រោមដៃពេទ្យ | R3: =IFERROR(VLOOKUP(ROWS($R$2:$R3),Table2[[Nub2]:[Name]],2,0),"") | W3: =IF(ISNUMBER(SEARCH('Data Entry'!$J$3,$Y3)),MAX($W$1:$W2)+1,0) -> 0 | X3: =IF(ISNUMBER(SEARCH('Data Entry'!$J$3,$Y3)),MAX($X$1:$X2)+1,0) -> 0 | Y3: 168 Curtain BeautyLOSS | Z3: =IFERROR(VLOOKUP(ROWS($Z$2:$Z3),Table4[[Nub2]:[Supplied Name]],2,0),"") | AA3: =OFFSET($Z$2,,,COUNTIF($Z$2:$Z$25,"?*")) -> #REF! | AC3: =IF(ISNUMBER(SEARCH('Data Entry'!$J$3,$AE3)),MAX($AC$1:$AC2)+1,0) -> 0 | AD3: =IF(ISNUMBER(SEARCH('Data Entry'!$J$3,$AE3)),MAX($AD$1:$AD2)+1,0) -> 0 | AE3: Central Bakery | AF3: =IFERROR(VLOOKUP(ROWS($Z$2:$Z3),Table5[[#All],[Nub2]:[Location ]],2,0),"") | AG3: =OFFSET($AF$2,,,COUNTIF($AF$2:$AF$25,"?*")) -> #REF! | AI3: 2 Day | AJ3: Nealy Exp
A4: {=ROW(3:3)} -> 3 | B4: DF-0001 | C4: 900136 | D4: Grined Pork Jerky (orginal) | F4: CENTRAL KITCHEN | G4: FOOD | H4: Dry Food | I4: PKT | J4: 1PKT*30G (6 Sliced) | K4: =6.57/10 -> 0.657 | M4: 1 | N4: 10 | O4: =IF(ISNUMBER(SEARCH('Data Entry'!$J$3,$Q4)),MAX($O$1:$O3)+1,0) -> 0 | P4: =IF(ISNUMBER(SEARCH('Data Entry'!$J$3,$Q4)),MAX($P$1:$P3)+1,0) -> 0 | Q4: =Table2[[#This Row],[Item Name ]] -> Grined Pork Jerky (orginal) | R4: =IFERROR(VLOOKUP(ROWS($R$2:$R4),Table2[[Nub2]:[Name]],2,0),"") | W4: =IF(ISNUMBER(SEARCH('Data Entry'!$J$3,$Y4)),MAX($W$1:$W3)+1,0) -> 0 | X4: =IF(ISNUMBER(SEARCH('Data Entry'!$J$3,$Y4)),MAX($X$1:$X3)+1,0) -> 0 | Y4: 3PLE FARMS CO., LTD | Z4: =IFERROR(VLOOKUP(ROWS($Z$2:$Z4),Table4[[Nub2]:[Supplied Name]],2,0),"") | AA4: =OFFSET($Z$2,,,COUNTIF($Z$2:$Z$25,"?*")) -> #REF! | AC4: =IF(ISNUMBER(SEARCH('Data Entry'!$J$3,$AE4)),MAX($AC$1:$AC3)+1,0) -> 0 | AD4: =IF(ISNUMBER(SEARCH('Data Entry'!$J$3,$AE4)),MAX($AD$1:$AD3)+1,0) -> 0 | AE4: Central Kitchen | AF4: =IFERROR(VLOOKUP(ROWS($Z$2:$Z4),Table5[[#All],[Nub2]:[Location ]],2,0),"") | AG4: =OFFSET($AF$2,,,COUNTIF($AF$2:$AF$25,"?*")) -> #REF! | AI4: 3 Day | AJ4: Wrong Brand
A5: {=ROW(4:4)} -> 4 | B5: DF-0002 | C5: 900137 | D5: Grined Pork Jerky (spicy) | F5: CENTRAL KITCHEN | G5: FOOD | H5: Dry Food | I5: PKT | J5: 1PKT*30G (6 Sliced) | K5: =6.64/10 -> 0.664 | M5: 1 | N5: 10 | O5: =IF(ISNUMBER(SEARCH('Data Entry'!$J$3,$Q5)),MAX($O$1:$O4)+1,0) -> 0 | P5: =IF(ISNUMBER(SEARCH('Data Entry'!$J$3,$Q5)),MAX($P$1:$P4)+1,0) -> 0 | Q5: =Table2[[#This Row],[Item Name ]] -> Grined Pork Jerky (spicy) | R5: =IFERROR(VLOOKUP(ROWS($R$2:$R5),Table2[[Nub2]:[Name]],2,0),"") | W5: =IF(ISNUMBER(SEARCH('Data Entry'!$J$3,$Y5)),MAX($W$1:$W4)+1,0) -> 0 | X5: =IF(ISNUMBER(SEARCH('Data Entry'!$J$3,$Y5)),MAX($X$1:$X4)+1,0) -> 0 | Y5: 62 Printing Service | Z5: =IFERROR(VLOOKUP(ROWS($Z$2:$Z5),Table4[[Nub2]:[Supplied Name]],2,0),"") | AA5: =OFFSET($Z$2,,,COUNTIF($Z$2:$Z$25,"?*")) -> #REF! | AC5: =IF(ISNUMBER(SEARCH('Data Entry'!$J$3,$AE5)),MAX($AC$1:$AC4)+1,0) -> 0 | AD5: =IF(ISNUMBER(SEARCH('Data Entry'!$J$3,$AE5)),MAX($AD$1:$AD4)+1,0) -> 0 | AE5: Fine Dining-TK | AF5: =IFERROR(VLOOKUP(ROWS($Z$2:$Z5),Table5[[#All],[Nub2]:[Location ]],2,0),"") | AG5: =OFFSET($AF$2,,,COUNTIF($AF$2:$AF$25,"?*")) -> #REF! | AI5: 7 Day | AJ5: Wrong Size
A6: {=ROW(5:5)} -> 5 | B6: DF-0003 | C6: 900138 | D6: Grined Beef Jerky (orginal) | F6: CENTRAL KITCHEN | G6: FOOD | H6: Dry Food | I6: PKT | J6: 1PKT*30G (6 Sliced) | K6: =14.274/10 -> 1.4274 | M6: 1 | N6: 10 | O6: =IF(ISNUMBER(SEARCH('Data Entry'!$J$3,$Q6)),MAX($O$1:$O5)+1,0) -> 0 | P6: =IF(ISNUMBER(SEARCH('Data Entry'!$J$3,$Q6)),MAX($P$1:$P5)+1,0) -> 0 | Q6: =Table2[[#This Row],[Item Name ]] -> Grined Beef Jerky (orginal) | R6: =IFERROR(VLOOKUP(ROWS($R$2:$R6),Table2[[Nub2]:[Name]],2,0),"") | W6: =IF(ISNUMBER(SEARCH('Data Entry'!$J$3,$Y6)),MAX($W$1:$W5)+1,0) -> 0 | X6: =IF(ISNUMBER(SEARCH('Data Entry'!$J$3,$Y6)),MAX($X$1:$X5)+1,0) -> 0 | Y6: 800 SUPER GAEA (CAMBODIA) CO., LTD | Z6: =IFERROR(VLOOKUP(ROWS($Z$2:$Z6),Table4[[Nub2]:[Supplied Name]],2,0),"") | AA6: =OFFSET($Z$2,,,COUNTIF($Z$2:$Z$25,"?*")) -> #REF! | AC6: =IF(ISNUMBER(SEARCH('Data Entry'!$J$3,$AE6)),MAX($AC$1:$AC5)+1,0) -> 0 | AD6: =IF(ISNUMBER(SEARCH('Data Entry'!$J$3,$AE6)),MAX($AD$1:$AD5)+1,0) -> 0 | AE6: Fun Crab - 271 Mega Mall | AF6: =IFERROR(VLOOKUP(ROWS($Z$2:$Z6),Table5[[#All],[Nub2]:[Location ]],2,0),"") | AG6: =OFFSET($AF$2,,,COUNTIF($AF$2:$AF$25,"?*")) -> #REF! | AI6: 15 Day | AJ6: Other
A7: {=ROW(6:6)} -> 6 | B7: DF-0004 | C7: 900139 | D7: Grined Beef Jerky (spicy) | F7: CENTRAL KITCHEN | G7: FOOD | H7: Dry Food | I7: PKT | J7: 1PKT*30G (6 Sliced) | K7: =14.38/10 -> 1.438 | M7: 1 | N7: 10 | O7: =IF(ISNUMBER(SEARCH('Data Entry'!$J$3,$Q7)),MAX($O$1:$O6)+1,0) -> 0 | P7: =IF(ISNUMBER(SEARCH('Data Entry'!$J$3,$Q7)),MAX($P$1:$P6)+1,0) -> 0 | Q7: =Table2[[#This Row],[Item Name ]] -> Grined Beef Jerky (spicy) | R7: =IFERROR(VLOOKUP(ROWS($R$2:$R7),Table2[[Nub2]:[Name]],2,0),"") | W7: =IF(ISNUMBER(SEARCH('Data Entry'!$J$3,$Y7)),MAX($W$1:$W6)+1,0) -> 0 | X7: =IF(ISNUMBER(SEARCH('Data Entry'!$J$3,$Y7)),MAX($X$1:$X6)+1,0) -> 0 | Y7: A.V.R (Asia Vehicle Rental) Co.,Ltd(AVR) | Z7: =IFERROR(VLOOKUP(ROWS($Z$2:$Z7),Table4[[Nub2]:[Supplied Name]],2,0),"") | AA7: =OFFSET($Z$2,,,COUNTIF($Z$2:$Z$25,"?*")) -> #REF! | AC7: =IF(ISNUMBER(SEARCH('Data Entry'!$J$3,$AE7)),MAX($AC$1:$AC6)+1,0) -> 0 | AD7: =IF(ISNUMBER(SEARCH('Data Entry'!$J$3,$AE7)),MAX($AD$1:$AD6)+1,0) -> 0 | AE7: Fun Crab - Aeon 2 | AF7: =IFERROR(VLOOKUP(ROWS($Z$2:$Z7),Table5[[#All],[Nub2]:[Location ]],2,0),"") | AG7: =OFFSET($AF$2,,,COUNTIF($AF$2:$AF$25,"?*")) -> #REF! | AI7: 30 Day | AJ7: Spoiled
A8: {=ROW(7:7)} -> 7 | B8: DF-0005 | C8: 900140 | D8: Char Siew Pork Jerky (Original) | F8: CENTRAL KITCHEN | G8: FOOD | H8: Dry Food | I8: PKT | J8: 1PKT*30G | K8: =5.51/10 -> 0.551 | M8: 1 | N8: 10 | O8: =IF(ISNUMBER(SEARCH('Data Entry'!$J$3,$Q8)),MAX($O$1:$O7)+1,0) -> 0 | P8: =IF(ISNUMBER(SEARCH('Data Entry'!$J$3,$Q8)),MAX($P$1:$P7)+1,0) -> 0 | Q8: =Table2[[#This Row],[Item Name ]] -> Char Siew Pork Jerky (Original) | R8: =IFERROR(VLOOKUP(ROWS($R$2:$R8),Table2[[Nub2]:[Name]],2,0),"") | W8: =IF(ISNUMBER(SEARCH('Data Entry'!$J$3,$Y8)),MAX($W$1:$W7)+1,0) -> 0 | X8: =IF(ISNUMBER(SEARCH('Data Entry'!$J$3,$Y8)),MAX($X$1:$X7)+1,0) -> 0 | Y8: A2 TRADING | Z8: =IFERROR(VLOOKUP(ROWS($Z$2:$Z8),Table4[[Nub2]:[Supplied Name]],2,0),"") | AA8: =OFFSET($Z$2,,,COUNTIF($Z$2:$Z$25,"?*")) -> #REF! | AC8: =IF(ISNUMBER(SEARCH('Data Entry'!$J$3,$AE8)),MAX($AC$1:$AC7)+1,0) -> 0 | AD8: =IF(ISNUMBER(SEARCH('Data Entry'!$J$3,$AE8)),MAX($AD$1:$AD7)+1,0) -> 0 | AE8: Fun Crab - Toul Tom Pong | AF8: =IFERROR(VLOOKUP(ROWS($Z$2:$Z8),Table5[[#All],[Nub2]:[Location ]],2,0),"") | AG8: =OFFSET($AF$2,,,COUNTIF($AF$2:$AF$25,"?*")) -> #REF! | AI8: Daily Use | AJ8: Suport operation
A9: {=ROW(8:8)} -> 8 | B9: DF-0006 | C9: 900141 | D9: Char Siew Pork Jerky (Spicy) | F9: CENTRAL KITCHEN | G9: FOOD | H9: Dry Food | I9: PKT | J9: 1PKT*30G | K9: =5.694/10 -> 0.5694 | M9: 1 | N9: 10 | O9: =IF(ISNUMBER(SEARCH('Data Entry'!$J$3,$Q9)),MAX($O$1:$O8)+1,0) -> 0 | P9: =IF(ISNUMBER(SEARCH('Data Entry'!$J$3,$Q9)),MAX($P$1:$P8)+1,0) -> 0 | Q9: =Table2[[#This Row],[Item Name ]] -> Char Siew Pork Jerky (Spicy) | R9: =IFERROR(VLOOKUP(ROWS($R$2:$R9),Table2[[Nub2]:[Name]],2,0),"") | W9: =IF(ISNUMBER(SEARCH('Data Entry'!$J$3,$Y9)),MAX($W$1:$W8)+1,0) -> 0 | X9: =IF(ISNUMBER(SEARCH('Data Entry'!$J$3,$Y9)),MAX($X$1:$X8)+1,0) -> 0 | Y9: ABC Green Supply Co., Ltd | Z9: =IFERROR(VLOOKUP(ROWS($Z$2:$Z9),Table4[[Nub2]:[Supplied Name]],2,0),"") | AA9: =OFFSET($Z$2,,,COUNTIF($Z$2:$Z$25,"?*")) -> #REF! | AC9: =IF(ISNUMBER(SEARCH('Data Entry'!$J$3,$AE9)),MAX($AC$1:$AC8)+1,0) -> 0 | AD9: =IF(ISNUMBER(SEARCH('Data Entry'!$J$3,$AE9)),MAX($AD$1:$AD8)+1,0) -> 0 | AE9: Fun Crab - Tuol Kork | AF9: =IFERROR(VLOOKUP(ROWS($Z$2:$Z9),Table5[[#All],[Nub2]:[Location ]],2,0),"") | AG9: =OFFSET($AF$2,,,COUNTIF($AF$2:$AF$25,"?*")) -> #REF!
A10: {=ROW(9:9)} -> 9 | B10: DF-0007 | C10: 900142 | D10: Dried beef (original) | F10: CENTRAL KITCHEN | G10: FOOD | H10: Dry Food | I10: PKT | J10: 1PKT*30G | K10: =8.4/10 -> 0.84 | M10: 1 | N10: 10 | O10: =IF(ISNUMBER(SEARCH('Data Entry'!$J$3,$Q10)),MAX($O$1:$O9)+1,0) -> 0 | P10: =IF(ISNUMBER(SEARCH('Data Entry'!$J$3,$Q10)),MAX($P$1:$P9)+1,0) -> 0 | Q10: =Table2[[#This Row],[Item Name ]] -> Dried beef (original) | R10: =IFERROR(VLOOKUP(ROWS($R$2:$R10),Table2[[Nub2]:[Name]],2,0),"") | W10: =IF(ISNUMBER(SEARCH('Data Entry'!$J$3,$Y10)),MAX($W$1:$W9)+1,0) -> 0 | X10: =IF(ISNUMBER(SEARCH('Data Entry'!$J$3,$Y10)),MAX($X$1:$X9)+1,0) -> 0 | Y10: ACCOUNTING AND AUDITING REGULATOR | Z10: =IFERROR(VLOOKUP(ROWS($Z$2:$Z10),Table4[[Nub2]:[Supplied Name]],2,0),"") | AA10: =OFFSET($Z$2,,,COUNTIF($Z$2:$Z$25,"?*")) -> #REF! | AC10: =IF(ISNUMBER(SEARCH('Data Entry'!$J$3,$AE10)),MAX($AC$1:$AC9)+1,0) -> 0 | AD10: =IF(ISNUMBER(SEARCH('Data Entry'!$J$3,$AE10)),MAX($AD$1:$AD9)+1,0) -> 0 | AE10: Guriru - Toulkok | AF10: =IFERROR(VLOOKUP(ROWS($Z$2:$Z10),Table5[[#All],[Nub2]:[Location ]],2,0),"") | AG10: =OFFSET($AF$2,,,COUNTIF($AF$2:$AF$25,"?*")) -> #REF!
A11: {=ROW(10:10)} -> 10 | B11: DF-0008 | C11: 900143 | D11: Dried beef (spicy) | F11: CENTRAL KITCHEN | G11: FOOD | H11: Dry Food | I11: PKT | J11: 1PKT*30G | K11: =8.43/10 -> 0.843 | M11: 1 | N11: 10 | O11: =IF(ISNUMBER(SEARCH('Data Entry'!$J$3,$Q11)),MAX($O$1:$O10)+1,0) -> 0 | P11: =IF(ISNUMBER(SEARCH('Data Entry'!$J$3,$Q11)),MAX($P$1:$P10)+1,0) -> 0 | Q11: =Table2[[#This Row],[Item Name ]] -> Dried beef (spicy) | R11: =IFERROR(VLOOKUP(ROWS($R$2:$R11),Table2[[Nub2]:[Name]],2,0),"") | W11: =IF(ISNUMBER(SEARCH('Data Entry'!$J$3,$Y11)),MAX($W$1:$W10)+1,0) -> 0 | X11: =IF(ISNUMBER(SEARCH('Data Entry'!$J$3,$Y11)),MAX($X$1:$X10)+1,0) -> 0 | Y11: ACE ZAPA | Z11: =IFERROR(VLOOKUP(ROWS($Z$2:$Z11),Table4[[Nub2]:[Supplied Name]],2,0),"") | AA11: =OFFSET($Z$2,,,COUNTIF($Z$2:$Z$25,"?*")) -> #REF! | AC11: =IF(ISNUMBER(SEARCH('Data Entry'!$J$3,$AE11)),MAX($AC$1:$AC10)+1,0) -> 0 | AD11: =IF(ISNUMBER(SEARCH('Data Entry'!$J$3,$AE11)),MAX($AD$1:$AD10)+1,0) -> 0 | AE11: Hiko - Euro Park | AF11: =IFERROR(VLOOKUP(ROWS($Z$2:$Z11),Table5[[#All],[Nub2]:[Location ]],2,0),"") | AG11: =OFFSET($AF$2,,,COUNTIF($AF$2:$AF$25,"?*")) -> #REF!
A12: {=ROW(11:11)} -> 11 | B12: DF-0009 | C12: 900144 | D12: Beef sausage (Steamed & vacuum) | F12: CENTRAL KITCHEN | G12: FOOD | H12: Dry Food | I12: PKT | J12: 1PKT*45G (1 PCS) | K12: =8.64/12 -> 0.72 | M12: 1 | N12: 10 | O12: =IF(ISNUMBER(SEARCH('Data Entry'!$J$3,$Q12)),MAX($O$1:$O11)+1,0) -> 0 | P12: =IF(ISNUMBER(SEARCH('Data Entry'!$J$3,$Q12)),MAX($P$1:$P11)+1,0) -> 0 | Q12: =Table2[[#This Row],[Item Name ]] -> Beef sausage (Steamed & vacuum) | R12: =IFERROR(VLOOKUP(ROWS($R$2:$R12),Table2[[Nub2]:[Name]],2,0),"") | W12: =IF(ISNUMBER(SEARCH('Data Entry'!$J$3,$Y12)),MAX($W$1:$W11)+1,0) -> 0 | X12: =IF(ISNUMBER(SEARCH('Data Entry'!$J$3,$Y12)),MAX($X$1:$X11)+1,0) -> 0 | Y12: ACLEDA BANK PLC. | Z12: =IFERROR(VLOOKUP(ROWS($Z$2:$Z12),Table4[[Nub2]:[Supplied Name]],2,0),"") | AA12: =OFFSET($Z$2,,,COUNTIF($Z$2:$Z$25,"?*")) -> #REF! | AC12: =IF(ISNUMBER(SEARCH('Data Entry'!$J$3,$AE12)),MAX($AC$1:$AC11)+1,0) -> 0 | AD12: =IF(ISNUMBER(SEARCH('Data Entry'!$J$3,$AE12)),MAX($AD$1:$AD11)+1,0) -> 0 | AE12: Hiko - Noro Mall | AF12: =IFERROR(VLOOKUP(ROWS($Z$2:$Z12),Table5[[#All],[Nub2]:[Location ]],2,0),"") | AG12: =OFFSET($AF$2,,,COUNTIF($AF$2:$AF$25,"?*")) -> #REF!
A13: {=ROW(12:12)} -> 12 | B13: DF-0010 | C13: 900145 | D13: Pork sausage (Steamed & Vacuum) | F13: CENTRAL KITCHEN | G13: FOOD | H13: Dry Food | I13: PKT | J13: 1PKT*45G (1 PCS) | K13: =8.64/12 -> 0.72 | M13: 1 | N13: 10 | O13: =IF(ISNUMBER(SEARCH('Data Entry'!$J$3,$Q13)),MAX($O$1:$O12)+1,0) -> 0 | P13: =IF(ISNUMBER(SEARCH('Data Entry'!$J$3,$Q13)),MAX($P$1:$P12)+1,0) -> 0 | Q13: =Table2[[#This Row],[Item Name ]] -> Pork sausage (Steamed & Vacuum) | R13: =IFERROR(VLOOKUP(ROWS($R$2:$R13),Table2[[Nub2]:[Name]],2,0),"") | W13: =IF(ISNUMBER(SEARCH('Data Entry'!$J$3,$Y13)),MAX($W$1:$W12)+1,0) -> 0 | X13: =IF(ISNUMBER(SEARCH('Data Entry'!$J$3,$Y13)),MAX($X$1:$X12)+1,0) -> 0 | Y13: ACM HR Consultancy | Z13: =IFERROR(VLOOKUP(ROWS($Z$2:$Z13),Table4[[Nub2]:[Supplied Name]],2,0),"") | AA13: =OFFSET($Z$2,,,COUNTIF($Z$2:$Z$25,"?*")) -> #REF! | AC13: =IF(ISNUMBER(SEARCH('Data Entry'!$J$3,$AE13)),MAX($AC$1:$AC12)+1,0) -> 0 | AD13: =IF(ISNUMBER(SEARCH('Data Entry'!$J$3,$AE13)),MAX($AD$1:$AD12)+1,0) -> 0 | AE13: Hiko 271- Mega Mall | AF13: =IFERROR(VLOOKUP(ROWS($Z$2:$Z13),Table5[[#All],[Nub2]:[Location ]],2,0),"") | AG13: =OFFSET($AF$2,,,COUNTIF($AF$2:$AF$25,"?*")) -> #REF!
A14: {=ROW(13:13)} -> 13 | B14: DF-0011 | C14: 900146 | D14: Fish Kakerm | G14: FOOD | H14: Dry Food | I14: PKT | J14: 1PKT*150G | M14: 1 | N14: 10 | O14: =IF(ISNUMBER(SEARCH('Data Entry'!$J$3,$Q14)),MAX($O$1:$O13)+1,0) -> 0 | P14: =IF(ISNUMBER(SEARCH('Data Entry'!$J$3,$Q14)),MAX($P$1:$P13)+1,0) -> 0 | Q14: =Table2[[#This Row],[Item Name ]] -> Fish Kakerm | R14: =IFERROR(VLOOKUP(ROWS($R$2:$R14),Table2[[Nub2]:[Name]],2,0),"") | W14: =IF(ISNUMBER(SEARCH('Data Entry'!$J$3,$Y14)),MAX($W$1:$W13)+1,0) -> 0 | X14: =IF(ISNUMBER(SEARCH('Data Entry'!$J$3,$Y14)),MAX($X$1:$X13)+1,0) -> 0 | Y14: ACTIVE COMMUNICATIONS CO.,LTD | Z14: =IFERROR(VLOOKUP(ROWS($Z$2:$Z14),Table4[[Nub2]:[Supplied Name]],2,0),"") | AA14: =OFFSET($Z$2,,,COUNTIF($Z$2:$Z$25,"?*")) -> #REF! | AC14: =IF(ISNUMBER(SEARCH('Data Entry'!$J$3,$AE14)),MAX($AC$1:$AC13)+1,0) -> 0 | AD14: =IF(ISNUMBER(SEARCH('Data Entry'!$J$3,$AE14)),MAX($AD$1:$AD13)+1,0) -> 0 | AE14: Hiko-Design Village | AF14: =IFERROR(VLOOKUP(ROWS($Z$2:$Z14),Table5[[#All],[Nub2]:[Location ]],2,0),"") | AG14: =OFFSET($AF$2,,,COUNTIF($AF$2:$AF$25,"?*")) -> #REF!
A15: {=ROW(14:14)} -> 14 | B15: DF-0012 | C15: 900147 | D15: Cashew nuts (original) | F15: CENTRAL KITCHEN | G15: FOOD | H15: Dry Food | I15: PKT | J15: 1PKT*150G | M15: 1 | N15: 10 | O15: =IF(ISNUMBER(SEARCH('Data Entry'!$J$3,$Q15)),MAX($O$1:$O14)+1,0) -> 0 | P15: =IF(ISNUMBER(SEARCH('Data Entry'!$J$3,$Q15)),MAX($P$1:$P14)+1,0) -> 0 | Q15: =Table2[[#This Row],[Item Name ]] -> Cashew nuts (original) | R15: =IFERROR(VLOOKUP(ROWS($R$2:$R15),Table2[[Nub2]:[Name]],2,0),"") | W15: =IF(ISNUMBER(SEARCH('Data Entry'!$J$3,$Y15)),MAX($W$1:$W14)+1,0) -> 0 | X15: =IF(ISNUMBER(SEARCH('Data Entry'!$J$3,$Y15)),MAX($X$1:$X14)+1,0) -> 0 | Y15: ADVANCED BANK OF ASIA LIMITED | Z15: =IFERROR(VLOOKUP(ROWS($Z$2:$Z15),Table4[[Nub2]:[Supplied Name]],2,0),"") | AA15: =OFFSET($Z$2,,,COUNTIF($Z$2:$Z$25,"?*")) -> #REF! | AC15: =IF(ISNUMBER(SEARCH('Data Entry'!$J$3,$AE15)),MAX($AC$1:$AC14)+1,0) -> 0 | AD15: =IF(ISNUMBER(SEARCH('Data Entry'!$J$3,$AE15)),MAX($AD$1:$AD14)+1,0) -> 0 | AE15: Mras Prov - Borey Keyla | AF15: =IFERROR(VLOOKUP(ROWS($Z$2:$Z15),Table5[[#All],[Nub2]:[Location ]],2,0),"") | AG15: =OFFSET($AF$2,,,COUNTIF($AF$2:$AF$25,"?*")) -> #REF!
A16: {=ROW(15:15)} -> 15 | B16: DF-0013 | C16: 900148 | D16: Cashew nuts (spicy) | F16: CENTRAL KITCHEN | G16: FOOD | H16: Dry Food | I16: PKT | J16: 1PKT*150G | M16: 1 | N16: 10 | O16: =IF(ISNUMBER(SEARCH('Data Entry'!$J$3,$Q16)),MAX($O$1:$O15)+1,0) -> 0 | P16: =IF(ISNUMBER(SEARCH('Data Entry'!$J$3,$Q16)),MAX($P$1:$P15)+1,0) -> 0 | Q16: =Table2[[#This Row],[Item Name ]] -> Cashew nuts (spicy) | R16: =IFERROR(VLOOKUP(ROWS($R$2:$R16),Table2[[Nub2]:[Name]],2,0),"") | W16: =IF(ISNUMBER(SEARCH('Data Entry'!$J$3,$Y16)),MAX($W$1:$W15)+1,0) -> 0 | X16: =IF(ISNUMBER(SEARCH('Data Entry'!$J$3,$Y16)),MAX($X$1:$X15)+1,0) -> 0 | Y16: ADVERTISING DECORATION & PRINTING | Z16: =IFERROR(VLOOKUP(ROWS($Z$2:$Z16),Table4[[Nub2]:[Supplied Name]],2,0),"") | AA16: =OFFSET($Z$2,,,COUNTIF($Z$2:$Z$25,"?*")) -> #REF! | AC16: =IF(ISNUMBER(SEARCH('Data Entry'!$J$3,$AE16)),MAX($AC$1:$AC15)+1,0) -> 0 | AD16: =IF(ISNUMBER(SEARCH('Data Entry'!$J$3,$AE16)),MAX($AD$1:$AD15)+1,0) -> 0 | AE16: Neptune - Seafood | AF16: =IFERROR(VLOOKUP(ROWS($Z$2:$Z16),Table5[[#All],[Nub2]:[Location ]],2,0),"") | AG16: =OFFSET($AF$2,,,COUNTIF($AF$2:$AF$25,"?*")) -> #REF!
A17: {=ROW(16:16)} -> 16 | B17: DF-0014 | C17: 900149 | D17: Big Peanuts (original) | F17: CENTRAL KITCHEN | G17: FOOD | H17: Dry Food | I17: PKT | J17: 1PKT*150G | K17: 0.76 | M17: 1 | N17: 10 | O17: =IF(ISNUMBER(SEARCH('Data Entry'!$J$3,$Q17)),MAX($O$1:$O16)+1,0) -> 0 | P17: =IF(ISNUMBER(SEARCH('Data Entry'!$J$3,$Q17)),MAX($P$1:$P16)+1,0) -> 0 | Q17: =Table2[[#This Row],[Item Name ]] -> Big Peanuts (original) | R17: =IFERROR(VLOOKUP(ROWS($R$2:$R17),Table2[[Nub2]:[Name]],2,0),"") | W17: =IF(ISNUMBER(SEARCH('Data Entry'!$J$3,$Y17)),MAX($W$1:$W16)+1,0) -> 0 | X17: =IF(ISNUMBER(SEARCH('Data Entry'!$J$3,$Y17)),MAX($X$1:$X16)+1,0) -> 0 | Y17: AEON MALL (CAMBODIA) CO., LTD_A3 | Z17: =IFERROR(VLOOKUP(ROWS($Z$2:$Z17),Table4[[Nub2]:[Supplied Name]],2,0),"") | AA17: =OFFSET($Z$2,,,COUNTIF($Z$2:$Z$25,"?*")) -> #REF! | AC17: =IF(ISNUMBER(SEARCH('Data Entry'!$J$3,$AE17)),MAX($AC$1:$AC16)+1,0) -> 0 | AD17: =IF(ISNUMBER(SEARCH('Data Entry'!$J$3,$AE17)),MAX($AD$1:$AD16)+1,0) -> 0 | AE17: Office & Admin | AF17: =IFERROR(VLOOKUP(ROWS($Z$2:$Z17),Table5[[#All],[Nub2]:[Location ]],2,0),"") | AG17: =OFFSET($AF$2,,,COUNTIF($AF$2:$AF$25,"?*")) -> #REF!
A18: {=ROW(17:17)} -> 17 | B18: DF-0015 | C18: 900150 | D18: Big Peanuts (spicy) | F18: CENTRAL KITCHEN | G18: FOOD | H18: Dry Food | I18: PKT | J18: 1PKT*150G | K18: 0.76 | M18: 1 | N18: 10 | O18: =IF(ISNUMBER(SEARCH('Data Entry'!$J$3,$Q18)),MAX($O$1:$O17)+1,0) -> 0 | P18: =IF(ISNUMBER(SEARCH('Data Entry'!$J$3,$Q18)),MAX($P$1:$P17)+1,0) -> 0 | Q18: =Table2[[#This Row],[Item Name ]] -> Big Peanuts (spicy) | R18: =IFERROR(VLOOKUP(ROWS($R$2:$R18),Table2[[Nub2]:[Name]],2,0),"") | W18: =IF(ISNUMBER(SEARCH('Data Entry'!$J$3,$Y18)),MAX($W$1:$W17)+1,0) -> 0 | X18: =IF(ISNUMBER(SEARCH('Data Entry'!$J$3,$Y18)),MAX($X$1:$X17)+1,0) -> 0 | Y18: AEON Mall (Cambodia) Co., Ltd | Z18: =IFERROR(VLOOKUP(ROWS($Z$2:$Z18),Table4[[Nub2]:[Supplied Name]],2,0),"") | AA18: =OFFSET($Z$2,,,COUNTIF($Z$2:$Z$25,"?*")) -> #REF! | AC18: =IF(ISNUMBER(SEARCH('Data Entry'!$J$3,$AE18)),MAX($AC$1:$AC17)+1,0) -> 0 | AD18: =IF(ISNUMBER(SEARCH('Data Entry'!$J$3,$AE18)),MAX($AD$1:$AD17)+1,0) -> 0 | AE18: QB - 271 Mega Mall | AF18: =IFERROR(VLOOKUP(ROWS($Z$2:$Z18),Table5[[#All],[Nub2]:[Location ]],2,0),"") | AG18: =OFFSET($AF$2,,,COUNTIF($AF$2:$AF$25,"?*")) -> #REF!
A19: {=ROW(18:18)} -> 18 | B19: FF-0001 | C19: 900281 | D19: Fresh Honey Melon In The Cup | F19: CENTRAL KITCHEN | G19: FOOD | H19: Fresh Fruit | I19: Cup | K19: 1.356 | M19: 1 | N19: 10 | O19: =IF(ISNUMBER(SEARCH('Data Entry'!$J$3,$Q19)),MAX($O$1:$O18)+1,0) -> 0 | P19: =IF(ISNUMBER(SEARCH('Data Entry'!$J$3,$Q19)),MAX($P$1:$P18)+1,0) -> 0 | Q19: =Table2[[#This Row],[Item Name ]] -> Fresh Honey Melon In The Cup | R19: =IFERROR(VLOOKUP(ROWS($R$2:$R19),Table2[[Nub2]:[Name]],2,0),"") | W19: =IF(ISNUMBER(SEARCH('Data Entry'!$J$3,$Y19)),MAX($W$1:$W18)+1,0) -> 0 | X19: =IF(ISNUMBER(SEARCH('Data Entry'!$J$3,$Y19)),MAX($X$1:$X18)+1,0) -> 0 | Y19: AGB Consulting Co.,Ltd | Z19: =IFERROR(VLOOKUP(ROWS($Z$2:$Z19),Table4[[Nub2]:[Supplied Name]],2,0),"") | AA19: =OFFSET($Z$2,,,COUNTIF($Z$2:$Z$25,"?*")) -> #REF! | AC19: =IF(ISNUMBER(SEARCH('Data Entry'!$J$3,$AE19)),MAX($AC$1:$AC18)+1,0) -> 0 | AD19: =IF(ISNUMBER(SEARCH('Data Entry'!$J$3,$AE19)),MAX($AD$1:$AD18)+1,0) -> 0 | AE19: QB PPIU | AF19: =IFERROR(VLOOKUP(ROWS($Z$2:$Z19),Table5[[#All],[Nub2]:[Location ]],2,0),"") | AG19: =OFFSET($AF$2,,,COUNTIF($AF$2:$AF$25,"?*")) -> #REF!
A20: {=ROW(19:19)} -> 19 | B20: FF-0002 | C20: 900282 | D20: Fresh Red Apple In The Cup | F20: CENTRAL KITCHEN | G20: FOOD | H20: Fresh Fruit | I20: Cup | K20: 0.708 | M20: 1 | N20: 10 | O20: =IF(ISNUMBER(SEARCH('Data Entry'!$J$3,$Q20)),MAX($O$1:$O19)+1,0) -> 0 | P20: =IF(ISNUMBER(SEARCH('Data Entry'!$J$3,$Q20)),MAX($P$1:$P19)+1,0) -> 0 | Q20: =Table2[[#This Row],[Item Name ]] -> Fresh Red Apple In The Cup | R20: =IFERROR(VLOOKUP(ROWS($R$2:$R20),Table2[[Nub2]:[Name]],2,0),"") | W20: =IF(ISNUMBER(SEARCH('Data Entry'!$J$3,$Y20)),MAX($W$1:$W19)+1,0) -> 0 | X20: =IF(ISNUMBER(SEARCH('Data Entry'!$J$3,$Y20)),MAX($X$1:$X19)+1,0) -> 0 | Y20: AH VY Orusey Market | Z20: =IFERROR(VLOOKUP(ROWS($Z$2:$Z20),Table4[[Nub2]:[Supplied Name]],2,0),"") | AA20: =OFFSET($Z$2,,,COUNTIF($Z$2:$Z$25,"?*")) -> #REF! | AC20: =IF(ISNUMBER(SEARCH('Data Entry'!$J$3,$AE20)),MAX($AC$1:$AC19)+1,0) -> 0 | AD20: =IF(ISNUMBER(SEARCH('Data Entry'!$J$3,$AE20)),MAX($AD$1:$AD19)+1,0) -> 0 | AE20: QB-Aeon Meanchey | AF20: =IFERROR(VLOOKUP(ROWS($Z$2:$Z20),Table5[[#All],[Nub2]:[Location ]],2,0),"") | AG20: =OFFSET($AF$2,,,COUNTIF($AF$2:$AF$25,"?*")) -> #REF!
A21: {=ROW(20:20)} -> 20 | B21: FF-0003 | C21: 900283 | D21: Fresh Ripe Mango In The Cup | F21: CENTRAL KITCHEN | G21: FOOD | H21: Fresh Fruit | I21: Cup | K21: 0.66 | M21: 1 | N21: 10 | O21: =IF(ISNUMBER(SEARCH('Data Entry'!$J$3,$Q21)),MAX($O$1:$O20)+1,0) -> 0 | P21: =IF(ISNUMBER(SEARCH('Data Entry'!$J$3,$Q21)),MAX($P$1:$P20)+1,0) -> 0 | Q21: =Table2[[#This Row],[Item Name ]] -> Fresh Ripe Mango In The Cup | R21: =IFERROR(VLOOKUP(ROWS($R$2:$R21),Table2[[Nub2]:[Name]],2,0),"") | W21: =IF(ISNUMBER(SEARCH('Data Entry'!$J$3,$Y21)),MAX($W$1:$W20)+1,0) -> 0 | X21: =IF(ISNUMBER(SEARCH('Data Entry'!$J$3,$Y21)),MAX($X$1:$X20)+1,0) -> 0 | Y21: ANANA COMPUTER CO., LTD | Z21: =IFERROR(VLOOKUP(ROWS($Z$2:$Z21),Table4[[Nub2]:[Supplied Name]],2,0),"") | AA21: =OFFSET($Z$2,,,COUNTIF($Z$2:$Z$25,"?*")) -> #REF! | AC21: =IF(ISNUMBER(SEARCH('Data Entry'!$J$3,$AE21)),MAX($AC$1:$AC20)+1,0) -> 0 | AD21: =IF(ISNUMBER(SEARCH('Data Entry'!$J$3,$AE21)),MAX($AD$1:$AD20)+1,0) -> 0 | AE21: Tako Lounge- Toulkok | AF21: =IFERROR(VLOOKUP(ROWS($Z$2:$Z21),Table5[[#All],[Nub2]:[Location ]],2,0),"") | AG21: =OFFSET($AF$2,,,COUNTIF($AF$2:$AF$25,"?*")) -> #REF!
A22: {=ROW(21:21)} -> 21 | B22: FF-0004 | C22: 900284 | D22: Fresh Ripe watermelon In The Cup | F22: CENTRAL KITCHEN | G22: FOOD | H22: Fresh Fruit | I22: Cup | K22: 0.504 | M22: 1 | N22: 10 | O22: =IF(ISNUMBER(SEARCH('Data Entry'!$J$3,$Q22)),MAX($O$1:$O21)+1,0) -> 0 | P22: =IF(ISNUMBER(SEARCH('Data Entry'!$J$3,$Q22)),MAX($P$1:$P21)+1,0) -> 0 | Q22: =Table2[[#This Row],[Item Name ]] -> Fresh Ripe watermelon In The Cup | R22: =IFERROR(VLOOKUP(ROWS($R$2:$R22),Table2[[Nub2]:[Name]],2,0),"") | W22: =IF(ISNUMBER(SEARCH('Data Entry'!$J$3,$Y22)),MAX($W$1:$W21)+1,0) -> 0 | X22: =IF(ISNUMBER(SEARCH('Data Entry'!$J$3,$Y22)),MAX($X$1:$X21)+1,0) -> 0 | Y22: ANTICIMEX PEST MANAGEMENT CO.,LTD | Z22: =IFERROR(VLOOKUP(ROWS($Z$2:$Z22),Table4[[Nub2]:[Supplied Name]],2,0),"") | AA22: =OFFSET($Z$2,,,COUNTIF($Z$2:$Z$25,"?*")) -> #REF! | AC22: =IF(ISNUMBER(SEARCH('Data Entry'!$J$3,$AE22)),MAX($AC$1:$AC21)+1,0) -> 0 | AD22: =IF(ISNUMBER(SEARCH('Data Entry'!$J$3,$AE22)),MAX($AD$1:$AD21)+1,0) -> 0 | AE22: The Cut - Boeung Kak | AF22: =IFERROR(VLOOKUP(ROWS($Z$2:$Z22),Table5[[#All],[Nub2]:[Location ]],2,0),"") | AG22: =OFFSET($AF$2,,,COUNTIF($AF$2:$AF$25,"?*")) -> #REF!
A23: {=ROW(22:22)} -> 22 | B23: FF-0005 | C23: 900285 | D23: Fresh Pineapple In The Cup | F23: CENTRAL KITCHEN | G23: FOOD | H23: Fresh Fruit | I23: Cup | K23: 0.396 | M23: 1 | N23: 10 | O23: =IF(ISNUMBER(SEARCH('Data Entry'!$J$3,$Q23)),MAX($O$1:$O22)+1,0) -> 0 | P23: =IF(ISNUMBER(SEARCH('Data Entry'!$J$3,$Q23)),MAX($P$1:$P22)+1,0) -> 0 | Q23: =Table2[[#This Row],[Item Name ]] -> Fresh Pineapple In The Cup | R23: =IFERROR(VLOOKUP(ROWS($R$2:$R23),Table2[[Nub2]:[Name]],2,0),"") | W23: =IF(ISNUMBER(SEARCH('Data Entry'!$J$3,$Y23)),MAX($W$1:$W22)+1,0) -> 0 | X23: =IF(ISNUMBER(SEARCH('Data Entry'!$J$3,$Y23)),MAX($X$1:$X22)+1,0) -> 0 | Y23: APOLLO ELOGISTICS CO., LTD | Z23: =IFERROR(VLOOKUP(ROWS($Z$2:$Z23),Table4[[Nub2]:[Supplied Name]],2,0),"") | AA23: =OFFSET($Z$2,,,COUNTIF($Z$2:$Z$25,"?*")) -> #REF! | AC23: =IF(ISNUMBER(SEARCH('Data Entry'!$J$3,$AE23)),MAX($AC$1:$AC22)+1,0) -> 0 | AD23: =IF(ISNUMBER(SEARCH('Data Entry'!$J$3,$AE23)),MAX($AD$1:$AD22)+1,0) -> 0 | AF23: =IFERROR(VLOOKUP(ROWS($Z$2:$Z23),Table5[[#All],[Nub2]:[Location ]],2,0),"") | AG23: =OFFSET($AF$2,,,COUNTIF($AF$2:$AF$25,"?*")) -> #REF!
A24: {=ROW(23:23)} -> 23 | B24: HF-0001 | C24: 900029 | D24: BEEF LOK LAK WITH RICE (បាយ​ ឡុកឡាក់សាច់គោ) | F24: CENTRAL KITCHEN | G24: FOOD | H24: Khmer Food | I24: BOX | J24: 1BOX*1Portion | K24: 1.668 | M24: 1 | N24: 10 | O24: =IF(ISNUMBER(SEARCH('Data Entry'!$J$3,$Q24)),MAX($O$1:$O23)+1,0) -> 0 | P24: =IF(ISNUMBER(SEARCH('Data Entry'!$J$3,$Q24)),MAX($P$1:$P23)+1,0) -> 0 | Q24: =Table2[[#This Row],[Item Name ]] -> BEEF LOK LAK WITH RICE (បាយ​ ឡុកឡាក់សាច់គោ) | R24: =IFERROR(VLOOKUP(ROWS($R$2:$R24),Table2[[Nub2]:[Name]],2,0),"") | W24: =IF(ISNUMBER(SEARCH('Data Entry'!$J$3,$Y24)),MAX($W$1:$W23)+1,0) -> 0 | X24: =IF(ISNUMBER(SEARCH('Data Entry'!$J$3,$Y24)),MAX($X$1:$X23)+1,0) -> 0 | Y24: ASIAN T A C T CO., LTD | Z24: =IFERROR(VLOOKUP(ROWS($Z$2:$Z24),Table4[[Nub2]:[Supplied Name]],2,0),"") | AA24: =OFFSET($Z$2,,,COUNTIF($Z$2:$Z$25,"?*")) -> #REF! | AC24: =IF(ISNUMBER(SEARCH('Data Entry'!$J$3,$AE24)),MAX($AC$1:$AC23)+1,0) -> 0 | AD24: =IF(ISNUMBER(SEARCH('Data Entry'!$J$3,$AE24)),MAX($AD$1:$AD23)+1,0) -> 0 | AF24: =IFERROR(VLOOKUP(ROWS($Z$2:$Z24),Table5[[#All],[Nub2]:[Location ]],2,0),"") | AG24: =OFFSET($AF$2,,,COUNTIF($AF$2:$AF$25,"?*")) -> #REF!
A25: {=ROW(24:24)} -> 24 | B25: HF-0002 | C25: 900027 | D25: STIR FRIED MINCED PORK HOT BASIL WITH RICE (បាយ សាច់ជ្រូកចិញ្រ្ចាំឆាម្រះព្រៅ) | F25: CENTRAL KITCHEN | G25: FOOD | H25: Khmer Food | I25: BOX | J25: 1BOX*1Portion | K25: 1.2024 | M25: 1 | N25: 10 | O25: =IF(ISNUMBER(SEARCH('Data Entry'!$J$3,$Q25)),MAX($O$1:$O24)+1,0) -> 0 | P25: =IF(ISNUMBER(SEARCH('Data Entry'!$J$3,$Q25)),MAX($P$1:$P24)+1,0) -> 0 | Q25: =Table2[[#This Row],[Item Name ]] -> STIR FRIED MINCED PORK HOT BASIL WITH RICE (បាយ សាច់ជ្រូកចិញ្រ្ចាំឆាម្រះព្រៅ) | R25: =IFERROR(VLOOKUP(ROWS($R$2:$R25),Table2[[Nub2]:[Name]],2,0),"") | W25: =IF(ISNUMBER(SEARCH('Data Entry'!$J$3,$Y25)),MAX($W$1:$W24)+1,0) -> 0 | X25: =IF(ISNUMBER(SEARCH('Data Entry'!$J$3,$Y25)),MAX($X$1:$X24)+1,0) -> 0 | Y25: AT & B CONSTRUCTING | Z25: =IFERROR(VLOOKUP(ROWS($Z$2:$Z25),Table4[[Nub2]:[Supplied Name]],2,0),"") | AA25: =OFFSET($Z$2,,,COUNTIF($Z$2:$Z$25,"?*")) -> #REF! | AC25: =IF(ISNUMBER(SEARCH('Data Entry'!$J$3,$AE25)),MAX($AC$1:$AC24)+1,0) -> 0 | AD25: =IF(ISNUMBER(SEARCH('Data Entry'!$J$3,$AE25)),MAX($AD$1:$AD24)+1,0) -> 0 | AF25: =IFERROR(VLOOKUP(ROWS($Z$2:$Z25),Table5[[#All],[Nub2]:[Location ]],2,0),"") | AG25: =OFFSET($AF$2,,,COUNTIF($AF$2:$AF$25,"?*")) -> #REF!
A26: {=ROW(25:25)} -> 25 | B26: HF-0003 | C26: 900026 | D26: STIR FRIED CHICKEN HOT BASIL WITH RICE (បាយ​ សាច់មាន់ឆាក្ដៅ) | F26: CENTRAL KITCHEN | G26: FOOD | H26: Khmer Food | I26: BOX | J26: 1BOX*1Portion | K26: 1.2984 | M26: 1 | N26: 10 | O26: =IF(ISNUMBER(SEARCH('Data Entry'!$J$3,$Q26)),MAX($O$1:$O25)+1,0) -> 0 | P26: =IF(ISNUMBER(SEARCH('Data Entry'!$J$3,$Q26)),MAX($P$1:$P25)+1,0) -> 0 | Q26: =Table2[[#This Row],[Item Name ]] -> STIR FRIED CHICKEN HOT BASIL WITH RICE (បាយ​ សាច់មាន់ឆាក្ដៅ) | R26: =IFERROR(VLOOKUP(ROWS($R$2:$R26),Table2[[Nub2]:[Name]],2,0),"") | W26: =IF(ISNUMBER(SEARCH('Data Entry'!$J$3,$Y26)),MAX($W$1:$W25)+1,0) -> 0 | X26: =IF(ISNUMBER(SEARCH('Data Entry'!$J$3,$Y26)),MAX($X$1:$X25)+1,0) -> 0 | Y26: ATLAS ICE (Cambodia) Co., Ltd | Z26: =IFERROR(VLOOKUP(ROWS($Z$2:$Z26),Table4[[Nub2]:[Supplied Name]],2,0),"") | AA26: =OFFSET($Z$2,,,COUNTIF($Z$2:$Z$25,"?*")) -> #REF! | AC26: =IF(ISNUMBER(SEARCH('Data Entry'!$J$3,$AE26)),MAX($AC$1:$AC25)+1,0) -> 0 | AD26: =IF(ISNUMBER(SEARCH('Data Entry'!$J$3,$AE26)),MAX($AD$1:$AD25)+1,0) -> 0 | AF26: =IFERROR(VLOOKUP(ROWS($Z$2:$Z26),Table5[[#All],[Nub2]:[Location ]],2,0),"") | AG26: =OFFSET($AF$2,,,COUNTIF($AF$2:$AF$25,"?*")) -> #REF!
A27: {=ROW(26:26)} -> 26 | B27: HF-0004 | C27: 900032 | D27: STIR FRIED MINCED CHICKEN HOT BASIL WITH RICE (បាយ​ សាច់មាន់ចិញ្រ្ចាំឆាម្រះព្រៅ) | F27: CENTRAL KITCHEN | G27: FOOD | H27: Khmer Food | I27: BOX | J27: 1BOX*1Portion | K27: 1.2984 | M27: 1 | N27: 10 | O27: =IF(ISNUMBER(SEARCH('Data Entry'!$J$3,$Q27)),MAX($O$1:$O26)+1,0) -> 0 | P27: =IF(ISNUMBER(SEARCH('Data Entry'!$J$3,$Q27)),MAX($P$1:$P26)+1,0) -> 0 | Q27: =Table2[[#This Row],[Item Name ]] -> STIR FRIED MINCED CHICKEN HOT BASIL WITH RICE (បាយ​ សាច់មាន់ចិញ្រ្ចាំឆាម្រះព្រៅ) | R27: =IFERROR(VLOOKUP(ROWS($R$2:$R27),Table2[[Nub2]:[Name]],2,0),"") | W27: =IF(ISNUMBER(SEARCH('Data Entry'!$J$3,$Y27)),MAX($W$1:$W26)+1,0) -> 0 | X27: =IF(ISNUMBER(SEARCH('Data Entry'!$J$3,$Y27)),MAX($X$1:$X26)+1,0) -> 0 | Y27: ATTWOOD IMPORT EXPORT CO., LTD | Z27: =IFERROR(VLOOKUP(ROWS($Z$2:$Z27),Table4[[Nub2]:[Supplied Name]],2,0),"") | AA27: =OFFSET($Z$2,,,COUNTIF($Z$2:$Z$25,"?*")) -> #REF! | AC27: =IF(ISNUMBER(SEARCH('Data Entry'!$J$3,$AE27)),MAX($AC$1:$AC26)+1,0) -> 0 | AD27: =IF(ISNUMBER(SEARCH('Data Entry'!$J$3,$AE27)),MAX($AD$1:$AD26)+1,0) -> 0 | AF27: =IFERROR(VLOOKUP(ROWS($Z$2:$Z27),Table5[[#All],[Nub2]:[Location ]],2,0),"") | AG27: =OFFSET($AF$2,,,COUNTIF($AF$2:$AF$25,"?*")) -> #REF!
A28: {=ROW(27:27)} -> 27 | B28: HF-0005 | C28: 900028 | D28: STIR FRIED MINCED PORK EGGPLANT WITH RICE (បាយ សាច់ជ្រូកចិញ្ច្រាំឆាត្រប់វែង) | F28: CENTRAL KITCHEN | G28: FOOD | H28: Khmer Food | I28: BOX | J28: 1BOX*1Portion | K28: 1.0104 | M28: 1 | N28: 10 | O28: =IF(ISNUMBER(SEARCH('Data Entry'!$J$3,$Q28)),MAX($O$1:$O27)+1,0) -> 0 | P28: =IF(ISNUMBER(SEARCH('Data Entry'!$J$3,$Q28)),MAX($P$1:$P27)+1,0) -> 0 | Q28: =Table2[[#This Row],[Item Name ]] -> STIR FRIED MINCED PORK EGGPLANT WITH RICE (បាយ សាច់ជ្រូកចិញ្ច្រាំឆាត្រប់វែង) | R28: =IFERROR(VLOOKUP(ROWS($R$2:$R28),Table2[[Nub2]:[Name]],2,0),"") | W28: =IF(ISNUMBER(SEARCH('Data Entry'!$J$3,$Y28)),MAX($W$1:$W27)+1,0) -> 0 | X28: =IF(ISNUMBER(SEARCH('Data Entry'!$J$3,$Y28)),MAX($X$1:$X27)+1,0) -> 0 | Y28: AUS KHMER IMPORT EXPORT CO.,LTD | Z28: =IFERROR(VLOOKUP(ROWS($Z$2:$Z28),Table4[[Nub2]:[Supplied Name]],2,0),"") | AA28: =OFFSET($Z$2,,,COUNTIF($Z$2:$Z$25,"?*")) -> #REF! | AC28: =IF(ISNUMBER(SEARCH('Data Entry'!$J$3,$AE28)),MAX($AC$1:$AC27)+1,0) -> 0 | AD28: =IF(ISNUMBER(SEARCH('Data Entry'!$J$3,$AE28)),MAX($AD$1:$AD27)+1,0) -> 0 | AF28: =IFERROR(VLOOKUP(ROWS($Z$2:$Z28),Table5[[#All],[Nub2]:[Location ]],2,0),"") | AG28: =OFFSET($AF$2,,,COUNTIF($AF$2:$AF$25,"?*")) -> #REF!
A29: {=ROW(28:28)} -> 28 | B29: HF-0006 | C29: 900025 | D29: HAINANESE CHICKEN WITH RICE (បាយ មាន់ហៃណាំ) | F29: CENTRAL KITCHEN | G29: FOOD | H29: Khmer Food | I29: BOX | J29: 1BOX*1Portion | K29: 1.0584 | M29: 1 | N29: 10 | O29: =IF(ISNUMBER(SEARCH('Data Entry'!$J$3,$Q29)),MAX($O$1:$O28)+1,0) -> 0 | P29: =IF(ISNUMBER(SEARCH('Data Entry'!$J$3,$Q29)),MAX($P$1:$P28)+1,0) -> 0 | Q29: =Table2[[#This Row],[Item Name ]] -> HAINANESE CHICKEN WITH RICE (បាយ មាន់ហៃណាំ) | R29: =IFERROR(VLOOKUP(ROWS($R$2:$R29),Table2[[Nub2]:[Name]],2,0),"") | W29: =IF(ISNUMBER(SEARCH('Data Entry'!$J$3,$Y29)),MAX($W$1:$W28)+1,0) -> 0 | X29: =IF(ISNUMBER(SEARCH('Data Entry'!$J$3,$Y29)),MAX($X$1:$X28)+1,0) -> 0 | Y29: AXION Printing & Supplies Material | Z29: =IFERROR(VLOOKUP(ROWS($Z$2:$Z29),Table4[[Nub2]:[Supplied Name]],2,0),"") | AA29: =OFFSET($Z$2,,,COUNTIF($Z$2:$Z$25,"?*")) -> #REF! | AC29: =IF(ISNUMBER(SEARCH('Data Entry'!$J$3,$AE29)),MAX($AC$1:$AC28)+1,0) -> 0 | AD29: =IF(ISNUMBER(SEARCH('Data Entry'!$J$3,$AE29)),MAX($AD$1:$AD28)+1,0) -> 0 | AF29: =IFERROR(VLOOKUP(ROWS($Z$2:$Z29),Table5[[#All],[Nub2]:[Location ]],2,0),"") | AG29: =OFFSET($AF$2,,,COUNTIF($AF$2:$AF$25,"?*")) -> #REF!
A30: {=ROW(29:29)} -> 29 | B30: HF-0007 | C30: 900030 | D30: ROASTED CHICKEN WITH RICE (បាយ មាន់ខ្វៃ) | F30: CENTRAL KITCHEN | G30: FOOD | H30: Khmer Food | I30: BOX | J30: 1BOX*1Portion | K30: 1.07 | M30: 1 | N30: 10 | O30: =IF(ISNUMBER(SEARCH('Data Entry'!$J$3,$Q30)),MAX($O$1:$O29)+1,0) -> 0 | P30: =IF(ISNUMBER(SEARCH('Data Entry'!$J$3,$Q30)),MAX($P$1:$P29)+1,0) -> 0 | Q30: =Table2[[#This Row],[Item Name ]] -> ROASTED CHICKEN WITH RICE (បាយ មាន់ខ្វៃ) | R30: =IFERROR(VLOOKUP(ROWS($R$2:$R30),Table2[[Nub2]:[Name]],2,0),"") | W30: =IF(ISNUMBER(SEARCH('Data Entry'!$J$3,$Y30)),MAX($W$1:$W29)+1,0) -> 0 | X30: =IF(ISNUMBER(SEARCH('Data Entry'!$J$3,$Y30)),MAX($X$1:$X29)+1,0) -> 0 | Y30: Adalloon Balloon and Party Supplies | Z30: =IFERROR(VLOOKUP(ROWS($Z$2:$Z30),Table4[[Nub2]:[Supplied Name]],2,0),"") | AA30: =OFFSET($Z$2,,,COUNTIF($Z$2:$Z$25,"?*")) -> #REF! | AC30: =IF(ISNUMBER(SEARCH('Data Entry'!$J$3,$AE30)),MAX($AC$1:$AC29)+1,0) -> 0 | AD30: =IF(ISNUMBER(SEARCH('Data Entry'!$J$3,$AE30)),MAX($AD$1:$AD29)+1,0) -> 0 | AF30: =IFERROR(VLOOKUP(ROWS($Z$2:$Z30),Table5[[#All],[Nub2]:[Location ]],2,0),"") | AG30: =OFFSET($AF$2,,,COUNTIF($AF$2:$AF$25,"?*")) -> #REF!
A31: {=ROW(30:30)} -> 30 | B31: HF-0008 | C31: 900031 | D31: ROASTED DUCK WITH RICE (បាយ ទាខ្វៃ) | F31: CENTRAL KITCHEN | G31: FOOD | H31: Khmer Food | I31: BOX | J31: 1BOX*1Portion | K31: 1.4784 | M31: 1 | N31: 10 | O31: =IF(ISNUMBER(SEARCH('Data Entry'!$J$3,$Q31)),MAX($O$1:$O30)+1,0) -> 0 | P31: =IF(ISNUMBER(SEARCH('Data Entry'!$J$3,$Q31)),MAX($P$1:$P30)+1,0) -> 0 | Q31: =Table2[[#This Row],[Item Name ]] -> ROASTED DUCK WITH RICE (បាយ ទាខ្វៃ) | R31: =IFERROR(VLOOKUP(ROWS($R$2:$R31),Table2[[Nub2]:[Name]],2,0),"") | W31: =IF(ISNUMBER(SEARCH('Data Entry'!$J$3,$Y31)),MAX($W$1:$W30)+1,0) -> 0 | X31: =IF(ISNUMBER(SEARCH('Data Entry'!$J$3,$Y31)),MAX($X$1:$X30)+1,0) -> 0 | Y31: Alphapeak Co., Ltd | Z31: =IFERROR(VLOOKUP(ROWS($Z$2:$Z31),Table4[[Nub2]:[Supplied Name]],2,0),"") | AA31: =OFFSET($Z$2,,,COUNTIF($Z$2:$Z$25,"?*")) -> #REF! | AC31: =IF(ISNUMBER(SEARCH('Data Entry'!$J$3,$AE31)),MAX($AC$1:$AC30)+1,0) -> 0 | AD31: =IF(ISNUMBER(SEARCH('Data Entry'!$J$3,$AE31)),MAX($AD$1:$AD30)+1,0) -> 0 | AF31: =IFERROR(VLOOKUP(ROWS($Z$2:$Z31),Table5[[#All],[Nub2]:[Location ]],2,0),"") | AG31: =OFFSET($AF$2,,,COUNTIF($AF$2:$AF$25,"?*")) -> #REF!
A32: {=ROW(31:31)} -> 31 | B32: HF-0009 | C32: 900286 | D32: ROATED PORK CHAR SIEW WITH RICE (បាយ សាច់ជ្រូកសាស៊ីវ) | F32: CENTRAL KITCHEN | G32: FOOD | H32: Khmer Food | I32: BOX | J32: 1BOX*1Portion | K32: 1.476 | M32: 1 | N32: 10 | O32: =IF(ISNUMBER(SEARCH('Data Entry'!$J$3,$Q32)),MAX($O$1:$O31)+1,0) -> 0 | P32: =IF(ISNUMBER(SEARCH('Data Entry'!$J$3,$Q32)),MAX($P$1:$P31)+1,0) -> 0 | Q32: =Table2[[#This Row],[Item Name ]] -> ROATED PORK CHAR SIEW WITH RICE (បាយ សាច់ជ្រូកសាស៊ីវ) | R32: =IFERROR(VLOOKUP(ROWS($R$2:$R32),Table2[[Nub2]:[Name]],2,0),"") | W32: =IF(ISNUMBER(SEARCH('Data Entry'!$J$3,$Y32)),MAX($W$1:$W31)+1,0) -> 0 | X32: =IF(ISNUMBER(SEARCH('Data Entry'!$J$3,$Y32)),MAX($X$1:$X31)+1,0) -> 0 | Y32: American Chamberof Commerce in Cambodia | Z32: =IFERROR(VLOOKUP(ROWS($Z$2:$Z32),Table4[[Nub2]:[Supplied Name]],2,0),"") | AA32: =OFFSET($Z$2,,,COUNTIF($Z$2:$Z$25,"?*")) -> #REF! | AC32: =IF(ISNUMBER(SEARCH('Data Entry'!$J$3,$AE32)),MAX($AC$1:$AC31)+1,0) -> 0 | AD32: =IF(ISNUMBER(SEARCH('Data Entry'!$J$3,$AE32)),MAX($AD$1:$AD31)+1,0) -> 0 | AF32: =IFERROR(VLOOKUP(ROWS($Z$2:$Z32),Table5[[#All],[Nub2]:[Location ]],2,0),"") | AG32: =OFFSET($AF$2,,,COUNTIF($AF$2:$AF$25,"?*")) -> #REF!
A33: {=ROW(32:32)} -> 32 | B33: HF-0010 | C33: 900038 | D33: ROATED PORK BELLY WITH RICE (បាយ សាច់ជ្រូក៣ជាន់) | F33: CENTRAL KITCHEN | G33: FOOD | H33: Khmer Food | I33: BOX | J33: 1BOX*1Portion | K33: 1.092 | M33: 1 | N33: 10 | O33: =IF(ISNUMBER(SEARCH('Data Entry'!$J$3,$Q33)),MAX($O$1:$O32)+1,0) -> 0 | P33: =IF(ISNUMBER(SEARCH('Data Entry'!$J$3,$Q33)),MAX($P$1:$P32)+1,0) -> 0 | Q33: =Table2[[#This Row],[Item Name ]] -> ROATED PORK BELLY WITH RICE (បាយ សាច់ជ្រូក៣ជាន់) | R33: =IFERROR(VLOOKUP(ROWS($R$2:$R33),Table2[[Nub2]:[Name]],2,0),"") | W33: =IF(ISNUMBER(SEARCH('Data Entry'!$J$3,$Y33)),MAX($W$1:$W32)+1,0) -> 0 | X33: =IF(ISNUMBER(SEARCH('Data Entry'!$J$3,$Y33)),MAX($X$1:$X32)+1,0) -> 0 | Y33: Angkor Art Printing House | Z33: =IFERROR(VLOOKUP(ROWS($Z$2:$Z33),Table4[[Nub2]:[Supplied Name]],2,0),"") | AA33: =OFFSET($Z$2,,,COUNTIF($Z$2:$Z$25,"?*")) -> #REF! | AC33: =IF(ISNUMBER(SEARCH('Data Entry'!$J$3,$AE33)),MAX($AC$1:$AC32)+1,0) -> 0 | AD33: =IF(ISNUMBER(SEARCH('Data Entry'!$J$3,$AE33)),MAX($AD$1:$AD32)+1,0) -> 0 | AF33: =IFERROR(VLOOKUP(ROWS($Z$2:$Z33),Table5[[#All],[Nub2]:[Location ]],2,0),"") | AG33: =OFFSET($AF$2,,,COUNTIF($AF$2:$AF$25,"?*")) -> #REF!
A34: {=ROW(33:33)} -> 33 | B34: HF-0011 | C34: 900036 | D34: THICK CHICKEN CURRY (ការីសាច់មាន់) ខាប់ | F34: CENTRAL KITCHEN | G34: FOOD | H34: Khmer Food | I34: BOX | J34: 1BOX*1Portion | K34: 1.3824 | M34: 1 | N34: 10 | O34: =IF(ISNUMBER(SEARCH('Data Entry'!$J$3,$Q34)),MAX($O$1:$O33)+1,0) -> 0 | P34: =IF(ISNUMBER(SEARCH('Data Entry'!$J$3,$Q34)),MAX($P$1:$P33)+1,0) -> 0 | Q34: =Table2[[#This Row],[Item Name ]] -> THICK CHICKEN CURRY (ការីសាច់មាន់) ខាប់ | R34: =IFERROR(VLOOKUP(ROWS($R$2:$R34),Table2[[Nub2]:[Name]],2,0),"") | W34: =IF(ISNUMBER(SEARCH('Data Entry'!$J$3,$Y34)),MAX($W$1:$W33)+1,0) -> 0 | X34: =IF(ISNUMBER(SEARCH('Data Entry'!$J$3,$Y34)),MAX($X$1:$X33)+1,0) -> 0 | Y34: Angkor Shoes Making | Z34: =IFERROR(VLOOKUP(ROWS($Z$2:$Z34),Table4[[Nub2]:[Supplied Name]],2,0),"") | AA34: =OFFSET($Z$2,,,COUNTIF($Z$2:$Z$25,"?*")) -> #REF! | AC34: =IF(ISNUMBER(SEARCH('Data Entry'!$J$3,$AE34)),MAX($AC$1:$AC33)+1,0) -> 0 | AD34: =IF(ISNUMBER(SEARCH('Data Entry'!$J$3,$AE34)),MAX($AD$1:$AD33)+1,0) -> 0 | AF34: =IFERROR(VLOOKUP(ROWS($Z$2:$Z34),Table5[[#All],[Nub2]:[Location ]],2,0),"") | AG34: =OFFSET($AF$2,,,COUNTIF($AF$2:$AF$25,"?*")) -> #REF!
A35: {=ROW(34:34)} -> 34 | B35: HF-0012 | C35: 900035 | D35: THICK BEEF CURRY SARAMAN (ការីសារ៉ាម៉ាន់សាច់គោ) ខាប់ | F35: CENTRAL KITCHEN | G35: FOOD | H35: Khmer Food | I35: BOX | J35: 1BOX*1Portion | K35: 1.908 | M35: 1 | N35: 10 | O35: =IF(ISNUMBER(SEARCH('Data Entry'!$J$3,$Q35)),MAX($O$1:$O34)+1,0) -> 0 | P35: =IF(ISNUMBER(SEARCH('Data Entry'!$J$3,$Q35)),MAX($P$1:$P34)+1,0) -> 0 | Q35: =Table2[[#This Row],[Item Name ]] -> THICK BEEF CURRY SARAMAN (ការីសារ៉ាម៉ាន់សាច់គោ) ខាប់ | R35: =IFERROR(VLOOKUP(ROWS($R$2:$R35),Table2[[Nub2]:[Name]],2,0),"") | W35: =IF(ISNUMBER(SEARCH('Data Entry'!$J$3,$Y35)),MAX($W$1:$W34)+1,0) -> 0 | X35: =IF(ISNUMBER(SEARCH('Data Entry'!$J$3,$Y35)),MAX($X$1:$X34)+1,0) -> 0 | Y35: Anon Studio | Z35: =IFERROR(VLOOKUP(ROWS($Z$2:$Z35),Table4[[Nub2]:[Supplied Name]],2,0),"") | AA35: =OFFSET($Z$2,,,COUNTIF($Z$2:$Z$25,"?*")) -> #REF! | AC35: =IF(ISNUMBER(SEARCH('Data Entry'!$J$3,$AE35)),MAX($AC$1:$AC34)+1,0) -> 0 | AD35: =IF(ISNUMBER(SEARCH('Data Entry'!$J$3,$AE35)),MAX($AD$1:$AD34)+1,0) -> 0 | AF35: =IFERROR(VLOOKUP(ROWS($Z$2:$Z35),Table5[[#All],[Nub2]:[Location ]],2,0),"") | AG35: =OFFSET($AF$2,,,COUNTIF($AF$2:$AF$25,"?*")) -> #REF!
A36: {=ROW(35:35)} -> 35 | B36: HF-0016 | C36: 900033 | D36: GRILLED PORK WITH RICE (បាយ សាច់ជ្រូកអាំង) | F36: CENTRAL KITCHEN | G36: FOOD | H36: Khmer Food | I36: BOX | J36: 1BOX*1Portion | K36: 1.212 | M36: 1 | N36: 10 | O36: =IF(ISNUMBER(SEARCH('Data Entry'!$J$3,$Q36)),MAX($O$1:$O35)+1,0) -> 0 | P36: =IF(ISNUMBER(SEARCH('Data Entry'!$J$3,$Q36)),MAX($P$1:$P35)+1,0) -> 0 | Q36: =Table2[[#This Row],[Item Name ]] -> GRILLED PORK WITH RICE (បាយ សាច់ជ្រូកអាំង) | R36: =IFERROR(VLOOKUP(ROWS($R$2:$R36),Table2[[Nub2]:[Name]],2,0),"") | W36: =IF(ISNUMBER(SEARCH('Data Entry'!$J$3,$Y36)),MAX($W$1:$W35)+1,0) -> 0 | X36: =IF(ISNUMBER(SEARCH('Data Entry'!$J$3,$Y36)),MAX($X$1:$X35)+1,0) -> 0 | Y36: Anorng Interior Design | Z36: =IFERROR(VLOOKUP(ROWS($Z$2:$Z36),Table4[[Nub2]:[Supplied Name]],2,0),"") | AA36: =OFFSET($Z$2,,,COUNTIF($Z$2:$Z$25,"?*")) -> #REF! | AC36: =IF(ISNUMBER(SEARCH('Data Entry'!$J$3,$AE36)),MAX($AC$1:$AC35)+1,0) -> 0 | AD36: =IF(ISNUMBER(SEARCH('Data Entry'!$J$3,$AE36)),MAX($AD$1:$AD35)+1,0) -> 0 | AF36: =IFERROR(VLOOKUP(ROWS($Z$2:$Z36),Table5[[#All],[Nub2]:[Location ]],2,0),"") | AG36: =OFFSET($AF$2,,,COUNTIF($AF$2:$AF$25,"?*")) -> #REF!
A37: {=ROW(36:36)} -> 36 | B37: HF-0017 | C37: 900037 | D37: HIKO FRIED RICE (បាយឆា HIKO) | F37: CENTRAL KITCHEN | G37: FOOD | H37: Khmer Food | I37: BOX | J37: 1BOX*1Portion | K37: 1.68 | M37: 1 | N37: 10 | O37: =IF(ISNUMBER(SEARCH('Data Entry'!$J$3,$Q37)),MAX($O$1:$O36)+1,0) -> 0 | P37: =IF(ISNUMBER(SEARCH('Data Entry'!$J$3,$Q37)),MAX($P$1:$P36)+1,0) -> 0 | Q37: =Table2[[#This Row],[Item Name ]] -> HIKO FRIED RICE (បាយឆា HIKO) | R37: =IFERROR(VLOOKUP(ROWS($R$2:$R37),Table2[[Nub2]:[Name]],2,0),"") | W37: =IF(ISNUMBER(SEARCH('Data Entry'!$J$3,$Y37)),MAX($W$1:$W36)+1,0) -> 0 | X37: =IF(ISNUMBER(SEARCH('Data Entry'!$J$3,$Y37)),MAX($X$1:$X36)+1,0) -> 0 | Y37: Apsara Modern Furniture Shop | Z37: =IFERROR(VLOOKUP(ROWS($Z$2:$Z37),Table4[[Nub2]:[Supplied Name]],2,0),"") | AA37: =OFFSET($Z$2,,,COUNTIF($Z$2:$Z$25,"?*")) -> #REF! | AC37: =IF(ISNUMBER(SEARCH('Data Entry'!$J$3,$AE37)),MAX($AC$1:$AC36)+1,0) -> 0 | AD37: =IF(ISNUMBER(SEARCH('Data Entry'!$J$3,$AE37)),MAX($AD$1:$AD36)+1,0) -> 0 | AF37: =IFERROR(VLOOKUP(ROWS($Z$2:$Z37),Table5[[#All],[Nub2]:[Location ]],2,0),"") | AG37: =OFFSET($AF$2,,,COUNTIF($AF$2:$AF$25,"?*")) -> #REF!
A38: {=ROW(37:37)} -> 37 | B38: I-0001 | C38: 900268 | D38: White Sugar (Bag*50Kg) | F38: CENTRAL KITCHEN | G38: FOOD | H38: Ingredients | I38: KG | J38: 1BAG*50KG | K38: 0.96 | M38: 1 | N38: 10 | O38: =IF(ISNUMBER(SEARCH('Data Entry'!$J$3,$Q38)),MAX($O$1:$O37)+1,0) -> 0 | P38: =IF(ISNUMBER(SEARCH('Data Entry'!$J$3,$Q38)),MAX($P$1:$P37)+1,0) -> 0 | Q38: =Table2[[#This Row],[Item Name ]] -> White Sugar (Bag*50Kg) | R38: =IFERROR(VLOOKUP(ROWS($R$2:$R38),Table2[[Nub2]:[Name]],2,0),"") | W38: =IF(ISNUMBER(SEARCH('Data Entry'!$J$3,$Y38)),MAX($W$1:$W37)+1,0) -> 0 | X38: =IF(ISNUMBER(SEARCH('Data Entry'!$J$3,$Y38)),MAX($X$1:$X37)+1,0) -> 0 | Y38: Aqua Filter | Z38: =IFERROR(VLOOKUP(ROWS($Z$2:$Z38),Table4[[Nub2]:[Supplied Name]],2,0),"") | AA38: =OFFSET($Z$2,,,COUNTIF($Z$2:$Z$25,"?*")) -> #REF! | AC38: =IF(ISNUMBER(SEARCH('Data Entry'!$J$3,$AE38)),MAX($AC$1:$AC37)+1,0) -> 0 | AD38: =IF(ISNUMBER(SEARCH('Data Entry'!$J$3,$AE38)),MAX($AD$1:$AD37)+1,0) -> 0 | AF38: =IFERROR(VLOOKUP(ROWS($Z$2:$Z38),Table5[[#All],[Nub2]:[Location ]],2,0),"") | AG38: =OFFSET($AF$2,,,COUNTIF($AF$2:$AF$25,"?*")) -> #REF!
A39: {=ROW(38:38)} -> 38 | B39: I-0017 | C39: 900269 | D39: Cooking Oil 18LTR (ប្រេងឆា) | F39: CENTRAL KITCHEN | G39: FOOD | H39: Ingredients | I39: TIN | J39: TIN*18LTR | K39: 36 | L39: 36 | M39: 1 | N39: 10 | O39: =IF(ISNUMBER(SEARCH('Data Entry'!$J$3,$Q39)),MAX($O$1:$O38)+1,0) -> 0 | P39: =IF(ISNUMBER(SEARCH('Data Entry'!$J$3,$Q39)),MAX($P$1:$P38)+1,0) -> 0 | Q39: =Table2[[#This Row],[Item Name ]] -> Cooking Oil 18LTR (ប្រេងឆា) | R39: =IFERROR(VLOOKUP(ROWS($R$2:$R39),Table2[[Nub2]:[Name]],2,0),"") | W39: =IF(ISNUMBER(SEARCH('Data Entry'!$J$3,$Y39)),MAX($W$1:$W38)+1,0) -> 0 | X39: =IF(ISNUMBER(SEARCH('Data Entry'!$J$3,$Y39)),MAX($X$1:$X38)+1,0) -> 0 | Y39: Arome Khmer | Z39: =IFERROR(VLOOKUP(ROWS($Z$2:$Z39),Table4[[Nub2]:[Supplied Name]],2,0),"") | AA39: =OFFSET($Z$2,,,COUNTIF($Z$2:$Z$25,"?*")) -> #REF! | AC39: =IF(ISNUMBER(SEARCH('Data Entry'!$J$3,$AE39)),MAX($AC$1:$AC38)+1,0) -> 0 | AD39: =IF(ISNUMBER(SEARCH('Data Entry'!$J$3,$AE39)),MAX($AD$1:$AD38)+1,0) -> 0 | AF39: =IFERROR(VLOOKUP(ROWS($Z$2:$Z39),Table5[[#All],[Nub2]:[Location ]],2,0),"") | AG39: =OFFSET($AF$2,,,COUNTIF($AF$2:$AF$25,"?*")) -> #REF!
A40: {=ROW(39:39)} -> 39 | B40: I-0050 | C40: 900294 | D40: Roasted White Sesame Seed (ល្ងសលីង) | F40: CENTRAL KITCHEN | G40: FOOD | H40: Semi-Product | I40: KG | J40: KG | K40: 4.92 | M40: 1 | N40: 10 | O40: =IF(ISNUMBER(SEARCH('Data Entry'!$J$3,$Q40)),MAX($O$1:$O39)+1,0) -> 0 | P40: =IF(ISNUMBER(SEARCH('Data Entry'!$J$3,$Q40)),MAX($P$1:$P39)+1,0) -> 0 | Q40: =Table2[[#This Row],[Item Name ]] -> Roasted White Sesame Seed (ល្ងសលីង) | R40: =IFERROR(VLOOKUP(ROWS($R$2:$R40),Table2[[Nub2]:[Name]],2,0),"") | W40: =IF(ISNUMBER(SEARCH('Data Entry'!$J$3,$Y40)),MAX($W$1:$W39)+1,0) -> 0 | X40: =IF(ISNUMBER(SEARCH('Data Entry'!$J$3,$Y40)),MAX($X$1:$X39)+1,0) -> 0 | Y40: Asora Printing | Z40: =IFERROR(VLOOKUP(ROWS($Z$2:$Z40),Table4[[Nub2]:[Supplied Name]],2,0),"") | AA40: =OFFSET($Z$2,,,COUNTIF($Z$2:$Z$25,"?*")) -> #REF! | AC40: =IF(ISNUMBER(SEARCH('Data Entry'!$J$3,$AE40)),MAX($AC$1:$AC39)+1,0) -> 0 | AD40: =IF(ISNUMBER(SEARCH('Data Entry'!$J$3,$AE40)),MAX($AD$1:$AD39)+1,0) -> 0 | AF40: =IFERROR(VLOOKUP(ROWS($Z$2:$Z40),Table5[[#All],[Nub2]:[Location ]],2,0),"") | AG40: =OFFSET($AF$2,,,COUNTIF($AF$2:$AF$25,"?*")) -> #REF!
A41: {=ROW(40:40)} -> 40 | B41: I-0070 | C41: 900266 | D41: Heinz Tomato Sauce 5Kg | F41: CENTRAL KITCHEN | G41: FOOD | H41: Ingredients | I41: LTR | J41: GALLON*5LTR | K41: 2.99 | L41: 2.99 | M41: 1 | N41: 10 | O41: =IF(ISNUMBER(SEARCH('Data Entry'!$J$3,$Q41)),MAX($O$1:$O40)+1,0) -> 0 | P41: =IF(ISNUMBER(SEARCH('Data Entry'!$J$3,$Q41)),MAX($P$1:$P40)+1,0) -> 0 | Q41: =Table2[[#This Row],[Item Name ]] -> Heinz Tomato Sauce 5Kg | R41: =IFERROR(VLOOKUP(ROWS($R$2:$R41),Table2[[Nub2]:[Name]],2,0),"") | W41: =IF(ISNUMBER(SEARCH('Data Entry'!$J$3,$Y41)),MAX($W$1:$W40)+1,0) -> 0 | X41: =IF(ISNUMBER(SEARCH('Data Entry'!$J$3,$Y41)),MAX($X$1:$X40)+1,0) -> 0 | Y41: Auto Wash Commercial Laundry Solution | Z41: =IFERROR(VLOOKUP(ROWS($Z$2:$Z41),Table4[[Nub2]:[Supplied Name]],2,0),"") | AA41: =OFFSET($Z$2,,,COUNTIF($Z$2:$Z$25,"?*")) -> #REF! | AC41: =IF(ISNUMBER(SEARCH('Data Entry'!$J$3,$AE41)),MAX($AC$1:$AC40)+1,0) -> 0 | AD41: =IF(ISNUMBER(SEARCH('Data Entry'!$J$3,$AE41)),MAX($AD$1:$AD40)+1,0) -> 0 | AF41: =IFERROR(VLOOKUP(ROWS($Z$2:$Z41),Table5[[#All],[Nub2]:[Location ]],2,0),"") | AG41: =OFFSET($AF$2,,,COUNTIF($AF$2:$AF$25,"?*")) -> #REF!
A42: {=ROW(41:41)} -> 41 | B42: I-0099 | C42: 900270 | D42: Thai Salt (អំបិលកញ្ចប់) | F42: CENTRAL KITCHEN | G42: FOOD | H42: Ingredients | I42: PKT | J42: 1PKT*1KG | K42: 0.72 | M42: 1 | N42: 10 | O42: =IF(ISNUMBER(SEARCH('Data Entry'!$J$3,$Q42)),MAX($O$1:$O41)+1,0) -> 0 | P42: =IF(ISNUMBER(SEARCH('Data Entry'!$J$3,$Q42)),MAX($P$1:$P41)+1,0) -> 0 | Q42: =Table2[[#This Row],[Item Name ]] -> Thai Salt (អំបិលកញ្ចប់) | R42: =IFERROR(VLOOKUP(ROWS($R$2:$R42),Table2[[Nub2]:[Name]],2,0),"") | W42: =IF(ISNUMBER(SEARCH('Data Entry'!$J$3,$Y42)),MAX($W$1:$W41)+1,0) -> 0 | X42: =IF(ISNUMBER(SEARCH('Data Entry'!$J$3,$Y42)),MAX($X$1:$X41)+1,0) -> 0 | Y42: Azaylla Cambodia Co., Ltd | Z42: =IFERROR(VLOOKUP(ROWS($Z$2:$Z42),Table4[[Nub2]:[Supplied Name]],2,0),"") | AA42: =OFFSET($Z$2,,,COUNTIF($Z$2:$Z$25,"?*")) -> #REF! | AC42: =IF(ISNUMBER(SEARCH('Data Entry'!$J$3,$AE42)),MAX($AC$1:$AC41)+1,0) -> 0 | AD42: =IF(ISNUMBER(SEARCH('Data Entry'!$J$3,$AE42)),MAX($AD$1:$AD41)+1,0) -> 0 | AF42: =IFERROR(VLOOKUP(ROWS($Z$2:$Z42),Table5[[#All],[Nub2]:[Location ]],2,0),"") | AG42: =OFFSET($AF$2,,,COUNTIF($AF$2:$AF$25,"?*")) -> #REF!
A43: {=ROW(42:42)} -> 42 | B43: I-0177 | C43: 900279 | D43: Baking Soda | F43: CENTRAL KITCHEN | G43: FOOD | H43: Ingredients | I43: BOX | J43: 1BOX*500GM | K43: 3 | M43: 1 | N43: 10 | O43: =IF(ISNUMBER(SEARCH('Data Entry'!$J$3,$Q43)),MAX($O$1:$O42)+1,0) -> 0 | P43: =IF(ISNUMBER(SEARCH('Data Entry'!$J$3,$Q43)),MAX($P$1:$P42)+1,0) -> 0 | Q43: =Table2[[#This Row],[Item Name ]] -> Baking Soda | R43: =IFERROR(VLOOKUP(ROWS($R$2:$R43),Table2[[Nub2]:[Name]],2,0),"") | W43: =IF(ISNUMBER(SEARCH('Data Entry'!$J$3,$Y43)),MAX($W$1:$W42)+1,0) -> 0 | X43: =IF(ISNUMBER(SEARCH('Data Entry'!$J$3,$Y43)),MAX($X$1:$X42)+1,0) -> 0 | Y43: Azure Interior | Z43: =IFERROR(VLOOKUP(ROWS($Z$2:$Z43),Table4[[Nub2]:[Supplied Name]],2,0),"") | AA43: =OFFSET($Z$2,,,COUNTIF($Z$2:$Z$25,"?*")) -> #REF! | AC43: =IF(ISNUMBER(SEARCH('Data Entry'!$J$3,$AE43)),MAX($AC$1:$AC42)+1,0) -> 0 | AD43: =IF(ISNUMBER(SEARCH('Data Entry'!$J$3,$AE43)),MAX($AD$1:$AD42)+1,0) -> 0 | AF43: =IFERROR(VLOOKUP(ROWS($Z$2:$Z43),Table5[[#All],[Nub2]:[Location ]],2,0),"") | AG43: =OFFSET($AF$2,,,COUNTIF($AF$2:$AF$25,"?*")) -> #REF!
A44: {=ROW(43:43)} -> 43 | B44: I-0212 | C44: 900271 | D44: Best Food Mayonniase 3.5KG | F44: CENTRAL KITCHEN | G44: FOOD | H44: Ingredients | I44: TUB | J44: 1CTN*4TUB*3.5KG | K44: 22.8 | M44: 1 | N44: 10 | O44: =IF(ISNUMBER(SEARCH('Data Entry'!$J$3,$Q44)),MAX($O$1:$O43)+1,0) -> 0 | P44: =IF(ISNUMBER(SEARCH('Data Entry'!$J$3,$Q44)),MAX($P$1:$P43)+1,0) -> 0 | Q44: =Table2[[#This Row],[Item Name ]] -> Best Food Mayonniase 3.5KG | R44: =IFERROR(VLOOKUP(ROWS($R$2:$R44),Table2[[Nub2]:[Name]],2,0),"") | W44: =IF(ISNUMBER(SEARCH('Data Entry'!$J$3,$Y44)),MAX($W$1:$W43)+1,0) -> 0 | X44: =IF(ISNUMBER(SEARCH('Data Entry'!$J$3,$Y44)),MAX($X$1:$X43)+1,0) -> 0 | Y44: BELBEV ASIA CO., LTD | Z44: =IFERROR(VLOOKUP(ROWS($Z$2:$Z44),Table4[[Nub2]:[Supplied Name]],2,0),"") | AA44: =OFFSET($Z$2,,,COUNTIF($Z$2:$Z$25,"?*")) -> #REF! | AC44: =IF(ISNUMBER(SEARCH('Data Entry'!$J$3,$AE44)),MAX($AC$1:$AC43)+1,0) -> 0 | AD44: =IF(ISNUMBER(SEARCH('Data Entry'!$J$3,$AE44)),MAX($AD$1:$AD43)+1,0) -> 0 | AF44: =IFERROR(VLOOKUP(ROWS($Z$2:$Z44),Table5[[#All],[Nub2]:[Location ]],2,0),"") | AG44: =OFFSET($AF$2,,,COUNTIF($AF$2:$AF$25,"?*")) -> #REF!
A45: {=ROW(44:44)} -> 44 | B45: KF-0001 | C45: 900114 | D45: Raw Bulgogi Pork | F45: CENTRAL KITCHEN | G45: FOOD | H45: Semi-Product | I45: PKT | J45: 1PKT*1KG | K45: 5.76 | M45: 1 | N45: 10 | O45: =IF(ISNUMBER(SEARCH('Data Entry'!$J$3,$Q45)),MAX($O$1:$O44)+1,0) -> 0 | P45: =IF(ISNUMBER(SEARCH('Data Entry'!$J$3,$Q45)),MAX($P$1:$P44)+1,0) -> 0 | Q45: =Table2[[#This Row],[Item Name ]] -> Raw Bulgogi Pork | R45: =IFERROR(VLOOKUP(ROWS($R$2:$R45),Table2[[Nub2]:[Name]],2,0),"") | W45: =IF(ISNUMBER(SEARCH('Data Entry'!$J$3,$Y45)),MAX($W$1:$W44)+1,0) -> 0 | X45: =IF(ISNUMBER(SEARCH('Data Entry'!$J$3,$Y45)),MAX($X$1:$X44)+1,0) -> 0 | Y45: BETAGRO (CAMBODIA) COMPANY LIMITED | Z45: =IFERROR(VLOOKUP(ROWS($Z$2:$Z45),Table4[[Nub2]:[Supplied Name]],2,0),"") | AA45: =OFFSET($Z$2,,,COUNTIF($Z$2:$Z$25,"?*")) -> #REF!
A46: {=ROW(45:45)} -> 45 | B46: KF-0002 | C46: 900115 | D46: Raw Stir Fried Spicy Pork | F46: CENTRAL KITCHEN | G46: FOOD | H46: Semi-Product | I46: PKT | J46: 1PKT*1KG | K46: 6 | M46: 1 | N46: 10 | O46: =IF(ISNUMBER(SEARCH('Data Entry'!$J$3,$Q46)),MAX($O$1:$O45)+1,0) -> 0 | P46: =IF(ISNUMBER(SEARCH('Data Entry'!$J$3,$Q46)),MAX($P$1:$P45)+1,0) -> 0 | Q46: =Table2[[#This Row],[Item Name ]] -> Raw Stir Fried Spicy Pork | R46: =IFERROR(VLOOKUP(ROWS($R$2:$R46),Table2[[Nub2]:[Name]],2,0),"") | W46: =IF(ISNUMBER(SEARCH('Data Entry'!$J$3,$Y46)),MAX($W$1:$W45)+1,0) -> 0 | X46: =IF(ISNUMBER(SEARCH('Data Entry'!$J$3,$Y46)),MAX($X$1:$X45)+1,0) -> 0 | Y46: BHATTARAI KRISHNA | Z46: =IFERROR(VLOOKUP(ROWS($Z$2:$Z46),Table4[[Nub2]:[Supplied Name]],2,0),"") | AA46: =OFFSET($Z$2,,,COUNTIF($Z$2:$Z$25,"?*")) -> #REF!
A47: {=ROW(46:46)} -> 46 | B47: KF-0003 | C47: 900116 | D47: Raw Fried Japchae | F47: CENTRAL KITCHEN | G47: FOOD | H47: Semi-Product | I47: PKT | J47: 1PKT*1KG | K47: 3.6 | M47: 1 | N47: 10 | O47: =IF(ISNUMBER(SEARCH('Data Entry'!$J$3,$Q47)),MAX($O$1:$O46)+1,0) -> 0 | P47: =IF(ISNUMBER(SEARCH('Data Entry'!$J$3,$Q47)),MAX($P$1:$P46)+1,0) -> 0 | Q47: =Table2[[#This Row],[Item Name ]] -> Raw Fried Japchae | R47: =IFERROR(VLOOKUP(ROWS($R$2:$R47),Table2[[Nub2]:[Name]],2,0),"") | W47: =IF(ISNUMBER(SEARCH('Data Entry'!$J$3,$Y47)),MAX($W$1:$W46)+1,0) -> 0 | X47: =IF(ISNUMBER(SEARCH('Data Entry'!$J$3,$Y47)),MAX($X$1:$X46)+1,0) -> 0 | Y47: BK Tech Supply Co., Ltd | Z47: =IFERROR(VLOOKUP(ROWS($Z$2:$Z47),Table4[[Nub2]:[Supplied Name]],2,0),"") | AA47: =OFFSET($Z$2,,,COUNTIF($Z$2:$Z$25,"?*")) -> #REF!
A48: {=ROW(47:47)} -> 47 | B48: KF-0004 | C48: 900117 | D48: Raw Deep Fried Chicken | F48: CENTRAL KITCHEN | G48: FOOD | H48: Semi-Product | I48: PKT | J48: 1PKT*1KG | K48: 6 | M48: 1 | N48: 10 | O48: =IF(ISNUMBER(SEARCH('Data Entry'!$J$3,$Q48)),MAX($O$1:$O47)+1,0) -> 0 | P48: =IF(ISNUMBER(SEARCH('Data Entry'!$J$3,$Q48)),MAX($P$1:$P47)+1,0) -> 0 | Q48: =Table2[[#This Row],[Item Name ]] -> Raw Deep Fried Chicken | R48: =IFERROR(VLOOKUP(ROWS($R$2:$R48),Table2[[Nub2]:[Name]],2,0),"") | W48: =IF(ISNUMBER(SEARCH('Data Entry'!$J$3,$Y48)),MAX($W$1:$W47)+1,0) -> 0 | X48: =IF(ISNUMBER(SEARCH('Data Entry'!$J$3,$Y48)),MAX($X$1:$X47)+1,0) -> 0 | Y48: BK WORLD DEVELOPMENT CO., LTD | Z48: =IFERROR(VLOOKUP(ROWS($Z$2:$Z48),Table4[[Nub2]:[Supplied Name]],2,0),"") | AA48: =OFFSET($Z$2,,,COUNTIF($Z$2:$Z$25,"?*")) -> #REF!
A49: {=ROW(48:48)} -> 48 | B49: KF-0005 | C49: 900118 | D49: Raw Stir Fried Kimchi | F49: CENTRAL KITCHEN | G49: FOOD | H49: Semi-Product | I49: PKT | J49: 1PKT*1KG | K49: 5.76 | M49: 1 | N49: 10 | O49: =IF(ISNUMBER(SEARCH('Data Entry'!$J$3,$Q49)),MAX($O$1:$O48)+1,0) -> 0 | P49: =IF(ISNUMBER(SEARCH('Data Entry'!$J$3,$Q49)),MAX($P$1:$P48)+1,0) -> 0 | Q49: =Table2[[#This Row],[Item Name ]] -> Raw Stir Fried Kimchi | R49: =IFERROR(VLOOKUP(ROWS($R$2:$R49),Table2[[Nub2]:[Name]],2,0),"") | W49: =IF(ISNUMBER(SEARCH('Data Entry'!$J$3,$Y49)),MAX($W$1:$W48)+1,0) -> 0 | X49: =IF(ISNUMBER(SEARCH('Data Entry'!$J$3,$Y49)),MAX($X$1:$X48)+1,0) -> 0 | Y49: BKB Hotel Supply | Z49: =IFERROR(VLOOKUP(ROWS($Z$2:$Z49),Table4[[Nub2]:[Supplied Name]],2,0),"") | AA49: =OFFSET($Z$2,,,COUNTIF($Z$2:$Z$25,"?*")) -> #REF!
A50: {=ROW(49:49)} -> 49 | B50: KF-0006 | C50: 900119 | D50: Raw Deep Fried Kimmari | F50: CENTRAL KITCHEN | G50: FOOD | H50: Semi-Product | I50: PKT | J50: 1PKT*10PCS*40G | K50: 2.4 | M50: 1 | N50: 10 | O50: =IF(ISNUMBER(SEARCH('Data Entry'!$J$3,$Q50)),MAX($O$1:$O49)+1,0) -> 0 | P50: =IF(ISNUMBER(SEARCH('Data Entry'!$J$3,$Q50)),MAX($P$1:$P49)+1,0) -> 0 | Q50: =Table2[[#This Row],[Item Name ]] -> Raw Deep Fried Kimmari | R50: =IFERROR(VLOOKUP(ROWS($R$2:$R50),Table2[[Nub2]:[Name]],2,0),"") | W50: =IF(ISNUMBER(SEARCH('Data Entry'!$J$3,$Y50)),MAX($W$1:$W49)+1,0) -> 0 | X50: =IF(ISNUMBER(SEARCH('Data Entry'!$J$3,$Y50)),MAX($X$1:$X49)+1,0) -> 0 | Y50: BKB KITCHEN | Z50: =IFERROR(VLOOKUP(ROWS($Z$2:$Z50),Table4[[Nub2]:[Supplied Name]],2,0),"") | AA50: =OFFSET($Z$2,,,COUNTIF($Z$2:$Z$25,"?*")) -> #REF!
A51: {=ROW(50:50)} -> 50 | B51: KF-0007 | C51: 900120 | D51: Raw Cheese Corn Dog | F51: CENTRAL KITCHEN | G51: FOOD | H51: Semi-Product | I51: PKT | J51: 1PKT*6PCS*100G | K51: 4.9 | M51: 1 | N51: 10 | O51: =IF(ISNUMBER(SEARCH('Data Entry'!$J$3,$Q51)),MAX($O$1:$O50)+1,0) -> 0 | P51: =IF(ISNUMBER(SEARCH('Data Entry'!$J$3,$Q51)),MAX($P$1:$P50)+1,0) -> 0 | Q51: =Table2[[#This Row],[Item Name ]] -> Raw Cheese Corn Dog | R51: =IFERROR(VLOOKUP(ROWS($R$2:$R51),Table2[[Nub2]:[Name]],2,0),"") | W51: =IF(ISNUMBER(SEARCH('Data Entry'!$J$3,$Y51)),MAX($W$1:$W50)+1,0) -> 0 | X51: =IF(ISNUMBER(SEARCH('Data Entry'!$J$3,$Y51)),MAX($X$1:$X50)+1,0) -> 0 | Y51: BLACK BOX STUDIO | Z51: =IFERROR(VLOOKUP(ROWS($Z$2:$Z51),Table4[[Nub2]:[Supplied Name]],2,0),"") | AA51: =OFFSET($Z$2,,,COUNTIF($Z$2:$Z$25,"?*")) -> #REF!
A52: {=ROW(51:51)} -> 51 | B52: KF-0008 | C52: 900121 | D52: Raw Sausage Corn Dog | F52: RTE | G52: FOOD | H52: Semi-Product | I52: PKT | J52: 1PKT*6PCS*100G | K52: 3.67 | M52: 1 | N52: 10 | O52: =IF(ISNUMBER(SEARCH('Data Entry'!$J$3,$Q52)),MAX($O$1:$O51)+1,0) -> 0 | P52: =IF(ISNUMBER(SEARCH('Data Entry'!$J$3,$Q52)),MAX($P$1:$P51)+1,0) -> 0 | Q52: =Table2[[#This Row],[Item Name ]] -> Raw Sausage Corn Dog | R52: =IFERROR(VLOOKUP(ROWS($R$2:$R52),Table2[[Nub2]:[Name]],2,0),"") | W52: =IF(ISNUMBER(SEARCH('Data Entry'!$J$3,$Y52)),MAX($W$1:$W51)+1,0) -> 0 | X52: =IF(ISNUMBER(SEARCH('Data Entry'!$J$3,$Y52)),MAX($X$1:$X51)+1,0) -> 0 | Y52: BLUE LADDER CO.,LTD | Z52: =IFERROR(VLOOKUP(ROWS($Z$2:$Z52),Table4[[Nub2]:[Supplied Name]],2,0),"") | AA52: =OFFSET($Z$2,,,COUNTIF($Z$2:$Z$25,"?*")) -> #REF!
A53: {=ROW(52:52)} -> 52 | B53: KF-0009 | C53: 900122 | D53: Raw Sriracha Mayo Sauce | F53: RTE | G53: FOOD | H53: Semi-Product | I53: PKT | J53: 1PKT*1KG | K53: 7.2 | M53: 1 | N53: 10 | O53: =IF(ISNUMBER(SEARCH('Data Entry'!$J$3,$Q53)),MAX($O$1:$O52)+1,0) -> 0 | P53: =IF(ISNUMBER(SEARCH('Data Entry'!$J$3,$Q53)),MAX($P$1:$P52)+1,0) -> 0 | Q53: =Table2[[#This Row],[Item Name ]] -> Raw Sriracha Mayo Sauce | R53: =IFERROR(VLOOKUP(ROWS($R$2:$R53),Table2[[Nub2]:[Name]],2,0),"") | W53: =IF(ISNUMBER(SEARCH('Data Entry'!$J$3,$Y53)),MAX($W$1:$W52)+1,0) -> 0 | X53: =IF(ISNUMBER(SEARCH('Data Entry'!$J$3,$Y53)),MAX($X$1:$X52)+1,0) -> 0 | Y53: BMI Team | Z53: =IFERROR(VLOOKUP(ROWS($Z$2:$Z53),Table4[[Nub2]:[Supplied Name]],2,0),"") | AA53: =OFFSET($Z$2,,,COUNTIF($Z$2:$Z$25,"?*")) -> #REF!
A54: {=ROW(53:53)} -> 53 | B54: KF-0010 | C54: 900123 | D54: Raw Sweet & Spicy Sauce (Yangyum Sauce) | F54: RTE | G54: FOOD | H54: Semi-Product | I54: PKT | J54: 1PKT*1KG | K54: 5.16 | M54: 1 | N54: 10 | O54: =IF(ISNUMBER(SEARCH('Data Entry'!$J$3,$Q54)),MAX($O$1:$O53)+1,0) -> 0 | P54: =IF(ISNUMBER(SEARCH('Data Entry'!$J$3,$Q54)),MAX($P$1:$P53)+1,0) -> 0 | Q54: =Table2[[#This Row],[Item Name ]] -> Raw Sweet & Spicy Sauce (Yangyum Sauce) | R54: =IFERROR(VLOOKUP(ROWS($R$2:$R54),Table2[[Nub2]:[Name]],2,0),"") | W54: =IF(ISNUMBER(SEARCH('Data Entry'!$J$3,$Y54)),MAX($W$1:$W53)+1,0) -> 0 | X54: =IF(ISNUMBER(SEARCH('Data Entry'!$J$3,$Y54)),MAX($X$1:$X53)+1,0) -> 0 | Y54: BNTD Distribution Co., Ltd | Z54: =IFERROR(VLOOKUP(ROWS($Z$2:$Z54),Table4[[Nub2]:[Supplied Name]],2,0),"") | AA54: =OFFSET($Z$2,,,COUNTIF($Z$2:$Z$25,"?*")) -> #REF!
A55: {=ROW(54:54)} -> 54 | B55: KF-0011 | C55: 900124 | D55: Raw Honey Sauce | F55: RTE | G55: FOOD | H55: Semi-Product | I55: PKT | J55: 1PKT*1KG | K55: 4.2 | M55: 1 | N55: 10 | O55: =IF(ISNUMBER(SEARCH('Data Entry'!$J$3,$Q55)),MAX($O$1:$O54)+1,0) -> 0 | P55: =IF(ISNUMBER(SEARCH('Data Entry'!$J$3,$Q55)),MAX($P$1:$P54)+1,0) -> 0 | Q55: =Table2[[#This Row],[Item Name ]] -> Raw Honey Sauce | R55: =IFERROR(VLOOKUP(ROWS($R$2:$R55),Table2[[Nub2]:[Name]],2,0),"") | W55: =IF(ISNUMBER(SEARCH('Data Entry'!$J$3,$Y55)),MAX($W$1:$W54)+1,0) -> 0 | X55: =IF(ISNUMBER(SEARCH('Data Entry'!$J$3,$Y55)),MAX($X$1:$X54)+1,0) -> 0 | Y55: BNi DRAGON | Z55: =IFERROR(VLOOKUP(ROWS($Z$2:$Z55),Table4[[Nub2]:[Supplied Name]],2,0),"") | AA55: =OFFSET($Z$2,,,COUNTIF($Z$2:$Z$25,"?*")) -> #REF!
A56: {=ROW(55:55)} -> 55 | B56: KF-0012 | C56: 900125 | D56: Raw Spicy Mayo Sauce | F56: RTE | G56: FOOD | H56: Semi-Product | I56: PKT | J56: 1PKT*1KG | K56: 7.8 | M56: 1 | N56: 10 | O56: =IF(ISNUMBER(SEARCH('Data Entry'!$J$3,$Q56)),MAX($O$1:$O55)+1,0) -> 0 | P56: =IF(ISNUMBER(SEARCH('Data Entry'!$J$3,$Q56)),MAX($P$1:$P55)+1,0) -> 0 | Q56: =Table2[[#This Row],[Item Name ]] -> Raw Spicy Mayo Sauce | R56: =IFERROR(VLOOKUP(ROWS($R$2:$R56),Table2[[Nub2]:[Name]],2,0),"") | W56: =IF(ISNUMBER(SEARCH('Data Entry'!$J$3,$Y56)),MAX($W$1:$W55)+1,0) -> 0 | X56: =IF(ISNUMBER(SEARCH('Data Entry'!$J$3,$Y56)),MAX($X$1:$X55)+1,0) -> 0 | Y56: BONCAFE (CAMBODIA) LTD. | Z56: =IFERROR(VLOOKUP(ROWS($Z$2:$Z56),Table4[[Nub2]:[Supplied Name]],2,0),"") | AA56: =OFFSET($Z$2,,,COUNTIF($Z$2:$Z$25,"?*")) -> #REF!
A57: {=ROW(56:56)} -> 56 | B57: KF-0013 | C57: 900126 | D57: Raw Teriyaki Sauce | F57: RTE | G57: FOOD | H57: Semi-Product | I57: PKT | J57: 1PKT*1KG | K57: 9.72 | M57: 1 | N57: 10 | O57: =IF(ISNUMBER(SEARCH('Data Entry'!$J$3,$Q57)),MAX($O$1:$O56)+1,0) -> 0 | P57: =IF(ISNUMBER(SEARCH('Data Entry'!$J$3,$Q57)),MAX($P$1:$P56)+1,0) -> 0 | Q57: =Table2[[#This Row],[Item Name ]] -> Raw Teriyaki Sauce | R57: =IFERROR(VLOOKUP(ROWS($R$2:$R57),Table2[[Nub2]:[Name]],2,0),"") | W57: =IF(ISNUMBER(SEARCH('Data Entry'!$J$3,$Y57)),MAX($W$1:$W56)+1,0) -> 0 | X57: =IF(ISNUMBER(SEARCH('Data Entry'!$J$3,$Y57)),MAX($X$1:$X56)+1,0) -> 0 | Y57: BORN SOPHEAKTRA | Z57: =IFERROR(VLOOKUP(ROWS($Z$2:$Z57),Table4[[Nub2]:[Supplied Name]],2,0),"") | AA57: =OFFSET($Z$2,,,COUNTIF($Z$2:$Z$25,"?*")) -> #REF!
A58: {=ROW(57:57)} -> 57 | B58: KF-0014 | C58: 900127 | D58: Raw Garlic Soy Sauce | F58: RTE | G58: FOOD | H58: Semi-Product | I58: PKT | J58: 1PKT*1KG | K58: 3.6 | M58: 1 | N58: 10 | O58: =IF(ISNUMBER(SEARCH('Data Entry'!$J$3,$Q58)),MAX($O$1:$O57)+1,0) -> 0 | P58: =IF(ISNUMBER(SEARCH('Data Entry'!$J$3,$Q58)),MAX($P$1:$P57)+1,0) -> 0 | Q58: =Table2[[#This Row],[Item Name ]] -> Raw Garlic Soy Sauce | R58: =IFERROR(VLOOKUP(ROWS($R$2:$R58),Table2[[Nub2]:[Name]],2,0),"") | W58: =IF(ISNUMBER(SEARCH('Data Entry'!$J$3,$Y58)),MAX($W$1:$W57)+1,0) -> 0 | X58: =IF(ISNUMBER(SEARCH('Data Entry'!$J$3,$Y58)),MAX($X$1:$X57)+1,0) -> 0 | Y58: BORVOR Media | Z58: =IFERROR(VLOOKUP(ROWS($Z$2:$Z58),Table4[[Nub2]:[Supplied Name]],2,0),"") | AA58: =OFFSET($Z$2,,,COUNTIF($Z$2:$Z$25,"?*")) -> #REF!
A59: {=ROW(58:58)} -> 58 | B59: KF-0015 | C59: 900128 | D59: Raw Bibm Spicy Sauce (Cupbap Sauce) | F59: RTE | G59: FOOD | H59: Semi-Product | I59: PKT | J59: 1PKT*1KG | K59: 4.56 | M59: 1 | N59: 10 | O59: =IF(ISNUMBER(SEARCH('Data Entry'!$J$3,$Q59)),MAX($O$1:$O58)+1,0) -> 0 | P59: =IF(ISNUMBER(SEARCH('Data Entry'!$J$3,$Q59)),MAX($P$1:$P58)+1,0) -> 0 | Q59: =Table2[[#This Row],[Item Name ]] -> Raw Bibm Spicy Sauce (Cupbap Sauce) | R59: =IFERROR(VLOOKUP(ROWS($R$2:$R59),Table2[[Nub2]:[Name]],2,0),"") | W59: =IF(ISNUMBER(SEARCH('Data Entry'!$J$3,$Y59)),MAX($W$1:$W58)+1,0) -> 0 | X59: =IF(ISNUMBER(SEARCH('Data Entry'!$J$3,$Y59)),MAX($X$1:$X58)+1,0) -> 0 | Y59: BOU SIV HORNG | Z59: =IFERROR(VLOOKUP(ROWS($Z$2:$Z59),Table4[[Nub2]:[Supplied Name]],2,0),"") | AA59: =OFFSET($Z$2,,,COUNTIF($Z$2:$Z$25,"?*")) -> #REF!
A60: {=ROW(59:59)} -> 59 | B60: KF-0016 | C60: 900129 | D60: Raw Fish Shapped Batter | F60: RTE | G60: FOOD | H60: Semi-Product | I60: PKT | J60: 1PKT*1KG | K60: 4.8 | M60: 1 | N60: 10 | O60: =IF(ISNUMBER(SEARCH('Data Entry'!$J$3,$Q60)),MAX($O$1:$O59)+1,0) -> 0 | P60: =IF(ISNUMBER(SEARCH('Data Entry'!$J$3,$Q60)),MAX($P$1:$P59)+1,0) -> 0 | Q60: =Table2[[#This Row],[Item Name ]] -> Raw Fish Shapped Batter | R60: =IFERROR(VLOOKUP(ROWS($R$2:$R60),Table2[[Nub2]:[Name]],2,0),"") | W60: =IF(ISNUMBER(SEARCH('Data Entry'!$J$3,$Y60)),MAX($W$1:$W59)+1,0) -> 0 | X60: =IF(ISNUMBER(SEARCH('Data Entry'!$J$3,$Y60)),MAX($X$1:$X59)+1,0) -> 0 | Y60: BPS (Cambodia) Co., Ltd | Z60: =IFERROR(VLOOKUP(ROWS($Z$2:$Z60),Table4[[Nub2]:[Supplied Name]],2,0),"") | AA60: =OFFSET($Z$2,,,COUNTIF($Z$2:$Z$25,"?*")) -> #REF!
A61: {=ROW(60:60)} -> 60 | B61: KF-0017 | C61: 900130 | D61: Raw Custard | F61: RTE | G61: FOOD | H61: Semi-Product | I61: PKT | J61: 1PKT*1KG | K61: 4.56 | M61: 1 | N61: 10 | O61: =IF(ISNUMBER(SEARCH('Data Entry'!$J$3,$Q61)),MAX($O$1:$O60)+1,0) -> 0 | P61: =IF(ISNUMBER(SEARCH('Data Entry'!$J$3,$Q61)),MAX($P$1:$P60)+1,0) -> 0 | Q61: =Table2[[#This Row],[Item Name ]] -> Raw Custard | R61: =IFERROR(VLOOKUP(ROWS($R$2:$R61),Table2[[Nub2]:[Name]],2,0),"") | W61: =IF(ISNUMBER(SEARCH('Data Entry'!$J$3,$Y61)),MAX($W$1:$W60)+1,0) -> 0 | X61: =IF(ISNUMBER(SEARCH('Data Entry'!$J$3,$Y61)),MAX($X$1:$X60)+1,0) -> 0 | Y61: BUONISSIMO TRADING CO., LTD | Z61: =IFERROR(VLOOKUP(ROWS($Z$2:$Z61),Table4[[Nub2]:[Supplied Name]],2,0),"") | AA61: =OFFSET($Z$2,,,COUNTIF($Z$2:$Z$25,"?*")) -> #REF!
A62: {=ROW(61:61)} -> 61 | B62: KF-0018 | C62: 900165 | D62: Raw Rice Cake Skewer Sauce (Sotteok Sotteok) | F62: RTE | G62: FOOD | H62: Semi-Product | I62: PKT | J62: 1PKT*1KG | K62: 4.56 | M62: 1 | N62: 10 | O62: =IF(ISNUMBER(SEARCH('Data Entry'!$J$3,$Q62)),MAX($O$1:$O61)+1,0) -> 0 | P62: =IF(ISNUMBER(SEARCH('Data Entry'!$J$3,$Q62)),MAX($P$1:$P61)+1,0) -> 0 | Q62: =Table2[[#This Row],[Item Name ]] -> Raw Rice Cake Skewer Sauce (Sotteok Sotteok) | R62: =IFERROR(VLOOKUP(ROWS($R$2:$R62),Table2[[Nub2]:[Name]],2,0),"") | W62: =IF(ISNUMBER(SEARCH('Data Entry'!$J$3,$Y62)),MAX($W$1:$W61)+1,0) -> 0 | X62: =IF(ISNUMBER(SEARCH('Data Entry'!$J$3,$Y62)),MAX($X$1:$X61)+1,0) -> 0 | Y62: Baseline Culinary Consultancy Corp. | Z62: =IFERROR(VLOOKUP(ROWS($Z$2:$Z62),Table4[[Nub2]:[Supplied Name]],2,0),"") | AA62: =OFFSET($Z$2,,,COUNTIF($Z$2:$Z$25,"?*")) -> #REF!
A63: {=ROW(62:62)} -> 62 | B63: KF-0019 | C63: 900166 | D63: Raw Rice Cake Skewer | F63: RTE | G63: FOOD | H63: Semi-Product | I63: PKT | J63: 1PKT*10 Portions | K63: 3.42 | M63: 1 | N63: 10 | O63: =IF(ISNUMBER(SEARCH('Data Entry'!$J$3,$Q63)),MAX($O$1:$O62)+1,0) -> 0 | P63: =IF(ISNUMBER(SEARCH('Data Entry'!$J$3,$Q63)),MAX($P$1:$P62)+1,0) -> 0 | Q63: =Table2[[#This Row],[Item Name ]] -> Raw Rice Cake Skewer | R63: =IFERROR(VLOOKUP(ROWS($R$2:$R63),Table2[[Nub2]:[Name]],2,0),"") | W63: =IF(ISNUMBER(SEARCH('Data Entry'!$J$3,$Y63)),MAX($W$1:$W62)+1,0) -> 0 | X63: =IF(ISNUMBER(SEARCH('Data Entry'!$J$3,$Y63)),MAX($X$1:$X62)+1,0) -> 0 | Y63: Bayon Furniture | Z63: =IFERROR(VLOOKUP(ROWS($Z$2:$Z63),Table4[[Nub2]:[Supplied Name]],2,0),"") | AA63: =OFFSET($Z$2,,,COUNTIF($Z$2:$Z$25,"?*")) -> #REF!
A64: {=ROW(63:63)} -> 63 | B64: KF-0020 | C64: 900167 | D64: Raw Sotteok Sotteok Skewer | F64: RTE | G64: FOOD | H64: Semi-Product | I64: PKT | J64: 1PKT*10 Portions | K64: 5.76 | M64: 1 | N64: 10 | O64: =IF(ISNUMBER(SEARCH('Data Entry'!$J$3,$Q64)),MAX($O$1:$O63)+1,0) -> 0 | P64: =IF(ISNUMBER(SEARCH('Data Entry'!$J$3,$Q64)),MAX($P$1:$P63)+1,0) -> 0 | Q64: =Table2[[#This Row],[Item Name ]] -> Raw Sotteok Sotteok Skewer | R64: =IFERROR(VLOOKUP(ROWS($R$2:$R64),Table2[[Nub2]:[Name]],2,0),"") | W64: =IF(ISNUMBER(SEARCH('Data Entry'!$J$3,$Y64)),MAX($W$1:$W63)+1,0) -> 0 | X64: =IF(ISNUMBER(SEARCH('Data Entry'!$J$3,$Y64)),MAX($X$1:$X63)+1,0) -> 0 | Y64: Benoit Jean Baptiste Dufour | Z64: =IFERROR(VLOOKUP(ROWS($Z$2:$Z64),Table4[[Nub2]:[Supplied Name]],2,0),"") | AA64: =OFFSET($Z$2,,,COUNTIF($Z$2:$Z$25,"?*")) -> #REF!
A65: {=ROW(64:64)} -> 64 | B65: KF-0021 | C65: 900168 | D65: Raw Sausage Bar | F65: CENTRAL KITCHEN | G65: FOOD | H65: Semi-Product | I65: PKT | J65: 1PKT*10 Portions | K65: 3.72 | M65: 1 | N65: 10 | O65: =IF(ISNUMBER(SEARCH('Data Entry'!$J$3,$Q65)),MAX($O$1:$O64)+1,0) -> 0 | P65: =IF(ISNUMBER(SEARCH('Data Entry'!$J$3,$Q65)),MAX($P$1:$P64)+1,0) -> 0 | Q65: =Table2[[#This Row],[Item Name ]] -> Raw Sausage Bar | R65: =IFERROR(VLOOKUP(ROWS($R$2:$R65),Table2[[Nub2]:[Name]],2,0),"") | W65: =IF(ISNUMBER(SEARCH('Data Entry'!$J$3,$Y65)),MAX($W$1:$W64)+1,0) -> 0 | X65: =IF(ISNUMBER(SEARCH('Data Entry'!$J$3,$Y65)),MAX($X$1:$X64)+1,0) -> 0 | Y65: Bettina Ygolinsky | Z65: =IFERROR(VLOOKUP(ROWS($Z$2:$Z65),Table4[[Nub2]:[Supplied Name]],2,0),"") | AA65: =OFFSET($Z$2,,,COUNTIF($Z$2:$Z$25,"?*")) -> #REF!
A66: {=ROW(65:65)} -> 65 | B66: KF-0022 | C66: 900169 | D66: Raw Sausage Stick | F66: CENTRAL KITCHEN | G66: FOOD | H66: Semi-Product | I66: PKT | J66: 1PKT*10 Portions | K66: 5.4 | M66: 1 | N66: 10 | O66: =IF(ISNUMBER(SEARCH('Data Entry'!$J$3,$Q66)),MAX($O$1:$O65)+1,0) -> 0 | P66: =IF(ISNUMBER(SEARCH('Data Entry'!$J$3,$Q66)),MAX($P$1:$P65)+1,0) -> 0 | Q66: =Table2[[#This Row],[Item Name ]] -> Raw Sausage Stick | R66: =IFERROR(VLOOKUP(ROWS($R$2:$R66),Table2[[Nub2]:[Name]],2,0),"") | W66: =IF(ISNUMBER(SEARCH('Data Entry'!$J$3,$Y66)),MAX($W$1:$W65)+1,0) -> 0 | X66: =IF(ISNUMBER(SEARCH('Data Entry'!$J$3,$Y66)),MAX($X$1:$X65)+1,0) -> 0 | Y66: Bliss Cafe & Marl | Z66: =IFERROR(VLOOKUP(ROWS($Z$2:$Z66),Table4[[Nub2]:[Supplied Name]],2,0),"") | AA66: =OFFSET($Z$2,,,COUNTIF($Z$2:$Z$25,"?*")) -> #REF!
A67: {=ROW(66:66)} -> 66 | B67: KF-0023 | C67: 900170 | D67: Raw Fish Ball Bar | F67: CENTRAL KITCHEN | G67: FOOD | H67: Semi-Product | I67: PKT | J67: 1PKT*10 Portions | K67: 3 | M67: 1 | N67: 10 | O67: =IF(ISNUMBER(SEARCH('Data Entry'!$J$3,$Q67)),MAX($O$1:$O66)+1,0) -> 0 | P67: =IF(ISNUMBER(SEARCH('Data Entry'!$J$3,$Q67)),MAX($P$1:$P66)+1,0) -> 0 | Q67: =Table2[[#This Row],[Item Name ]] -> Raw Fish Ball Bar | R67: =IFERROR(VLOOKUP(ROWS($R$2:$R67),Table2[[Nub2]:[Name]],2,0),"") | W67: =IF(ISNUMBER(SEARCH('Data Entry'!$J$3,$Y67)),MAX($W$1:$W66)+1,0) -> 0 | X67: =IF(ISNUMBER(SEARCH('Data Entry'!$J$3,$Y67)),MAX($X$1:$X66)+1,0) -> 0 | Y67: Boloni Cambodia | Z67: =IFERROR(VLOOKUP(ROWS($Z$2:$Z67),Table4[[Nub2]:[Supplied Name]],2,0),"") | AA67: =OFFSET($Z$2,,,COUNTIF($Z$2:$Z$25,"?*")) -> #REF!
A68: {=ROW(67:67)} -> 67 | B68: KF-0024 | C68: 900236 | D68: Raw Eu Muk Fish Square Skewer | F68: CENTRAL KITCHEN | G68: FOOD | H68: Semi-Product | I68: PKT | J68: 1PKT*10 Portions | K68: 3.6 | M68: 1 | N68: 10 | O68: =IF(ISNUMBER(SEARCH('Data Entry'!$J$3,$Q68)),MAX($O$1:$O67)+1,0) -> 0 | P68: =IF(ISNUMBER(SEARCH('Data Entry'!$J$3,$Q68)),MAX($P$1:$P67)+1,0) -> 0 | Q68: =Table2[[#This Row],[Item Name ]] -> Raw Eu Muk Fish Square Skewer | R68: =IFERROR(VLOOKUP(ROWS($R$2:$R68),Table2[[Nub2]:[Name]],2,0),"")
A69: {=ROW(68:68)} -> 68 | B69: KF-0025 | C69: 900237 | D69: Raw Eu Muk Fish Naruto | F69: CENTRAL KITCHEN | G69: FOOD | H69: Semi-Product | I69: PKT | J69: 1PKT*10 Portions | K69: 7.2 | M69: 1 | N69: 10 | O69: =IF(ISNUMBER(SEARCH('Data Entry'!$J$3,$Q69)),MAX($O$1:$O68)+1,0) -> 0 | P69: =IF(ISNUMBER(SEARCH('Data Entry'!$J$3,$Q69)),MAX($P$1:$P68)+1,0) -> 0 | Q69: =Table2[[#This Row],[Item Name ]] -> Raw Eu Muk Fish Naruto | R69: =IFERROR(VLOOKUP(ROWS($R$2:$R69),Table2[[Nub2]:[Name]],2,0),"")
A70: {=ROW(69:69)} -> 69 | B70: M-0346 | C70: 900265 | D70: NARUTO 160g | F70: CENTRAL KITCHEN | G70: FOOD | H70: Froozen Food | I70: PKT | J70: 1PKT*160GM | K70: 3.12 | M70: 1 | N70: 10 | O70: =IF(ISNUMBER(SEARCH('Data Entry'!$J$3,$Q70)),MAX($O$1:$O69)+1,0) -> 0 | P70: =IF(ISNUMBER(SEARCH('Data Entry'!$J$3,$Q70)),MAX($P$1:$P69)+1,0) -> 0 | Q70: =Table2[[#This Row],[Item Name ]] -> NARUTO 160g | R70: =IFERROR(VLOOKUP(ROWS($R$2:$R70),Table2[[Nub2]:[Name]],2,0),"")
A71: {=ROW(70:70)} -> 70 | B71: M-0354 | C71: 900267 | D71: Fish Ball Pack (ប្រហិតត្រីកញ្ចប់) | F71: CENTRAL KITCHEN | G71: FOOD | H71: Froozen Food | I71: PKT | J71: 1CTN*20PKT*1KG | K71: 3 | M71: 1 | N71: 10 | O71: =IF(ISNUMBER(SEARCH('Data Entry'!$J$3,$Q71)),MAX($O$1:$O70)+1,0) -> 0 | P71: =IF(ISNUMBER(SEARCH('Data Entry'!$J$3,$Q71)),MAX($P$1:$P70)+1,0) -> 0 | Q71: =Table2[[#This Row],[Item Name ]] -> Fish Ball Pack (ប្រហិតត្រីកញ្ចប់) | R71: =IFERROR(VLOOKUP(ROWS($R$2:$R71),Table2[[Nub2]:[Name]],2,0),"")
A72: {=ROW(71:71)} -> 71 | B72: M-0416 | C72: 900272 | D72: DEARIM Busan Eo Muk Square (Fish Cake) | F72: CENTRAL KITCHEN | G72: FOOD | H72: Froozen Food | I72: PKT | J72: 1PKT*1KG | K72: 6.9 | M72: 1 | N72: 10 | O72: =IF(ISNUMBER(SEARCH('Data Entry'!$J$3,$Q72)),MAX($O$1:$O71)+1,0) -> 0 | P72: =IF(ISNUMBER(SEARCH('Data Entry'!$J$3,$Q72)),MAX($P$1:$P71)+1,0) -> 0 | Q72: =Table2[[#This Row],[Item Name ]] -> DEARIM Busan Eo Muk Square (Fish Cake) | R72: =IFERROR(VLOOKUP(ROWS($R$2:$R72),Table2[[Nub2]:[Name]],2,0),"")
A73: {=ROW(72:72)} -> 72 | B73: O-0049 | C73: 900154 | D73: Cambodia Jasmine Rice | F73: CENTRAL KITCHEN | G73: FOOD | H73: Others / Dried Food | I73: KG | J73: 1BAG*50KG | K73: 1.2 | M73: 1 | N73: 10 | O73: =IF(ISNUMBER(SEARCH('Data Entry'!$J$3,$Q73)),MAX($O$1:$O72)+1,0) -> 0 | P73: =IF(ISNUMBER(SEARCH('Data Entry'!$J$3,$Q73)),MAX($P$1:$P72)+1,0) -> 0 | Q73: =Table2[[#This Row],[Item Name ]] -> Cambodia Jasmine Rice | R73: =IFERROR(VLOOKUP(ROWS($R$2:$R73),Table2[[Nub2]:[Name]],2,0),"")
A74: {=ROW(73:73)} -> 73 | B74: O-0147 | C74: 900154 | D74: Cambodia Jasmine Rice 50kg (អង្ករផ្កាម្លិះ) | F74: CENTRAL KITCHEN | G74: FOOD | H74: Others / Dried Food | I74: KG | J74: 1BAG*50KG | K74: 1.2 | M74: 1 | N74: 10 | O74: =IF(ISNUMBER(SEARCH('Data Entry'!$J$3,$Q74)),MAX($O$1:$O73)+1,0) -> 0 | P74: =IF(ISNUMBER(SEARCH('Data Entry'!$J$3,$Q74)),MAX($P$1:$P73)+1,0) -> 0 | Q74: =Table2[[#This Row],[Item Name ]] -> Cambodia Jasmine Rice 50kg (អង្ករផ្កាម្លិះ) | R74: =IFERROR(VLOOKUP(ROWS($R$2:$R74),Table2[[Nub2]:[Name]],2,0),"")
A75: {=ROW(74:74)} -> 74 | B75: O-0162 | C75: 3034 | D75: Deokbokki (Rice Cake) | F75: CENTRAL KITCHEN | G75: FOOD | H75: Froozen Food | I75: PKT | J75: 1PKT*2KG | K75: 6.408 | M75: 1 | N75: 10 | O75: =IF(ISNUMBER(SEARCH('Data Entry'!$J$3,$Q75)),MAX($O$1:$O74)+1,0) -> 0 | P75: =IF(ISNUMBER(SEARCH('Data Entry'!$J$3,$Q75)),MAX($P$1:$P74)+1,0) -> 0 | Q75: =Table2[[#This Row],[Item Name ]] -> Deokbokki (Rice Cake) | R75: =IFERROR(VLOOKUP(ROWS($R$2:$R75),Table2[[Nub2]:[Name]],2,0),"")
A76: {=ROW(75:75)} -> 75 | B76: P-0004 | C76: 900273 | D76: Chopsticks (ចង្កឹះឬស្សី) | F76: CENTRAL KITCHEN | G76: NON-FOOD | H76: Packaging Materials / Packaging | I76: PKT | J76: 1PKT*100PAIRS | K76: 1.74 | M76: 1 | N76: 10 | O76: =IF(ISNUMBER(SEARCH('Data Entry'!$J$3,$Q76)),MAX($O$1:$O75)+1,0) -> 0 | P76: =IF(ISNUMBER(SEARCH('Data Entry'!$J$3,$Q76)),MAX($P$1:$P75)+1,0) -> 0 | Q76: =Table2[[#This Row],[Item Name ]] -> Chopsticks (ចង្កឹះឬស្សី) | R76: =IFERROR(VLOOKUP(ROWS($R$2:$R76),Table2[[Nub2]:[Name]],2,0),"")
A77: {=ROW(76:76)} -> 76 | B77: P-0010 | C77: 900274 | D77: Black Garbage Bag 20*30 (ថង់សំរាមខ្មៅ) | F77: CENTRAL KITCHEN | G77: NON-FOOD | H77: NON-FOOD | I77: KG | J77: 1PKT*500GM | K77: 1.68 | M77: 1 | N77: 10 | O77: =IF(ISNUMBER(SEARCH('Data Entry'!$J$3,$Q77)),MAX($O$1:$O76)+1,0) -> 0 | P77: =IF(ISNUMBER(SEARCH('Data Entry'!$J$3,$Q77)),MAX($P$1:$P76)+1,0) -> 0 | Q77: =Table2[[#This Row],[Item Name ]] -> Black Garbage Bag 20*30 (ថង់សំរាមខ្មៅ) | R77: =IFERROR(VLOOKUP(ROWS($R$2:$R77),Table2[[Nub2]:[Name]],2,0),"")
A78: {=ROW(77:77)} -> 77 | B78: P-0011 | C78: 900275 | D78: Black Garbage Bag (No Handle) 70*120 (ថង់សម្រាមខ្មៅអត់ដៃ) | F78: CENTRAL KITCHEN | G78: NON-FOOD | H78: NON-FOOD | I78: KG | J78: 1PKT*1KG | K78: 1.56 | M78: 1 | N78: 10 | O78: =IF(ISNUMBER(SEARCH('Data Entry'!$J$3,$Q78)),MAX($O$1:$O77)+1,0) -> 0 | P78: =IF(ISNUMBER(SEARCH('Data Entry'!$J$3,$Q78)),MAX($P$1:$P77)+1,0) -> 0 | Q78: =Table2[[#This Row],[Item Name ]] -> Black Garbage Bag (No Handle) 70*120 (ថង់សម្រាមខ្មៅអត់ដៃ) | R78: =IFERROR(VLOOKUP(ROWS($R$2:$R78),Table2[[Nub2]:[Name]],2,0),"")
A79: {=ROW(78:78)} -> 78 | B79: P-0022 | C79: 900280 | D79: Plastic Bag White 12*20 (ថង់ថ្លាមានដៃ) | F79: CENTRAL KITCHEN | G79: NON-FOOD | H79: Packaging Materials / Packaging | I79: PKT | J79: 1PKT*100PCS | K79: 1.44 | M79: 1 | N79: 10 | O79: =IF(ISNUMBER(SEARCH('Data Entry'!$J$3,$Q79)),MAX($O$1:$O78)+1,0) -> 0 | P79: =IF(ISNUMBER(SEARCH('Data Entry'!$J$3,$Q79)),MAX($P$1:$P78)+1,0) -> 0 | Q79: =Table2[[#This Row],[Item Name ]] -> Plastic Bag White 12*20 (ថង់ថ្លាមានដៃ) | R79: =IFERROR(VLOOKUP(ROWS($R$2:$R79),Table2[[Nub2]:[Name]],2,0),"")
A80: {=ROW(79:79)} -> 79 | B80: P-0024 | C80: 900276 | D80: Bamboo Skewer 20cm | F80: CENTRAL KITCHEN | G80: NON-FOOD | H80: NON-FOOD | I80: PKT | J80: 1PKT*100PCS | K80: 1.5 | M80: 1 | N80: 10 | O80: =IF(ISNUMBER(SEARCH('Data Entry'!$J$3,$Q80)),MAX($O$1:$O79)+1,0) -> 0 | P80: =IF(ISNUMBER(SEARCH('Data Entry'!$J$3,$Q80)),MAX($P$1:$P79)+1,0) -> 0 | Q80: =Table2[[#This Row],[Item Name ]] -> Bamboo Skewer 20cm | R80: =IFERROR(VLOOKUP(ROWS($R$2:$R80),Table2[[Nub2]:[Name]],2,0),"")
A81: {=ROW(80:80)} -> 80 | B81: P-0033 | C81: 900295 | D81: Kelly Cling Wrap (ហ្វីមរុំម្ហូប) | F81: CENTRAL KITCHEN | G81: NON-FOOD | H81: NON-FOOD | I81: ROLL | J81: 1ROLL*600M*45CM | K81: 21.6 | M81: 1 | N81: 10 | O81: =IF(ISNUMBER(SEARCH('Data Entry'!$J$3,$Q81)),MAX($O$1:$O80)+1,0) -> 0 | P81: =IF(ISNUMBER(SEARCH('Data Entry'!$J$3,$Q81)),MAX($P$1:$P80)+1,0) -> 0 | Q81: =Table2[[#This Row],[Item Name ]] -> Kelly Cling Wrap (ហ្វីមរុំម្ហូប) | R81: =IFERROR(VLOOKUP(ROWS($R$2:$R81),Table2[[Nub2]:[Name]],2,0),"")
A82: {=ROW(81:81)} -> 81 | B82: P-0041 | C82: 900296 | D82: Baking Paper | F82: CENTRAL KITCHEN | G82: NON-FOOD | H82: NON-FOOD | I82: ROLL | J82: 1ROLL*600M*45CM | K82: 22.8 | M82: 1 | N82: 10 | O82: =IF(ISNUMBER(SEARCH('Data Entry'!$J$3,$Q82)),MAX($O$1:$O81)+1,0) -> 0 | P82: =IF(ISNUMBER(SEARCH('Data Entry'!$J$3,$Q82)),MAX($P$1:$P81)+1,0) -> 0 | Q82: =Table2[[#This Row],[Item Name ]] -> Baking Paper | R82: =IFERROR(VLOOKUP(ROWS($R$2:$R82),Table2[[Nub2]:[Name]],2,0),"")
A83: {=ROW(82:82)} -> 82 | B83: P-0075 | C83: 43A52003 | D83: Set Plastic Spoon & Fork (ឈុតស្លាបព្រា សម) | F83: CENTRAL KITCHEN | G83: NON-FOOD | H83: NON-FOOD | I83: PCS | J83: 1CTN*16PKT*50PCS | K83: =54/800 -> 0.0675 | M83: 1 | N83: 10 | O83: =IF(ISNUMBER(SEARCH('Data Entry'!$J$3,$Q83)),MAX($O$1:$O82)+1,0) -> 1 | P83: =IF(ISNUMBER(SEARCH('Data Entry'!$J$3,$Q83)),MAX($P$1:$P82)+1,0) -> 1 | Q83: =Table2[[#This Row],[Item Name ]] -> Set Plastic Spoon & Fork (ឈុតស្លាបព្រា សម) | R83: =IFERROR(VLOOKUP(ROWS($R$2:$R83),Table2[[Nub2]:[Name]],2,0),"")
A84: {=ROW(83:83)} -> 83 | B84: SW-0001 | C84: 900131 | D84: Crispy Chicken Sandwich | F84: CENTRAL KITCHEN | G84: FOOD | H84: Sandwich | I84: BOX | J84: 1BOX*1PCS | K84: 0.37 | M84: 1 | N84: 10 | O84: =IF(ISNUMBER(SEARCH('Data Entry'!$J$3,$Q84)),MAX($O$1:$O83)+1,0) -> 0 | P84: =IF(ISNUMBER(SEARCH('Data Entry'!$J$3,$Q84)),MAX($P$1:$P83)+1,0) -> 0 | Q84: =Table2[[#This Row],[Item Name ]] -> Crispy Chicken Sandwich | R84: =IFERROR(VLOOKUP(ROWS($R$2:$R84),Table2[[Nub2]:[Name]],2,0),"")
A85: {=ROW(84:84)} -> 84 | B85: SW-0002 | C85: 900132 | D85: Crab Meat Sandwich | F85: CENTRAL KITCHEN | G85: FOOD | H85: Sandwich | I85: BOX | J85: 1BOX*1PCS | K85: 0.37 | M85: 1 | N85: 10 | O85: =IF(ISNUMBER(SEARCH('Data Entry'!$J$3,$Q85)),MAX($O$1:$O84)+1,0) -> 0 | P85: =IF(ISNUMBER(SEARCH('Data Entry'!$J$3,$Q85)),MAX($P$1:$P84)+1,0) -> 0 | Q85: =Table2[[#This Row],[Item Name ]] -> Crab Meat Sandwich | R85: =IFERROR(VLOOKUP(ROWS($R$2:$R85),Table2[[Nub2]:[Name]],2,0),"")
A86: {=ROW(85:85)} -> 85 | B86: SW-0003 | C86: 900133 | D86: Chicken Cheese Sandwich | F86: CENTRAL KITCHEN | G86: FOOD | H86: Sandwich | I86: BOX | J86: 1BOX*1PCS | K86: 0.429 | M86: 1 | N86: 10 | O86: =IF(ISNUMBER(SEARCH('Data Entry'!$J$3,$Q86)),MAX($O$1:$O85)+1,0) -> 0 | P86: =IF(ISNUMBER(SEARCH('Data Entry'!$J$3,$Q86)),MAX($P$1:$P85)+1,0) -> 0 | Q86: =Table2[[#This Row],[Item Name ]] -> Chicken Cheese Sandwich | R86: =IFERROR(VLOOKUP(ROWS($R$2:$R86),Table2[[Nub2]:[Name]],2,0),"")
A87: {=ROW(86:86)} -> 86 | B87: SW-0004 | C87: 900134 | D87: Samsaek Sandwich | F87: CENTRAL KITCHEN | G87: FOOD | H87: Sandwich | I87: BOX | J87: 1BOX*1PCS | K87: 0.48 | M87: 1 | N87: 10 | O87: =IF(ISNUMBER(SEARCH('Data Entry'!$J$3,$Q87)),MAX($O$1:$O86)+1,0) -> 0 | P87: =IF(ISNUMBER(SEARCH('Data Entry'!$J$3,$Q87)),MAX($P$1:$P86)+1,0) -> 0 | Q87: =Table2[[#This Row],[Item Name ]] -> Samsaek Sandwich | R87: =IFERROR(VLOOKUP(ROWS($R$2:$R87),Table2[[Nub2]:[Name]],2,0),"")
A88: {=ROW(87:87)} -> 87 | B88: SW-0005 | C88: 900135 | D88: Inkigayo Sandwich | F88: CENTRAL KITCHEN | G88: FOOD | H88: Sandwich | I88: BOX | J88: 1BOX*1PCS | K88: 0.516 | M88: 1 | N88: 10 | O88: =IF(ISNUMBER(SEARCH('Data Entry'!$J$3,$Q88)),MAX($O$1:$O87)+1,0) -> 0 | P88: =IF(ISNUMBER(SEARCH('Data Entry'!$J$3,$Q88)),MAX($P$1:$P87)+1,0) -> 0 | Q88: =Table2[[#This Row],[Item Name ]] -> Inkigayo Sandwich | R88: =IFERROR(VLOOKUP(ROWS($R$2:$R88),Table2[[Nub2]:[Name]],2,0),"")
A89: {=ROW(88:88)} -> 88 | B89: V-0038 | C89: 900153 | D89: White Radish (Daikon) | F89: CENTRAL KITCHEN | G89: FOOD | H89: Fruits & Veggies / Veggies | I89: KG | J89: KG | K89: 0.84 | M89: 1 | N89: 10 | O89: =IF(ISNUMBER(SEARCH('Data Entry'!$J$3,$Q89)),MAX($O$1:$O88)+1,0) -> 0 | P89: =IF(ISNUMBER(SEARCH('Data Entry'!$J$3,$Q89)),MAX($P$1:$P88)+1,0) -> 0 | Q89: =Table2[[#This Row],[Item Name ]] -> White Radish (Daikon) | R89: =IFERROR(VLOOKUP(ROWS($R$2:$R89),Table2[[Nub2]:[Name]],2,0),"")
A90: {=ROW(89:89)} -> 89 | B90: V-0102 | C90: 900152 | D90: Lettuce Iceberg | F90: CENTRAL KITCHEN | G90: FOOD | H90: Fruits & Veggies / Veggies | I90: KG | J90: KG | K90: 3.12 | M90: 1 | N90: 10 | O90: =IF(ISNUMBER(SEARCH('Data Entry'!$J$3,$Q90)),MAX($O$1:$O89)+1,0) -> 0 | P90: =IF(ISNUMBER(SEARCH('Data Entry'!$J$3,$Q90)),MAX($P$1:$P89)+1,0) -> 0 | Q90: =Table2[[#This Row],[Item Name ]] -> Lettuce Iceberg | R90: =IFERROR(VLOOKUP(ROWS($R$2:$R90),Table2[[Nub2]:[Name]],2,0),"")
A91: {=ROW(90:90)} -> 90 | B91: V-0120 | C91: 900151 | D91: Leek | F91: CENTRAL KITCHEN | G91: FOOD | H91: Fruits & Veggies / Veggies | I91: KG | J91: KG | K91: 3.36 | M91: 1 | N91: 10 | O91: =IF(ISNUMBER(SEARCH('Data Entry'!$J$3,$Q91)),MAX($O$1:$O90)+1,0) -> 0 | P91: =IF(ISNUMBER(SEARCH('Data Entry'!$J$3,$Q91)),MAX($P$1:$P90)+1,0) -> 0 | Q91: =Table2[[#This Row],[Item Name ]] -> Leek | R91: =IFERROR(VLOOKUP(ROWS($R$2:$R91),Table2[[Nub2]:[Name]],2,0),"")
A92: {=ROW(91:91)} -> 91 | B92: P-0131 | D92: Bamboo Skewer 25cm | F92: CENTRAL KITCHEN | G92: NON-FOOD | H92: NON-FOOD | I92: PKT | J92: 1PKT*100PCS | K92: 1.5 | M92: 1 | N92: 10 | O92: =IF(ISNUMBER(SEARCH('Data Entry'!$J$3,$Q92)),MAX($O$1:$O91)+1,0) -> 0 | P92: =IF(ISNUMBER(SEARCH('Data Entry'!$J$3,$Q92)),MAX($P$1:$P91)+1,0) -> 0 | Q92: =Table2[[#This Row],[Item Name ]] -> Bamboo Skewer 25cm | R92: =IFERROR(VLOOKUP(ROWS($R$2:$R92),Table2[[Nub2]:[Name]],2,0),"")
A93: {=ROW(92:92)} -> 92 | B93: M-0107 | C93: 900272 | D93: Chicken Egg | F93: CENTRAL KITCHEN | G93: FOOD | H93: Food | I93: PCS | J93: PCS | K93: 0.17 | M93: 1 | N93: 10 | O93: =IF(ISNUMBER(SEARCH('Data Entry'!$J$3,$Q93)),MAX($O$1:$O92)+1,0) -> 0 | P93: =IF(ISNUMBER(SEARCH('Data Entry'!$J$3,$Q93)),MAX($P$1:$P92)+1,0) -> 0 | Q93: =Table2[[#This Row],[Item Name ]] -> Chicken Egg | R93: =IFERROR(VLOOKUP(ROWS($R$2:$R93),Table2[[Nub2]:[Name]],2,0),"")
A94: {=ROW(93:93)} -> 93 | B94: O-0164 | C94: 8852043005014 | D94: SMOKED COCKTAIL SAUSAGE DELUXE 1KG | F94: CENTRAL KITCHEN | G94: FOOD | H94: Froozen Food | I94: PKT | J94: 1CTN*11PKT*1KG | K94: 6.96 | M94: 1 | N94: 10 | O94: =IF(ISNUMBER(SEARCH('Data Entry'!$J$3,$Q94)),MAX($O$1:$O93)+1,0) -> 0 | P94: =IF(ISNUMBER(SEARCH('Data Entry'!$J$3,$Q94)),MAX($P$1:$P93)+1,0) -> 0 | Q94: =Table2[[#This Row],[Item Name ]] -> SMOKED COCKTAIL SAUSAGE DELUXE 1KG | R94: =IFERROR(VLOOKUP(ROWS($R$2:$R94),Table2[[Nub2]:[Name]],2,0),"")
A95: {=ROW(94:94)} -> 94 | B95: O-0163 | D95: JUMBO GOLD SAUSAGE 16PCS 1KG | F95: CENTRAL KITCHEN | G95: FOOD | H95: Froozen Food | I95: PKT | J95: 1CTN*11PKT*1KG | K95: 4.644 | M95: 1 | N95: 10 | O95: =IF(ISNUMBER(SEARCH('Data Entry'!$J$3,$Q95)),MAX($O$1:$O94)+1,0) -> 0 | P95: =IF(ISNUMBER(SEARCH('Data Entry'!$J$3,$Q95)),MAX($P$1:$P94)+1,0) -> 0 | Q95: =Table2[[#This Row],[Item Name ]] -> JUMBO GOLD SAUSAGE 16PCS 1KG | R95: =IFERROR(VLOOKUP(ROWS($R$2:$R95),Table2[[Nub2]:[Name]],2,0),"")
A96: {=ROW(95:95)} -> 95 | B96: RF-0001 | C96: C0101010534 | D96: Raw Frozen Chicken Drumstick | F96: CENTRAL KITCHEN | G96: FOOD | H96: Semi-Product | I96: KG | J96: 1PKT*1KG | K96: 4.74 | M96: 1 | N96: 10 | O96: =IF(ISNUMBER(SEARCH('Data Entry'!$J$3,$Q96)),MAX($O$1:$O95)+1,0) -> 0 | P96: =IF(ISNUMBER(SEARCH('Data Entry'!$J$3,$Q96)),MAX($P$1:$P95)+1,0) -> 0 | Q96: =Table2[[#This Row],[Item Name ]] -> Raw Frozen Chicken Drumstick | R96: =IFERROR(VLOOKUP(ROWS($R$2:$R96),Table2[[Nub2]:[Name]],2,0),"")
A97: {=ROW(96:96)} -> 96 | B97: RF-0002 | C97: C0101010535 | D97: Raw Frozen Chicken Middle Wing | F97: CENTRAL KITCHEN | G97: FOOD | H97: Semi-Product | I97: KG | J97: 1PKT*1KG | K97: 7.38 | M97: 1 | N97: 10 | O97: =IF(ISNUMBER(SEARCH('Data Entry'!$J$3,$Q97)),MAX($O$1:$O96)+1,0) -> 0 | P97: =IF(ISNUMBER(SEARCH('Data Entry'!$J$3,$Q97)),MAX($P$1:$P96)+1,0) -> 0 | Q97: =Table2[[#This Row],[Item Name ]] -> Raw Frozen Chicken Middle Wing | R97: =IFERROR(VLOOKUP(ROWS($R$2:$R97),Table2[[Nub2]:[Name]],2,0),"")
A98: {=ROW(97:97)} -> 97 | B98: KF-0026 | C98: C0101010536 | D98: Semi Chicken Sweet & Spicy Korean Sauce | F98: CENTRAL KITCHEN | G98: FOOD | H98: Semi-Product | I98: KG | J98: 1PKT*1KG | K98: 6.924 | M98: 1 | N98: 10 | O98: =IF(ISNUMBER(SEARCH('Data Entry'!$J$3,$Q98)),MAX($O$1:$O97)+1,0) -> 0 | P98: =IF(ISNUMBER(SEARCH('Data Entry'!$J$3,$Q98)),MAX($P$1:$P97)+1,0) -> 0 | Q98: =Table2[[#This Row],[Item Name ]] -> Semi Chicken Sweet & Spicy Korean Sauce | R98: =IFERROR(VLOOKUP(ROWS($R$2:$R132),Table2[[Nub2]:[Name]],2,0),"")
A99: {=ROW(98:98)} -> 98 | B99: REV-FOOD | D99: Revenue Food | F99: CENTRAL KITCHEN | G99: FOOD | H99: FOOD | M99: 1 | N99: 10 | O99: =IF(ISNUMBER(SEARCH('Data Entry'!$J$3,$Q99)),MAX($O$1:$O98)+1,0) -> 0 | P99: =IF(ISNUMBER(SEARCH('Data Entry'!$J$3,$Q99)),MAX($P$1:$P98)+1,0) -> 0 | Q99: =Table2[[#This Row],[Item Name ]] -> Revenue Food | R99: =IFERROR(VLOOKUP(ROWS($R$2:$R132),Table2[[Nub2]:[Name]],2,0),"")
A100: {=ROW(99:99)} -> 99 | B100: REV-NON ALCOHOL | D100: Revenue Non Alcohol | F100: CENTRAL KITCHEN | G100: BEVERAGE NON-ALOCOHOL | H100: BEVERAGE NON-ALOCOHOL | M100: 1 | N100: 10 | O100: =IF(ISNUMBER(SEARCH('Data Entry'!$J$3,$Q100)),MAX($O$1:$O99)+1,0) -> 0 | P100: =IF(ISNUMBER(SEARCH('Data Entry'!$J$3,$Q100)),MAX($P$1:$P99)+1,0) -> 0 | Q100: =Table2[[#This Row],[Item Name ]] -> Revenue Non Alcohol | R100: =IFERROR(VLOOKUP(ROWS($R$2:$R132),Table2[[Nub2]:[Name]],2,0),"")
...

Sheet Data Entry
W1: Paid
W2: On Credit
G3: Search For | I3: Item Name | J3: Set Plastic Spoon & Fork (ឈុតស្លាបព្រា សម) | K3: =IFERROR(INDEX(Table2[Item Code],MATCH('Data Entry'!J3,Table2[[Item Name ]],0),0),"") -> P-0075 | P3: Invoice Value By Invoice | R3: =SUMIFS(Table49[TOTAL PRICE (USD)],Table49[Document Number],$Q$3) -> 0 | S3: TODAY | T3: Week 03
A4: Nº | B4: DATE | C4: Month | D4: Week Num2 | E4: PO Number | F4: Document Number | G4: Delivered From/To | H4: BARCODE | I4: ITEM CODE | J4: ITEM NAME | K4: PACKING SIZE | L4: PURCHASE Uom | M4: QUANTITY | N4: Master List Prices | O4: INV Prices | P4: PRICE (USD) | Q4: TOTAL PRICE (USD) | R4: LAST TOTAL PRICE (USD) | S4: EXPRIED DATE | T4: ALERT | U4: REMARK | V4: Transaction Type | W4: Category | X4: Sub Category | Y4: H1
A5: =IF(Table49[[#This Row],[ITEM NAME]]="","",ROW()-4) -> 1 | B5: 45901 | C5: =IFERROR(VLOOKUP(B5,Table14[],3,0),"") -> 9 | D5: =IFERROR(VLOOKUP(B5,Table14[],2,0),"") -> Week 01 | E5: PO30955 | F5: DN-010901 | G5: E-MART24 BKK1 | H5: =IFERROR(VLOOKUP(Table49[[#This Row],[ITEM CODE]],Table2[[Item Code]:[Master Name]],2,0),"") -> F0103010009 | I5: CSW-0001 | J5: =IFERROR(VLOOKUP(Table49[[#This Row],[ITEM CODE]],Table2[[Item Code]:[Master Name]],3,0),"") -> Tuna & Egg Sandwich | K5: =IFERROR(VLOOKUP(Table49[[#This Row],[ITEM CODE]],Table2[[Item Code]:[Master Name]],9,0),"") -> 1BOX*2PCS | L5: =IFERROR(VLOOKUP(Table49[[#This Row],[ITEM CODE]],Table2[[Item Code]:[Master Name]],8,0),"") -> BOX | M5: 2 | N5: =IFERROR(VLOOKUP(Table49[[#This Row],[ITEM CODE]],Table2[[#All],[Item Code]:[Unit Cost]],10,0),0) -> 1.5 | O5: =IFERROR(VLOOKUP(Table49[[#This Row],[ITEM CODE]],Table2[[#All],[Item Code]:[Unit Cost]],10,0),0) -> 1.5 | R5: =Table49[[#This Row],[QUANTITY]]*Table49[[#This Row],[INV Prices]] -> 3 | V5: Sold | W5: =IFERROR(VLOOKUP(Table49[[#This Row],[ITEM CODE]],Table2[[Item Code]:[Category ]],6,0),"") -> FOOD | X5: =IFERROR(VLOOKUP(Table49[[#This Row],[ITEM CODE]],Table2[[Item Code]:[Sub Category]],7,0),"") -> Sandwich | Y5: =Table49[[#This Row],[PO Number]]&COUNTIFS($E$5:E5,E5) -> PO309551
A6: =IF(Table49[[#This Row],[ITEM NAME]]="","",ROW()-4) -> 2 | B6: 45901 | C6: =IFERROR(VLOOKUP(B6,Table14[],3,0),"") -> 9 | D6: =IFERROR(VLOOKUP(B6,Table14[],2,0),"") -> Week 01 | E6: PO30955 | F6: DN-010901 | G6: E-MART24 BKK1 | H6: =IFERROR(VLOOKUP(Table49[[#This Row],[ITEM CODE]],Table2[[Item Code]:[Master Name]],2,0),"") -> F0103010010 | I6: CSW-0002 | J6: =IFERROR(VLOOKUP(Table49[[#This Row],[ITEM CODE]],Table2[[Item Code]:[Master Name]],3,0),"") -> Ham & Corn Sandwich | K6: =IFERROR(VLOOKUP(Table49[[#This Row],[ITEM CODE]],Table2[[Item Code]:[Master Name]],9,0),"") -> 1BOX*2PCS | L6: =IFERROR(VLOOKUP(Table49[[#This Row],[ITEM CODE]],Table2[[Item Code]:[Master Name]],8,0),"") -> BOX | M6: 2 | N6: =IFERROR(VLOOKUP(Table49[[#This Row],[ITEM CODE]],Table2[[#All],[Item Code]:[Unit Cost]],10,0),0) -> 1.5 | O6: =IFERROR(VLOOKUP(Table49[[#This Row],[ITEM CODE]],Table2[[#All],[Item Code]:[Unit Cost]],10,0),0) -> 1.5 | R6: =Table49[[#This Row],[QUANTITY]]*Table49[[#This Row],[INV Prices]] -> 3 | V6: Sold | W6: =IFERROR(VLOOKUP(Table49[[#This Row],[ITEM CODE]],Table2[[Item Code]:[Category ]],6,0),"") -> FOOD | X6: =IFERROR(VLOOKUP(Table49[[#This Row],[ITEM CODE]],Table2[[Item Code]:[Sub Category]],7,0),"") -> Sandwich | Y6: =Table49[[#This Row],[PO Number]]&COUNTIFS($E$5:E6,E6) -> PO309552
A7: =IF(Table49[[#This Row],[ITEM NAME]]="","",ROW()-4) -> 3 | B7: 45901 | C7: =IFERROR(VLOOKUP(B7,Table14[],3,0),"") -> 9 | D7: =IFERROR(VLOOKUP(B7,Table14[],2,0),"") -> Week 01 | E7: PO30955 | F7: DN-010901 | G7: E-MART24 BKK1 | H7: =IFERROR(VLOOKUP(Table49[[#This Row],[ITEM CODE]],Table2[[Item Code]:[Master Name]],2,0),"") -> F0103010011 | I7: CSW-0003 | J7: =IFERROR(VLOOKUP(Table49[[#This Row],[ITEM CODE]],Table2[[Item Code]:[Master Name]],3,0),"") -> Sausage & Freid Egg Sandwich | K7: =IFERROR(VLOOKUP(Table49[[#This Row],[ITEM CODE]],Table2[[Item Code]:[Master Name]],9,0),"") -> 1BOX*2PCS | L7: =IFERROR(VLOOKUP(Table49[[#This Row],[ITEM CODE]],Table2[[Item Code]:[Master Name]],8,0),"") -> BOX | M7: 2 | N7: =IFERROR(VLOOKUP(Table49[[#This Row],[ITEM CODE]],Table2[[#All],[Item Code]:[Unit Cost]],10,0),0) -> 1.5 | O7: =IFERROR(VLOOKUP(Table49[[#This Row],[ITEM CODE]],Table2[[#All],[Item Code]:[Unit Cost]],10,0),0) -> 1.5 | R7: =Table49[[#This Row],[QUANTITY]]*Table49[[#This Row],[INV Prices]] -> 3 | W7: =IFERROR(VLOOKUP(Table49[[#This Row],[ITEM CODE]],Table2[[Item Code]:[Category ]],6,0),"") -> FOOD | X7: =IFERROR(VLOOKUP(Table49[[#This Row],[ITEM CODE]],Table2[[Item Code]:[Sub Category]],7,0),"") -> Sandwich | Y7: =Table49[[#This Row],[PO Number]]&COUNTIFS($E$5:E7,E7) -> PO309553
A8: =IF(Table49[[#This Row],[ITEM NAME]]="","",ROW()-4) -> 4 | B8: 45901 | C8: =IFERROR(VLOOKUP(B8,Table14[],3,0),"") -> 9 | D8: =IFERROR(VLOOKUP(B8,Table14[],2,0),"") -> Week 01 | E8: PO30955 | F8: DN-010901 | G8: E-MART24 BKK1 | H8: =IFERROR(VLOOKUP(Table49[[#This Row],[ITEM CODE]],Table2[[Item Code]:[Master Name]],2,0),"") -> F0103010012 | I8: CSW-0004 | J8: =IFERROR(VLOOKUP(Table49[[#This Row],[ITEM CODE]],Table2[[Item Code]:[Master Name]],3,0),"") -> Chicken Sandwich | K8: =IFERROR(VLOOKUP(Table49[[#This Row],[ITEM CODE]],Table2[[Item Code]:[Master Name]],9,0),"") -> 1BOX*2PCS | L8: =IFERROR(VLOOKUP(Table49[[#This Row],[ITEM CODE]],Table2[[Item Code]:[Master Name]],8,0),"") -> BOX | M8: 2 | N8: =IFERROR(VLOOKUP(Table49[[#This Row],[ITEM CODE]],Table2[[#All],[Item Code]:[Unit Cost]],10,0),0) -> 1.5 | O8: =IFERROR(VLOOKUP(Table49[[#This Row],[ITEM CODE]],Table2[[#All],[Item Code]:[Unit Cost]],10,0),0) -> 1.5 | R8: =Table49[[#This Row],[QUANTITY]]*Table49[[#This Row],[INV Prices]] -> 3 | V8: Sold | W8: =IFERROR(VLOOKUP(Table49[[#This Row],[ITEM CODE]],Table2[[Item Code]:[Category ]],6,0),"") -> FOOD | X8: =IFERROR(VLOOKUP(Table49[[#This Row],[ITEM CODE]],Table2[[Item Code]:[Sub Category]],7,0),"") -> Sandwich | Y8: =Table49[[#This Row],[PO Number]]&COUNTIFS($E$5:E8,E8) -> PO309554
A9: =IF(Table49[[#This Row],[ITEM NAME]]="","",ROW()-4) -> 5 | B9: 45901 | C9: =IFERROR(VLOOKUP(B9,Table14[],3,0),"") -> 9 | D9: =IFERROR(VLOOKUP(B9,Table14[],2,0),"") -> Week 01 | E9: PO30955 | F9: DN-010901 | G9: E-MART24 BKK1 | H9: =IFERROR(VLOOKUP(Table49[[#This Row],[ITEM CODE]],Table2[[Item Code]:[Master Name]],2,0),"") -> F0101010017 | I9: KL-0001 | J9: =IFERROR(VLOOKUP(Table49[[#This Row],[ITEM CODE]],Table2[[Item Code]:[Master Name]],3,0),"") -> Bulgogi Dosirak-KL-0001 | K9: =IFERROR(VLOOKUP(Table49[[#This Row],[ITEM CODE]],Table2[[Item Code]:[Master Name]],9,0),"") -> 1BOX*1Portion | L9: =IFERROR(VLOOKUP(Table49[[#This Row],[ITEM CODE]],Table2[[Item Code]:[Master Name]],8,0),"") -> BOX | M9: 2 | N9: =IFERROR(VLOOKUP(Table49[[#This Row],[ITEM CODE]],Table2[[#All],[Item Code]:[Unit Cost]],10,0),0) -> 2.2 | O9: =IFERROR(VLOOKUP(Table49[[#This Row],[ITEM CODE]],Table2[[#All],[Item Code]:[Unit Cost]],10,0),0) -> 2.2 | R9: =Table49[[#This Row],[QUANTITY]]*Table49[[#This Row],[INV Prices]] -> 4.4 | V9: Sold | W9: =IFERROR(VLOOKUP(Table49[[#This Row],[ITEM CODE]],Table2[[Item Code]:[Category ]],6,0),"") -> FOOD | X9: =IFERROR(VLOOKUP(Table49[[#This Row],[ITEM CODE]],Table2[[Item Code]:[Sub Category]],7,0),"") -> Korean Lunch Box | Y9: =Table49[[#This Row],[PO Number]]&COUNTIFS($E$5:E9,E9) -> PO309555
A10: =IF(Table49[[#This Row],[ITEM NAME]]="","",ROW()-4) -> 6 | B10: 45901 | C10: =IFERROR(VLOOKUP(B10,Table14[],3,0),"") -> 9 | D10: =IFERROR(VLOOKUP(B10,Table14[],2,0),"") -> Week 01 | E10: PO30955 | F10: DN-010901 | G10: E-MART24 BKK1 | H10: =IFERROR(VLOOKUP(Table49[[#This Row],[ITEM CODE]],Table2[[Item Code]:[Master Name]],2,0),"") -> F0101010015 | I10: KL-0003 | J10: =IFERROR(VLOOKUP(Table49[[#This Row],[ITEM CODE]],Table2[[Item Code]:[Master Name]],3,0),"") -> Japchae Dakgangjeong Dosirak-KL-0003 | K10: =IFERROR(VLOOKUP(Table49[[#This Row],[ITEM CODE]],Table2[[Item Code]:[Master Name]],9,0),"") -> 1BOX*1Portion | L10: =IFERROR(VLOOKUP(Table49[[#This Row],[ITEM CODE]],Table2[[Item Code]:[Master Name]],8,0),"") -> BOX | M10: 2 | N10: =IFERROR(VLOOKUP(Table49[[#This Row],[ITEM CODE]],Table2[[#All],[Item Code]:[Unit Cost]],10,0),0) -> 2.6 | O10: =IFERROR(VLOOKUP(Table49[[#This Row],[ITEM CODE]],Table2[[#All],[Item Code]:[Unit Cost]],10,0),0) -> 2.6 | R10: =Table49[[#This Row],[QUANTITY]]*Table49[[#This Row],[INV Prices]] -> 5.2 | V10: Sold | W10: =IFERROR(VLOOKUP(Table49[[#This Row],[ITEM CODE]],Table2[[Item Code]:[Category ]],6,0),"") -> FOOD | X10: =IFERROR(VLOOKUP(Table49[[#This Row],[ITEM CODE]],Table2[[Item Code]:[Sub Category]],7,0),"") -> Korean Lunch Box | Y10: =Table49[[#This Row],[PO Number]]&COUNTIFS($E$5:E10,E10) -> PO309556
A11: =IF(Table49[[#This Row],[ITEM NAME]]="","",ROW()-4) -> 7 | B11: 45901 | C11: =IFERROR(VLOOKUP(B11,Table14[],3,0),"") -> 9 | D11: =IFERROR(VLOOKUP(B11,Table14[],2,0),"") -> Week 01 | E11: PO30955 | F11: DN-010901 | G11: E-MART24 BKK1 | H11: =IFERROR(VLOOKUP(Table49[[#This Row],[ITEM CODE]],Table2[[Item Code]:[Master Name]],2,0),"") -> F0101010016 | I11: KL-0002 | J11: =IFERROR(VLOOKUP(Table49[[#This Row],[ITEM CODE]],Table2[[Item Code]:[Master Name]],3,0),"") -> Stir Fried Spicy Pork Dosirak-KL-0002 | K11: =IFERROR(VLOOKUP(Table49[[#This Row],[ITEM CODE]],Table2[[Item Code]:[Master Name]],9,0),"") -> 1BOX*1Portion | L11: =IFERROR(VLOOKUP(Table49[[#This Row],[ITEM CODE]],Table2[[Item Code]:[Master Name]],8,0),"") -> BOX | M11: 2 | N11: =IFERROR(VLOOKUP(Table49[[#This Row],[ITEM CODE]],Table2[[#All],[Item Code]:[Unit Cost]],10,0),0) -> 2.38 | O11: =IFERROR(VLOOKUP(Table49[[#This Row],[ITEM CODE]],Table2[[#All],[Item Code]:[Unit Cost]],10,0),0) -> 2.38 | R11: =Table49[[#This Row],[QUANTITY]]*Table49[[#This Row],[INV Prices]] -> 4.76 | V11: Sold | W11: =IFERROR(VLOOKUP(Table49[[#This Row],[ITEM CODE]],Table2[[Item Code]:[Category ]],6,0),"") -> FOOD | X11: =IFERROR(VLOOKUP(Table49[[#This Row],[ITEM CODE]],Table2[[Item Code]:[Sub Category]],7,0),"") -> Korean Lunch Box | Y11: =Table49[[#This Row],[PO Number]]&COUNTIFS($E$5:E11,E11) -> PO309557
A12: =IF(Table49[[#This Row],[ITEM NAME]]="","",ROW()-4) -> 8 | B12: 45901 | C12: =IFERROR(VLOOKUP(B12,Table14[],3,0),"") -> 9 | D12: =IFERROR(VLOOKUP(B12,Table14[],2,0),"") -> Week 01 | E12: PO30955 | F12: DN-010901 | G12: E-MART24 BKK1 | H12: =IFERROR(VLOOKUP(Table49[[#This Row],[ITEM CODE]],Table2[[Item Code]:[Master Name]],2,0),"") -> F0103010013 | I12: SS-0002 | J12: =IFERROR(VLOOKUP(Table49[[#This Row],[ITEM CODE]],Table2[[Item Code]:[Master Name]],3,0),"") -> Maki Crab & Chicken Egg | K12: =IFERROR(VLOOKUP(Table49[[#This Row],[ITEM CODE]],Table2[[Item Code]:[Master Name]],9,0),"") -> 1BOX*6PCS | L12: =IFERROR(VLOOKUP(Table49[[#This Row],[ITEM CODE]],Table2[[Item Code]:[Master Name]],8,0),"") -> Box | M12: 2 | N12: =IFERROR(VLOOKUP(Table49[[#This Row],[ITEM CODE]],Table2[[#All],[Item Code]:[Unit Cost]],10,0),0) -> 1.21 | O12: =IFERROR(VLOOKUP(Table49[[#This Row],[ITEM CODE]],Table2[[#All],[Item Code]:[Unit Cost]],10,0),0) -> 1.21 | R12: =Table49[[#This Row],[QUANTITY]]*Table49[[#This Row],[INV Prices]] -> 2.42 | V12: Sold | W12: =IFERROR(VLOOKUP(Table49[[#This Row],[ITEM CODE]],Table2[[Item Code]:[Category ]],6,0),"") -> FOOD | X12: =IFERROR(VLOOKUP(Table49[[#This Row],[ITEM CODE]],Table2[[Item Code]:[Sub Category]],7,0),"") -> Sushi | Y12: =Table49[[#This Row],[PO Number]]&COUNTIFS($E$5:E12,E12) -> PO309558
A13: =IF(Table49[[#This Row],[ITEM NAME]]="","",ROW()-4) -> 9 | B13: 45901 | C13: =IFERROR(VLOOKUP(B13,Table14[],3,0),"") -> 9 | D13: =IFERROR(VLOOKUP(B13,Table14[],2,0),"") -> Week 01 | E13: PO30955 | F13: DN-010901 | G13: E-MART24 BKK1 | H13: =IFERROR(VLOOKUP(Table49[[#This Row],[ITEM CODE]],Table2[[Item Code]:[Master Name]],2,0),"") -> F0103010014 | I13: SS-0004 | J13: =IFERROR(VLOOKUP(Table49[[#This Row],[ITEM CODE]],Table2[[Item Code]:[Master Name]],3,0),"") -> Maki Cali & Tuna Roll | K13: =IFERROR(VLOOKUP(Table49[[#This Row],[ITEM CODE]],Table2[[Item Code]:[Master Name]],9,0),"") -> 1BOX*3PCS | L13: =IFERROR(VLOOKUP(Table49[[#This Row],[ITEM CODE]],Table2[[Item Code]:[Master Name]],8,0),"") -> Box | M13: 2 | N13: =IFERROR(VLOOKUP(Table49[[#This Row],[ITEM CODE]],Table2[[#All],[Item Code]:[Unit Cost]],10,0),0) -> 1.21 | O13: =IFERROR(VLOOKUP(Table49[[#This Row],[ITEM CODE]],Table2[[#All],[Item Code]:[Unit Cost]],10,0),0) -> 1.21 | R13: =Table49[[#This Row],[QUANTITY]]*Table49[[#This Row],[INV Prices]] -> 2.42 | V13: Sold | W13: =IFERROR(VLOOKUP(Table49[[#This Row],[ITEM CODE]],Table2[[Item Code]:[Category ]],6,0),"") -> FOOD | X13: =IFERROR(VLOOKUP(Table49[[#This Row],[ITEM CODE]],Table2[[Item Code]:[Sub Category]],7,0),"") -> Sushi | Y13: =Table49[[#This Row],[PO Number]]&COUNTIFS($E$5:E13,E13) -> PO309559
A14: =IF(Table49[[#This Row],[ITEM NAME]]="","",ROW()-4) -> 10 | B14: 45901 | C14: =IFERROR(VLOOKUP(B14,Table14[],3,0),"") -> 9 | D14: =IFERROR(VLOOKUP(B14,Table14[],2,0),"") -> Week 01 | E14: PO30959 | F14: DN-010902 | G14: E-MART24 BKK1 | H14: =IFERROR(VLOOKUP(Table49[[#This Row],[ITEM CODE]],Table2[[Item Code]:[Master Name]],2,0),"") -> 900029 | I14: HF-0001 | J14: =IFERROR(VLOOKUP(Table49[[#This Row],[ITEM CODE]],Table2[[Item Code]:[Master Name]],3,0),"") -> BEEF LOK LAK WITH RICE (បាយ​ ឡុកឡាក់សាច់គោ) | K14: =IFERROR(VLOOKUP(Table49[[#This Row],[ITEM CODE]],Table2[[Item Code]:[Master Name]],9,0),"") -> 1BOX*1Portion | L14: =IFERROR(VLOOKUP(Table49[[#This Row],[ITEM CODE]],Table2[[Item Code]:[Master Name]],8,0),"") -> BOX | M14: 2 | N14: =IFERROR(VLOOKUP(Table49[[#This Row],[ITEM CODE]],Table2[[#All],[Item Code]:[Unit Cost]],10,0),0) -> 1.668 | O14: =IFERROR(VLOOKUP(Table49[[#This Row],[ITEM CODE]],Table2[[#All],[Item Code]:[Unit Cost]],10,0),0) -> 1.668 | R14: =Table49[[#This Row],[QUANTITY]]*Table49[[#This Row],[INV Prices]] -> 3.336 | V14: Sold | W14: =IFERROR(VLOOKUP(Table49[[#This Row],[ITEM CODE]],Table2[[Item Code]:[Category ]],6,0),"") -> FOOD | X14: =IFERROR(VLOOKUP(Table49[[#This Row],[ITEM CODE]],Table2[[Item Code]:[Sub Category]],7,0),"") -> Khmer Food | Y14: =Table49[[#This Row],[PO Number]]&COUNTIFS($E$5:E14,E14) -> PO309591
A15: =IF(Table49[[#This Row],[ITEM NAME]]="","",ROW()-4) -> 11 | B15: 45901 | C15: =IFERROR(VLOOKUP(B15,Table14[],3,0),"") -> 9 | D15: =IFERROR(VLOOKUP(B15,Table14[],2,0),"") -> Week 01 | E15: PO30959 | F15: DN-010902 | G15: E-MART24 BKK1 | H15: =IFERROR(VLOOKUP(Table49[[#This Row],[ITEM CODE]],Table2[[Item Code]:[Master Name]],2,0),"") -> 900027 | I15: HF-0002 | J15: =IFERROR(VLOOKUP(Table49[[#This Row],[ITEM CODE]],Table2[[Item Code]:[Master Name]],3,0),"") -> STIR FRIED MINCED PORK HOT BASIL WITH RICE (បាយ សាច់ជ្រូកចិញ្រ្ចាំឆាម្រះព្រៅ) | K15: =IFERROR(VLOOKUP(Table49[[#This Row],[ITEM CODE]],Table2[[Item Code]:[Master Name]],9,0),"") -> 1BOX*1Portion | L15: =IFERROR(VLOOKUP(Table49[[#This Row],[ITEM CODE]],Table2[[Item Code]:[Master Name]],8,0),"") -> BOX | M15: 2 | N15: =IFERROR(VLOOKUP(Table49[[#This Row],[ITEM CODE]],Table2[[#All],[Item Code]:[Unit Cost]],10,0),0) -> 1.2024 | O15: =IFERROR(VLOOKUP(Table49[[#This Row],[ITEM CODE]],Table2[[#All],[Item Code]:[Unit Cost]],10,0),0) -> 1.2024 | R15: =Table49[[#This Row],[QUANTITY]]*Table49[[#This Row],[INV Prices]] -> 2.4048 | V15: Sold | W15: =IFERROR(VLOOKUP(Table49[[#This Row],[ITEM CODE]],Table2[[Item Code]:[Category ]],6,0),"") -> FOOD | X15: =IFERROR(VLOOKUP(Table49[[#This Row],[ITEM CODE]],Table2[[Item Code]:[Sub Category]],7,0),"") -> Khmer Food | Y15: =Table49[[#This Row],[PO Number]]&COUNTIFS($E$5:E15,E15) -> PO309592
A16: =IF(Table49[[#This Row],[ITEM NAME]]="","",ROW()-4) -> 12 | B16: 45901 | C16: =IFERROR(VLOOKUP(B16,Table14[],3,0),"") -> 9 | D16: =IFERROR(VLOOKUP(B16,Table14[],2,0),"") -> Week 01 | E16: PO30959 | F16: DN-010902 | G16: E-MART24 BKK1 | H16: =IFERROR(VLOOKUP(Table49[[#This Row],[ITEM CODE]],Table2[[Item Code]:[Master Name]],2,0),"") -> 900031 | I16: HF-0008 | J16: =IFERROR(VLOOKUP(Table49[[#This Row],[ITEM CODE]],Table2[[Item Code]:[Master Name]],3,0),"") -> ROASTED DUCK WITH RICE (បាយ ទាខ្វៃ) | K16: =IFERROR(VLOOKUP(Table49[[#This Row],[ITEM CODE]],Table2[[Item Code]:[Master Name]],9,0),"") -> 1BOX*1Portion | L16: =IFERROR(VLOOKUP(Table49[[#This Row],[ITEM CODE]],Table2[[Item Code]:[Master Name]],8,0),"") -> BOX | M16: 2 | N16: =IFERROR(VLOOKUP(Table49[[#This Row],[ITEM CODE]],Table2[[#All],[Item Code]:[Unit Cost]],10,0),0) -> 1.4784 | O16: =IFERROR(VLOOKUP(Table49[[#This Row],[ITEM CODE]],Table2[[#All],[Item Code]:[Unit Cost]],10,0),0) -> 1.4784 | R16: =Table49[[#This Row],[QUANTITY]]*Table49[[#This Row],[INV Prices]] -> 2.9568 | V16: Sold | W16: =IFERROR(VLOOKUP(Table49[[#This Row],[ITEM CODE]],Table2[[Item Code]:[Category ]],6,0),"") -> FOOD | X16: =IFERROR(VLOOKUP(Table49[[#This Row],[ITEM CODE]],Table2[[Item Code]:[Sub Category]],7,0),"") -> Khmer Food | Y16: =Table49[[#This Row],[PO Number]]&COUNTIFS($E$5:E16,E16) -> PO309593
A17: =IF(Table49[[#This Row],[ITEM NAME]]="","",ROW()-4) -> 13 | B17: 45901 | C17: =IFERROR(VLOOKUP(B17,Table14[],3,0),"") -> 9 | D17: =IFERROR(VLOOKUP(B17,Table14[],2,0),"") -> Week 01 | E17: PO30959 | F17: DN-010902 | G17: E-MART24 BKK1 | H17: =IFERROR(VLOOKUP(Table49[[#This Row],[ITEM CODE]],Table2[[Item Code]:[Master Name]],2,0),"") -> 900032 | I17: HF-0004 | J17: =IFERROR(VLOOKUP(Table49[[#This Row],[ITEM CODE]],Table2[[Item Code]:[Master Name]],3,0),"") -> STIR FRIED MINCED CHICKEN HOT BASIL WITH RICE (បាយ​ សាច់មាន់ចិញ្រ្ចាំឆាម្រះព្រៅ) | K17: =IFERROR(VLOOKUP(Table49[[#This Row],[ITEM CODE]],Table2[[Item Code]:[Master Name]],9,0),"") -> 1BOX*1Portion | L17: =IFERROR(VLOOKUP(Table49[[#This Row],[ITEM CODE]],Table2[[Item Code]:[Master Name]],8,0),"") -> BOX | M17: 2 | N17: =IFERROR(VLOOKUP(Table49[[#This Row],[ITEM CODE]],Table2[[#All],[Item Code]:[Unit Cost]],10,0),0) -> 1.2984 | O17: =IFERROR(VLOOKUP(Table49[[#This Row],[ITEM CODE]],Table2[[#All],[Item Code]:[Unit Cost]],10,0),0) -> 1.2984 | R17: =Table49[[#This Row],[QUANTITY]]*Table49[[#This Row],[INV Prices]] -> 2.5968 | V17: Sold | W17: =IFERROR(VLOOKUP(Table49[[#This Row],[ITEM CODE]],Table2[[Item Code]:[Category ]],6,0),"") -> FOOD | X17: =IFERROR(VLOOKUP(Table49[[#This Row],[ITEM CODE]],Table2[[Item Code]:[Sub Category]],7,0),"") -> Khmer Food | Y17: =Table49[[#This Row],[PO Number]]&COUNTIFS($E$5:E17,E17) -> PO309594
A18: =IF(Table49[[#This Row],[ITEM NAME]]="","",ROW()-4) -> 14 | B18: 45901 | C18: =IFERROR(VLOOKUP(B18,Table14[],3,0),"") -> 9 | D18: =IFERROR(VLOOKUP(B18,Table14[],2,0),"") -> Week 01 | E18: PO30959 | F18: DN-010902 | G18: E-MART24 BKK1 | H18: =IFERROR(VLOOKUP(Table49[[#This Row],[ITEM CODE]],Table2[[Item Code]:[Master Name]],2,0),"") -> 900028 | I18: HF-0005 | J18: =IFERROR(VLOOKUP(Table49[[#This Row],[ITEM CODE]],Table2[[Item Code]:[Master Name]],3,0),"") -> STIR FRIED MINCED PORK EGGPLANT WITH RICE (បាយ សាច់ជ្រូកចិញ្ច្រាំឆាត្រប់វែង) | K18: =IFERROR(VLOOKUP(Table49[[#This Row],[ITEM CODE]],Table2[[Item Code]:[Master Name]],9,0),"") -> 1BOX*1Portion | L18: =IFERROR(VLOOKUP(Table49[[#This Row],[ITEM CODE]],Table2[[Item Code]:[Master Name]],8,0),"") -> BOX | M18: 2 | N18: =IFERROR(VLOOKUP(Table49[[#This Row],[ITEM CODE]],Table2[[#All],[Item Code]:[Unit Cost]],10,0),0) -> 1.0104 | O18: =IFERROR(VLOOKUP(Table49[[#This Row],[ITEM CODE]],Table2[[#All],[Item Code]:[Unit Cost]],10,0),0) -> 1.0104 | R18: =Table49[[#This Row],[QUANTITY]]*Table49[[#This Row],[INV Prices]] -> 2.0208 | V18: Sold | W18: =IFERROR(VLOOKUP(Table49[[#This Row],[ITEM CODE]],Table2[[Item Code]:[Category ]],6,0),"") -> FOOD | X18: =IFERROR(VLOOKUP(Table49[[#This Row],[ITEM CODE]],Table2[[Item Code]:[Sub Category]],7,0),"") -> Khmer Food | Y18: =Table49[[#This Row],[PO Number]]&COUNTIFS($E$5:E18,E18) -> PO309595
A19: =IF(Table49[[#This Row],[ITEM NAME]]="","",ROW()-4) -> 15 | B19: 45901 | C19: =IFERROR(VLOOKUP(B19,Table14[],3,0),"") -> 9 | D19: =IFERROR(VLOOKUP(B19,Table14[],2,0),"") -> Week 01 | E19: PO30959 | F19: DN-010902 | G19: E-MART24 BKK1 | H19: =IFERROR(VLOOKUP(Table49[[#This Row],[ITEM CODE]],Table2[[Item Code]:[Master Name]],2,0),"") -> 900038 | I19: HF-0010 | J19: =IFERROR(VLOOKUP(Table49[[#This Row],[ITEM CODE]],Table2[[Item Code]:[Master Name]],3,0),"") -> ROATED PORK BELLY WITH RICE (បាយ សាច់ជ្រូក៣ជាន់) | K19: =IFERROR(VLOOKUP(Table49[[#This Row],[ITEM CODE]],Table2[[Item Code]:[Master Name]],9,0),"") -> 1BOX*1Portion | L19: =IFERROR(VLOOKUP(Table49[[#This Row],[ITEM CODE]],Table2[[Item Code]:[Master Name]],8,0),"") -> BOX | M19: 2 | N19: =IFERROR(VLOOKUP(Table49[[#This Row],[ITEM CODE]],Table2[[#All],[Item Code]:[Unit Cost]],10,0),0) -> 1.092 | O19: =IFERROR(VLOOKUP(Table49[[#This Row],[ITEM CODE]],Table2[[#All],[Item Code]:[Unit Cost]],10,0),0) -> 1.092 | R19: =Table49[[#This Row],[QUANTITY]]*Table49[[#This Row],[INV Prices]] -> 2.184 | V19: Sold | W19: =IFERROR(VLOOKUP(Table49[[#This Row],[ITEM CODE]],Table2[[Item Code]:[Category ]],6,0),"") -> FOOD | X19: =IFERROR(VLOOKUP(Table49[[#This Row],[ITEM CODE]],Table2[[Item Code]:[Sub Category]],7,0),"") -> Khmer Food | Y19: =Table49[[#This Row],[PO Number]]&COUNTIFS($E$5:E19,E19) -> PO309596
... A23: =IF(Table49[[#This Row],[ITEM NAME]]="","",ROW()-4) -> 19 | B23: 45901 | C23: =IFERROR(VLOOKUP(B23,Table14[],3,0),"") -> 9 | D23: =IFERROR(VLOOKUP(B23,Table14[],2,0),"") -> Week 01 | E23: PO30959 | F23: DN-010902 | G23: E-MART24 BKK1 | H23: =IFERROR(VLOOKUP(Table49[[#This Row],[ITEM CODE]],Table2[[Item Code]:[Master Name]],2,0),"") -> F0101010018 | I23: HF-0027 | J23: =IFERROR(VLOOKUP(Table49[[#This Row],[ITEM CODE]],Table2[[Item Code]:[Master Name]],3,0),"") -> Salmon Fried Rice (បា​យឆា សាលម៉ុន) | K23: =IFERROR(VLOOKUP(Table49[[#This Row],[ITEM CODE]],Table2[[Item Code]:[Master Name]],9,0),"") -> 1BOX*1Portion | L23: =IFERROR(VLOOKUP(Table49[[#This Row],[ITEM CODE]],Table2[[Item Code]:[Master Name]],8,0),"") -> BOX | M23: 1 | N23: =IFERROR(VLOOKUP(Table49[[#This Row],[ITEM CODE]],Table2[[#All],[Item Code]:[Unit Cost]],10,0),0) -> 1.6 | O23: =IFERROR(VLOOKUP(Table49[[#This Row],[ITEM CODE]],Table2[[#All],[Item Code]:[Unit Cost]],10,0),0) -> 1.6 | R23: =Table49[[#This Row],[QUANTITY]]*Table49[[#This Row],[INV Prices]] -> 1.6 | V23: Sold | W23: =IFERROR(VLOOKUP(Table49[[#This Row],[ITEM CODE]],Table2[[Item Code]:[Category ]],6,0),"") -> FOOD | X23: =IFERROR(VLOOKUP(Table49[[#This Row],[ITEM CODE]],Table2[[Item Code]:[Sub Category]],7,0),"") -> Khmer Food | Y23: =Table49[[#This Row],[PO Number]]&COUNTIFS($E$5:E23,E23) -> PO3095910
A24: =IF(Table49[[#This Row],[ITEM NAME]]="","",ROW()-4) -> 20 | B24: 45901 | C24: =IFERROR(VLOOKUP(B24,Table14[],3,0),"") -> 9 | D24: =IFERROR(VLOOKUP(B24,Table14[],2,0),"") -> Week 01 | E24: PO30959 | F24: DN-010902 | G24: E-MART24 BKK1 | H24: =IFERROR(VLOOKUP(Table49[[#This Row],[ITEM CODE]],Table2[[Item Code]:[Master Name]],2,0),"") -> F0101010019 | I24: HF-0028 | J24: =IFERROR(VLOOKUP(Table49[[#This Row],[ITEM CODE]],Table2[[Item Code]:[Master Name]],3,0),"") -> Crab Fried Rice (បាយឆា ក្ដាម) | K24: =IFERROR(VLOOKUP(Table49[[#This Row],[ITEM CODE]],Table2[[Item Code]:[Master Name]],9,0),"") -> 1BOX*1Portion | L24: =IFERROR(VLOOKUP(Table49[[#This Row],[ITEM CODE]],Table2[[Item Code]:[Master Name]],8,0),"") -> BOX | M24: 1 | N24: =IFERROR(VLOOKUP(Table49[[#This Row],[ITEM CODE]],Table2[[#All],[Item Code]:[Unit Cost]],10,0),0) -> 1.6 | O24: =IFERROR(VLOOKUP(Table49[[#This Row],[ITEM CODE]],Table2[[#All],[Item Code]:[Unit Cost]],10,0),0) -> 1.6 | R24: =Table49[[#This Row],[QUANTITY]]*Table49[[#This Row],[INV Prices]] -> 1.6 | W24: =IFERROR(VLOOKUP(Table49[[#This Row],[ITEM CODE]],Table2[[Item Code]:[Category ]],6,0),"") -> FOOD | X24: =IFERROR(VLOOKUP(Table49[[#This Row],[ITEM CODE]],Table2[[Item Code]:[Sub Category]],7,0),"") -> Khmer Food | Y24: =Table49[[#This Row],[PO Number]]&COUNTIFS($E$5:E24,E24) -> PO3095911
A25: =IF(Table49[[#This Row],[ITEM NAME]]="","",ROW()-4) -> 21 | B25: 45901 | C25: =IFERROR(VLOOKUP(B25,Table14[],3,0),"") -> 9 | D25: =IFERROR(VLOOKUP(B25,Table14[],2,0),"") -> Week 01 | E25: PO30959 | F25: DN-010902 | G25: E-MART24 BKK1 | H25: =IFERROR(VLOOKUP(Table49[[#This Row],[ITEM CODE]],Table2[[Item Code]:[Master Name]],2,0),"") -> 900152 | I25: V-0102 | J25: =IFERROR(VLOOKUP(Table49[[#This Row],[ITEM CODE]],Table2[[Item Code]:[Master Name]],3,0),"") -> Lettuce Iceberg | K25: =IFERROR(VLOOKUP(Table49[[#This Row],[ITEM CODE]],Table2[[Item Code]:[Master Name]],9,0),"") -> KG | L25: =IFERROR(VLOOKUP(Table49[[#This Row],[ITEM CODE]],Table2[[Item Code]:[Master Name]],8,0),"") -> KG | M25: 1 | N25: =IFERROR(VLOOKUP(Table49[[#This Row],[ITEM CODE]],Table2[[#All],[Item Code]:[Unit Cost]],10,0),0) -> 3.12 | O25: =IFERROR(VLOOKUP(Table49[[#This Row],[ITEM CODE]],Table2[[#All],[Item Code]:[Unit Cost]],10,0),0) -> 3.12 | R25: =Table49[[#This Row],[QUANTITY]]*Table49[[#This Row],[INV Prices]] -> 3.12 | W25: =IFERROR(VLOOKUP(Table49[[#This Row],[ITEM CODE]],Table2[[Item Code]:[Category ]],6,0),"") -> FOOD | X25: =IFERROR(VLOOKUP(Table49[[#This Row],[ITEM CODE]],Table2[[Item Code]:[Sub Category]],7,0),"") -> Fruits & Veggies / Veggies | Y25: =Table49[[#This Row],[PO Number]]&COUNTIFS($E$5:E25,E25) -> PO3095912
A26: =IF(Table49[[#This Row],[ITEM NAME]]="","",ROW()-4) -> 22 | B26: 45901 | C26: =IFERROR(VLOOKUP(B26,Table14[],3,0),"") -> 9 | D26: =IFERROR(VLOOKUP(B26,Table14[],2,0),"") -> Week 01 | E26: PO30959 | F26: DN-010902 | G26: E-MART24 BKK1 | H26: =IFERROR(VLOOKUP(Table49[[#This Row],[ITEM CODE]],Table2[[Item Code]:[Master Name]],2,0),"") -> 900153 | I26: V-0038 | J26: =IFERROR(VLOOKUP(Table49[[#This Row],[ITEM CODE]],Table2[[Item Code]:[Master Name]],3,0),"") -> White Radish (Daikon) | K26: =IFERROR(VLOOKUP(Table49[[#This Row],[ITEM CODE]],Table2[[Item Code]:[Master Name]],9,0),"") -> KG | L26: =IFERROR(VLOOKUP(Table49[[#This Row],[ITEM CODE]],Table2[[Item Code]:[Master Name]],8,0),"") -> KG | M26: 1 | N26: =IFERROR(VLOOKUP(Table49[[#This Row],[ITEM CODE]],Table2[[#All],[Item Code]:[Unit Cost]],10,0),0) -> 0.84 | O26: =IFERROR(VLOOKUP(Table49[[#This Row],[ITEM CODE]],Table2[[#All],[Item Code]:[Unit Cost]],10,0),0) -> 0.84 | R26: =Table49[[#This Row],[QUANTITY]]*Table49[[#This Row],[INV Prices]] -> 0.84 | W26: =IFERROR(VLOOKUP(Table49[[#This Row],[ITEM CODE]],Table2[[Item Code]:[Category ]],6,0),"") -> FOOD | X26: =IFERROR(VLOOKUP(Table49[[#This Row],[ITEM CODE]],Table2[[Item Code]:[Sub Category]],7,0),"") -> Fruits & Veggies / Veggies | Y26: =Table49[[#This Row],[PO Number]]&COUNTIFS($E$5:E26,E26) -> PO3095913
A27: =IF(Table49[[#This Row],[ITEM NAME]]="","",ROW()-4) -> 23 | B27: 45901 | C27: =IFERROR(VLOOKUP(B27,Table14[],3,0),"") -> 9 | D27: =IFERROR(VLOOKUP(B27,Table14[],2,0),"") -> Week 01 | E27: PO30959 | F27: DN-010902 | G27: E-MART24 BKK1 | H27: =IFERROR(VLOOKUP(Table49[[#This Row],[ITEM CODE]],Table2[[Item Code]:[Master Name]],2,0),"") -> 900268 | I27: I-0001 | J27: =IFERROR(VLOOKUP(Table49[[#This Row],[ITEM CODE]],Table2[[Item Code]:[Master Name]],3,0),"") -> White Sugar (Bag*50Kg) | K27: =IFERROR(VLOOKUP(Table49[[#This Row],[ITEM CODE]],Table2[[Item Code]:[Master Name]],9,0),"") -> 1BAG*50KG | L27: =IFERROR(VLOOKUP(Table49[[#This Row],[ITEM CODE]],Table2[[Item Code]:[Master Name]],8,0),"") -> KG | M27: 50 | N27: =IFERROR(VLOOKUP(Table49[[#This Row],[ITEM CODE]],Table2[[#All],[Item Code]:[Unit Cost]],10,0),0) -> 0.96 | O27: =IFERROR(VLOOKUP(Table49[[#This Row],[ITEM CODE]],Table2[[#All],[Item Code]:[Unit Cost]],10,0),0) -> 0.96 | R27: =Table49[[#This Row],[QUANTITY]]*Table49[[#This Row],[INV Prices]] -> 48 | W27: =IFERROR(VLOOKUP(Table49[[#This Row],[ITEM CODE]],Table2[[Item Code]:[Category ]],6,0),"") -> FOOD | X27: =IFERROR(VLOOKUP(Table49[[#This Row],[ITEM CODE]],Table2[[Item Code]:[Sub Category]],7,0),"") -> Ingredients | Y27: =Table49[[#This Row],[PO Number]]&COUNTIFS($E$5:E27,E27) -> PO3095914
A28: =IF(Table49[[#This Row],[ITEM NAME]]="","",ROW()-4) -> 24 | B28: 45901 | C28: =IFERROR(VLOOKUP(B28,Table14[],3,0),"") -> 9 | D28: =IFERROR(VLOOKUP(B28,Table14[],2,0),"") -> Week 01 | E28: PO30959 | F28: DN-010902 | G28: E-MART24 BKK1 | H28: =IFERROR(VLOOKUP(Table49[[#This Row],[ITEM CODE]],Table2[[Item Code]:[Master Name]],2,0),"") -> 900295 | I28: P-0033 | J28: =IFERROR(VLOOKUP(Table49[[#This Row],[ITEM CODE]],Table2[[Item Code]:[Master Name]],3,0),"") -> Kelly Cling Wrap (ហ្វីមរុំម្ហូប) | K28: =IFERROR(VLOOKUP(Table49[[#This Row],[ITEM CODE]],Table2[[Item Code]:[Master Name]],9,0),"") -> 1ROLL*600M*45CM | L28: =IFERROR(VLOOKUP(Table49[[#This Row],[ITEM CODE]],Table2[[Item Code]:[Master Name]],8,0),"") -> ROLL | M28: 2 | N28: =IFERROR(VLOOKUP(Table49[[#This Row],[ITEM CODE]],Table2[[#All],[Item Code]:[Unit Cost]],10,0),0) -> 21.6 | O28: =IFERROR(VLOOKUP(Table49[[#This Row],[ITEM CODE]],Table2[[#All],[Item Code]:[Unit Cost]],10,0),0) -> 21.6 | R28: =Table49[[#This Row],[QUANTITY]]*Table49[[#This Row],[INV Prices]] -> 43.2 | W28: =IFERROR(VLOOKUP(Table49[[#This Row],[ITEM CODE]],Table2[[Item Code]:[Category ]],6,0),"") -> NON-FOOD | X28: =IFERROR(VLOOKUP(Table49[[#This Row],[ITEM CODE]],Table2[[Item Code]:[Sub Category]],7,0),"") -> NON-FOOD | Y28: =Table49[[#This Row],[PO Number]]&COUNTIFS($E$5:E28,E28) -> PO3095915
A29: =IF(Table49[[#This Row],[ITEM NAME]]="","",ROW()-4) -> 25 | B29: 45901 | C29: =IFERROR(VLOOKUP(B29,Table14[],3,0),"") -> 9 | D29: =IFERROR(VLOOKUP(B29,Table14[],2,0),"") -> Week 01 | E29: PO30959 | F29: DN-010902 | G29: E-MART24 BKK1 | H29: =IFERROR(VLOOKUP(Table49[[#This Row],[ITEM CODE]],Table2[[Item Code]:[Master Name]],2,0),"") -> 900296 | I29: P-0041 | J29: =IFERROR(VLOOKUP(Table49[[#This Row],[ITEM CODE]],Table2[[Item Code]:[Master Name]],3,0),"") -> Baking Paper | K29: =IFERROR(VLOOKUP(Table49[[#This Row],[ITEM CODE]],Table2[[Item Code]:[Master Name]],9,0),"") -> 1ROLL*600M*45CM | L29: =IFERROR(VLOOKUP(Table49[[#This Row],[ITEM CODE]],Table2[[Item Code]:[Master Name]],8,0),"") -> ROLL | M29: 1 | N29: =IFERROR(VLOOKUP(Table49[[#This Row],[ITEM CODE]],Table2[[#All],[Item Code]:[Unit Cost]],10,0),0) -> 22.8 | O29: =IFERROR(VLOOKUP(Table49[[#This Row],[ITEM CODE]],Table2[[#All],[Item Code]:[Unit Cost]],10,0),0) -> 22.8 | R29: =Table49[[#This Row],[QUANTITY]]*Table49[[#This Row],[INV Prices]] -> 22.8 | W29: =IFERROR(VLOOKUP(Table49[[#This Row],[ITEM CODE]],Table2[[Item Code]:[Category ]],6,0),"") -> NON-FOOD | X29: =IFERROR(VLOOKUP(Table49[[#This Row],[ITEM CODE]],Table2[[Item Code]:[Sub Category]],7,0),"") -> NON-FOOD | Y29: =Table49[[#This Row],[PO Number]]&COUNTIFS($E$5:E29,E29) -> PO3095916
A30: =IF(Table49[[#This Row],[ITEM NAME]]="","",ROW()-4) -> 26 | B30: 45901 | C30: =IFERROR(VLOOKUP(B30,Table14[],3,0),"") -> 9 | D30: =IFERROR(VLOOKUP(B30,Table14[],2,0),"") -> Week 01 | E30: PO30959 | F30: DN-010902 | G30: E-MART24 BKK1 | H30: =IFERROR(VLOOKUP(Table49[[#This Row],[ITEM CODE]],Table2[[Item Code]:[Master Name]],2,0),"") -> 900271 | I30: I-0212 | J30: =IFERROR(VLOOKUP(Table49[[#This Row],[ITEM CODE]],Table2[[Item Code]:[Master Name]],3,0),"") -> Best Food Mayonniase 3.5KG | K30: =IFERROR(VLOOKUP(Table49[[#This Row],[ITEM CODE]],Table2[[Item Code]:[Master Name]],9,0),"") -> 1CTN*4TUB*3.5KG | L30: =IFERROR(VLOOKUP(Table49[[#This Row],[ITEM CODE]],Table2[[Item Code]:[Master Name]],8,0),"") -> TUB | M30: 2 | N30: =IFERROR(VLOOKUP(Table49[[#This Row],[ITEM CODE]],Table2[[#All],[Item Code]:[Unit Cost]],10,0),0) -> 22.8 | O30: =IFERROR(VLOOKUP(Table49[[#This Row],[ITEM CODE]],Table2[[#All],[Item Code]:[Unit Cost]],10,0),0) -> 22.8 | R30: =Table49[[#This Row],[QUANTITY]]*Table49[[#This Row],[INV Prices]] -> 45.6 | W30: =IFERROR(VLOOKUP(Table49[[#This Row],[ITEM CODE]],Table2[[Item Code]:[Category ]],6,0),"") -> FOOD | X30: =IFERROR(VLOOKUP(Table49[[#This Row],[ITEM CODE]],Table2[[Item Code]:[Sub Category]],7,0),"") -> Ingredients | Y30: =Table49[[#This Row],[PO Number]]&COUNTIFS($E$5:E30,E30) -> PO3095917
A31: =IF(Table49[[#This Row],[ITEM NAME]]="","",ROW()-4) -> 27 | B31: 45901 | C31: =IFERROR(VLOOKUP(B31,Table14[],3,0),"") -> 9 | D31: =IFERROR(VLOOKUP(B31,Table14[],2,0),"") -> Week 01 | E31: PO30956 | F31: DN-010903 | G31: E-MART24 BKK3 | H31: =IFERROR(VLOOKUP(Table49[[#This Row],[ITEM CODE]],Table2[[Item Code]:[Master Name]],2,0),"") -> F0103010009 | I31: CSW-0001 | J31: =IFERROR(VLOOKUP(Table49[[#This Row],[ITEM CODE]],Table2[[Item Code]:[Master Name]],3,0),"") -> Tuna & Egg Sandwich | K31: =IFERROR(VLOOKUP(Table49[[#This Row],[ITEM CODE]],Table2[[Item Code]:[Master Name]],9,0),"") -> 1BOX*2PCS | L31: =IFERROR(VLOOKUP(Table49[[#This Row],[ITEM CODE]],Table2[[Item Code]:[Master Name]],8,0),"") -> BOX | M31: 1 | N31: =IFERROR(VLOOKUP(Table49[[#This Row],[ITEM CODE]],Table2[[#All],[Item Code]:[Unit Cost]],10,0),0) -> 1.5 | O31: =IFERROR(VLOOKUP(Table49[[#This Row],[ITEM CODE]],Table2[[#All],[Item Code]:[Unit Cost]],10,0),0) -> 1.5 | R31: =Table49[[#This Row],[QUANTITY]]*Table49[[#This Row],[INV Prices]] -> 1.5 | W31: =IFERROR(VLOOKUP(Table49[[#This Row],[ITEM CODE]],Table2[[Item Code]:[Category ]],6,0),"") -> FOOD | X31: =IFERROR(VLOOKUP(Table49[[#This Row],[ITEM CODE]],Table2[[Item Code]:[Sub Category]],7,0),"") -> Sandwich | Y31: =Table49[[#This Row],[PO Number]]&COUNTIFS($E$5:E31,E31) -> PO309561
A32: =IF(Table49[[#This Row],[ITEM NAME]]="","",ROW()-4) -> 28 | B32: 45901 | C32: =IFERROR(VLOOKUP(B32,Table14[],3,0),"") -> 9 | D32: =IFERROR(VLOOKUP(B32,Table14[],2,0),"") -> Week 01 | E32: PO30956 | F32: DN-010903 | G32: E-MART24 BKK3 | H32: =IFERROR(VLOOKUP(Table49[[#This Row],[ITEM CODE]],Table2[[Item Code]:[Master Name]],2,0),"") -> F0103010010 | I32: CSW-0002 | J32: =IFERROR(VLOOKUP(Table49[[#This Row],[ITEM CODE]],Table2[[Item Code]:[Master Name]],3,0),"") -> Ham & Corn Sandwich | K32: =IFERROR(VLOOKUP(Table49[[#This Row],[ITEM CODE]],Table2[[Item Code]:[Master Name]],9,0),"") -> 1BOX*2PCS | L32: =IFERROR(VLOOKUP(Table49[[#This Row],[ITEM CODE]],Table2[[Item Code]:[Master Name]],8,0),"") -> BOX | M32: 1 | N32: =IFERROR(VLOOKUP(Table49[[#This Row],[ITEM CODE]],Table2[[#All],[Item Code]:[Unit Cost]],10,0),0) -> 1.5 | O32: =IFERROR(VLOOKUP(Table49[[#This Row],[ITEM CODE]],Table2[[#All],[Item Code]:[Unit Cost]],10,0),0) -> 1.5 | R32: =Table49[[#This Row],[QUANTITY]]*Table49[[#This Row],[INV Prices]] -> 1.5 | W32: =IFERROR(VLOOKUP(Table49[[#This Row],[ITEM CODE]],Table2[[Item Code]:[Category ]],6,0),"") -> FOOD | X32: =IFERROR(VLOOKUP(Table49[[#This Row],[ITEM CODE]],Table2[[Item Code]:[Sub Category]],7,0),"") -> Sandwich | Y32: =Table49[[#This Row],[PO Number]]&COUNTIFS($E$5:E32,E32) -> PO309562
A33: =IF(Table49[[#This Row],[ITEM NAME]]="","",ROW()-4) -> 29 | B33: 45901 | C33: =IFERROR(VLOOKUP(B33,Table14[],3,0),"") -> 9 | D33: =IFERROR(VLOOKUP(B33,Table14[],2,0),"") -> Week 01 | E33: PO30956 | F33: DN-010903 | G33: E-MART24 BKK3 | H33: =IFERROR(VLOOKUP(Table49[[#This Row],[ITEM CODE]],Table2[[Item Code]:[Master Name]],2,0),"") -> F0103010011 | I33: CSW-0003 | J33: =IFERROR(VLOOKUP(Table49[[#This Row],[ITEM CODE]],Table2[[Item Code]:[Master Name]],3,0),"") -> Sausage & Freid Egg Sandwich | K33: =IFERROR(VLOOKUP(Table49[[#This Row],[ITEM CODE]],Table2[[Item Code]:[Master Name]],9,0),"") -> 1BOX*2PCS | L33: =IFERROR(VLOOKUP(Table49[[#This Row],[ITEM CODE]],Table2[[Item Code]:[Master Name]],8,0),"") -> BOX | M33: 1 | N33: =IFERROR(VLOOKUP(Table49[[#This Row],[ITEM CODE]],Table2[[#All],[Item Code]:[Unit Cost]],10,0),0) -> 1.5 | O33: =IFERROR(VLOOKUP(Table49[[#This Row],[ITEM CODE]],Table2[[#All],[Item Code]:[Unit Cost]],10,0),0) -> 1.5 | R33: =Table49[[#This Row],[QUANTITY]]*Table49[[#This Row],[INV Prices]] -> 1.5 | W33: =IFERROR(VLOOKUP(Table49[[#This Row],[ITEM CODE]],Table2[[Item Code]:[Category ]],6,0),"") -> FOOD | X33: =IFERROR(VLOOKUP(Table49[[#This Row],[ITEM CODE]],Table2[[Item Code]:[Sub Category]],7,0),"") -> Sandwich | Y33: =Table49[[#This Row],[PO Number]]&COUNTIFS($E$5:E33,E33) -> PO309563
A34: =IF(Table49[[#This Row],[ITEM NAME]]="","",ROW()-4) -> 30 | B34: 45901 | C34: =IFERROR(VLOOKUP(B34,Table14[],3,0),"") -> 9 | D34: =IFERROR(VLOOKUP(B34,Table14[],2,0),"") -> Week 01 | E34: PO30956 | F34: DN-010903 | G34: E-MART24 BKK3 | H34: =IFERROR(VLOOKUP(Table49[[#This Row],[ITEM CODE]],Table2[[Item Code]:[Master Name]],2,0),"") -> F0103010012 | I34: CSW-0004 | J34: =IFERROR(VLOOKUP(Table49[[#This Row],[ITEM CODE]],Table2[[Item Code]:[Master Name]],3,0),"") -> Chicken Sandwich | K34: =IFERROR(VLOOKUP(Table49[[#This Row],[ITEM CODE]],Table2[[Item Code]:[Master Name]],9,0),"") -> 1BOX*2PCS | L34: =IFERROR(VLOOKUP(Table49[[#This Row],[ITEM CODE]],Table2[[Item Code]:[Master Name]],8,0),"") -> BOX | M34: 1 | N34: =IFERROR(VLOOKUP(Table49[[#This Row],[ITEM CODE]],Table2[[#All],[Item Code]:[Unit Cost]],10,0),0) -> 1.5 | O34: =IFERROR(VLOOKUP(Table49[[#This Row],[ITEM CODE]],Table2[[#All],[Item Code]:[Unit Cost]],10,0),0) -> 1.5 | R34: =Table49[[#This Row],[QUANTITY]]*Table49[[#This Row],[INV Prices]] -> 1.5 | W34: =IFERROR(VLOOKUP(Table49[[#This Row],[ITEM CODE]],Table2[[Item Code]:[Category ]],6,0),"") -> FOOD | X34: =IFERROR(VLOOKUP(Table49[[#This Row],[ITEM CODE]],Table2[[Item Code]:[Sub Category]],7,0),"") -> Sandwich | Y34: =Table49[[#This Row],[PO Number]]&COUNTIFS($E$5:E34,E34) -> PO309564
A35: =IF(Table49[[#This Row],[ITEM NAME]]="","",ROW()-4) -> 31 | B35: 45901 | C35: =IFERROR(VLOOKUP(B35,Table14[],3,0),"") -> 9 | D35: =IFERROR(VLOOKUP(B35,Table14[],2,0),"") -> Week 01 | E35: PO30956 | F35: DN-010903 | G35: E-MART24 BKK3 | H35: =IFERROR(VLOOKUP(Table49[[#This Row],[ITEM CODE]],Table2[[Item Code]:[Master Name]],2,0),"") -> F0101010017 | I35: KL-0001 | J35: =IFERROR(VLOOKUP(Table49[[#This Row],[ITEM CODE]],Table2[[Item Code]:[Master Name]],3,0),"") -> Bulgogi Dosirak-KL-0001 | K35: =IFERROR(VLOOKUP(Table49[[#This Row],[ITEM CODE]],Table2[[Item Code]:[Master Name]],9,0),"") -> 1BOX*1Portion | L35: =IFERROR(VLOOKUP(Table49[[#This Row],[ITEM CODE]],Table2[[Item Code]:[Master Name]],8,0),"") -> BOX | M35: 1 | N35: =IFERROR(VLOOKUP(Table49[[#This Row],[ITEM CODE]],Table2[[#All],[Item Code]:[Unit Cost]],10,0),0) -> 2.2 | O35: =IFERROR(VLOOKUP(Table49[[#This Row],[ITEM CODE]],Table2[[#All],[Item Code]:[Unit Cost]],10,0),0) -> 2.2 | R35: =Table49[[#This Row],[QUANTITY]]*Table49[[#This Row],[INV Prices]] -> 2.2 | W35: =IFERROR(VLOOKUP(Table49[[#This Row],[ITEM CODE]],Table2[[Item Code]:[Category ]],6,0),"") -> FOOD | X35: =IFERROR(VLOOKUP(Table49[[#This Row],[ITEM CODE]],Table2[[Item Code]:[Sub Category]],7,0),"") -> Korean Lunch Box | Y35: =Table49[[#This Row],[PO Number]]&COUNTIFS($E$5:E35,E35) -> PO309565
... A903: =IF(Table49[[#This Row],[ITEM NAME]]="","",ROW()-4) -> 899 | B903: 45904 | C903: =IFERROR(VLOOKUP(B903,Table14[],3,0),"") -> 9 | D903: =IFERROR(VLOOKUP(B903,Table14[],2,0),"") -> Week 01 | E903: PO31211 | F903: DN-040919 | G903: E-MART ANLONG KNGAN (TK) | H903: =IFERROR(VLOOKUP(Table49[[#This Row],[ITEM CODE]],Table2[[Item Code]:[Master Name]],2,0),"") -> 0 | I903: M-0099 | J903: =IFERROR(VLOOKUP(Table49[[#This Row],[ITEM CODE]],Table2[[Item Code]:[Master Name]],3,0),"") -> Smoked Bacon 1kg | K903: =IFERROR(VLOOKUP(Table49[[#This Row],[ITEM CODE]],Table2[[Item Code]:[Master Name]],9,0),"") -> 1PKT*1KG | L903: =IFERROR(VLOOKUP(Table49[[#This Row],[ITEM CODE]],Table2[[Item Code]:[Master Name]],8,0),"") -> KG | M903: 3 | N903: =IFERROR(VLOOKUP(Table49[[#This Row],[ITEM CODE]],Table2[[#All],[Item Code]:[Unit Cost]],10,0),0) -> 15.6 | O903: =IFERROR(VLOOKUP(Table49[[#This Row],[ITEM CODE]],Table2[[#All],[Item Code]:[Unit Cost]],10,0),0) -> 15.6 | R903: =Table49[[#This Row],[QUANTITY]]*Table49[[#This Row],[INV Prices]] -> 46.8 | W903: =IFERROR(VLOOKUP(Table49[[#This Row],[ITEM CODE]],Table2[[Item Code]:[Category ]],6,0),"") -> FOOD | X903: =IFERROR(VLOOKUP(Table49[[#This Row],[ITEM CODE]],Table2[[Item Code]:[Sub Category]],7,0),"") -> Froozen Food | Y903: =Table49[[#This Row],[PO Number]]&COUNTIFS($E$5:E903,E903) -> PO3121115
A904: =IF(Table49[[#This Row],[ITEM NAME]]="","",ROW()-4) | C904: =IFERROR(VLOOKUP(B904,Table14[],3,0),"") | D904: =IFERROR(VLOOKUP(B904,Table14[],2,0),"") | H904: =IFERROR(VLOOKUP(Table49[[#This Row],[ITEM CODE]],Table2[[Item Code]:[Master Name]],2,0),"") | J904: =IFERROR(VLOOKUP(Table49[[#This Row],[ITEM CODE]],Table2[[Item Code]:[Master Name]],3,0),"") | K904: =IFERROR(VLOOKUP(Table49[[#This Row],[ITEM CODE]],Table2[[Item Code]:[Master Name]],9,0),"") | L904: =IFERROR(VLOOKUP(Table49[[#This Row],[ITEM CODE]],Table2[[Item Code]:[Master Name]],8,0),"") | N904: =IFERROR(VLOOKUP(Table49[[#This Row],[ITEM CODE]],Table2[[#All],[Item Code]:[Unit Cost]],10,0),0) -> 0 | O904: =IFERROR(VLOOKUP(Table49[[#This Row],[ITEM CODE]],Table2[[#All],[Item Code]:[Unit Cost]],10,0),0) -> 0 | R904: =Table49[[#This Row],[QUANTITY]]*Table49[[#This Row],[INV Prices]] -> 0 | W904: =IFERROR(VLOOKUP(Table49[[#This Row],[ITEM CODE]],Table2[[Item Code]:[Category ]],6,0),"") | X904: =IFERROR(VLOOKUP(Table49[[#This Row],[ITEM CODE]],Table2[[Item Code]:[Sub Category]],7,0),"") | Y904: =Table49[[#This Row],[PO Number]]&COUNTIFS($E$5:E904,E904) -> 0
A905: =IF(Table49[[#This Row],[ITEM NAME]]="","",ROW()-4) | C905: =IFERROR(VLOOKUP(B905,Table14[],3,0),"") | D905: =IFERROR(VLOOKUP(B905,Table14[],2,0),"") | H905: =IFERROR(VLOOKUP(Table49[[#This Row],[ITEM CODE]],Table2[[Item Code]:[Master Name]],2,0),"") | J905: =IFERROR(VLOOKUP(Table49[[#This Row],[ITEM CODE]],Table2[[Item Code]:[Master Name]],3,0),"") | K905: =IFERROR(VLOOKUP(Table49[[#This Row],[ITEM CODE]],Table2[[Item Code]:[Master Name]],9,0),"") | L905: =IFERROR(VLOOKUP(Table49[[#This Row],[ITEM CODE]],Table2[[Item Code]:[Master Name]],8,0),"") | N905: =IFERROR(VLOOKUP(Table49[[#This Row],[ITEM CODE]],Table2[[#All],[Item Code]:[Unit Cost]],10,0),0) -> 0 | O905: =IFERROR(VLOOKUP(Table49[[#This Row],[ITEM CODE]],Table2[[#All],[Item Code]:[Unit Cost]],10,0),0) -> 0 | R905: =Table49[[#This Row],[QUANTITY]]*Table49[[#This Row],[INV Prices]] -> 0 | W905: =IFERROR(VLOOKUP(Table49[[#This Row],[ITEM CODE]],Table2[[Item Code]:[Category ]],6,0),"") | X905: =IFERROR(VLOOKUP(Table49[[#This Row],[ITEM CODE]],Table2[[Item Code]:[Sub Category]],7,0),"") | Y905: =Table49[[#This Row],[PO Number]]&COUNTIFS($E$5:E905,E905) -> 0
A906: =IF(Table49[[#This Row],[ITEM NAME]]="","",ROW()-4) | C906: =IFERROR(VLOOKUP(B906,Table14[],3,0),"") | D906: =IFERROR(VLOOKUP(B906,Table14[],2,0),"") | H906: =IFERROR(VLOOKUP(Table49[[#This Row],[ITEM CODE]],Table2[[Item Code]:[Master Name]],2,0),"") | J906: =IFERROR(VLOOKUP(Table49[[#This Row],[ITEM CODE]],Table2[[Item Code]:[Master Name]],3,0),"") | K906: =IFERROR(VLOOKUP(Table49[[#This Row],[ITEM CODE]],Table2[[Item Code]:[Master Name]],9,0),"") | L906: =IFERROR(VLOOKUP(Table49[[#This Row],[ITEM CODE]],Table2[[Item Code]:[Master Name]],8,0),"") | N906: =IFERROR(VLOOKUP(Table49[[#This Row],[ITEM CODE]],Table2[[#All],[Item Code]:[Unit Cost]],10,0),0) -> 0 | O906: =IFERROR(VLOOKUP(Table49[[#This Row],[ITEM CODE]],Table2[[#All],[Item Code]:[Unit Cost]],10,0),0) -> 0 | R906: =Table49[[#This Row],[QUANTITY]]*Table49[[#This Row],[INV Prices]] -> 0 | W906: =IFERROR(VLOOKUP(Table49[[#This Row],[ITEM CODE]],Table2[[Item Code]:[Category ]],6,0),"") | X906: =IFERROR(VLOOKUP(Table49[[#This Row],[ITEM CODE]],Table2[[Item Code]:[Sub Category]],7,0),"") | Y906: =Table49[[#This Row],[PO Number]]&COUNTIFS($E$5:E906,E906) -> 0
A907: =IF(Table49[[#This Row],[ITEM NAME]]="","",ROW()-4) | C907: =IFERROR(VLOOKUP(B907,Table14[],3,0),"") | D907: =IFERROR(VLOOKUP(B907,Table14[],2,0),"") | H907: =IFERROR(VLOOKUP(Table49[[#This Row],[ITEM CODE]],Table2[[Item Code]:[Master Name]],2,0),"") | J907: =IFERROR(VLOOKUP(Table49[[#This Row],[ITEM CODE]],Table2[[Item Code]:[Master Name]],3,0),"") | K907: =IFERROR(VLOOKUP(Table49[[#This Row],[ITEM CODE]],Table2[[Item Code]:[Master Name]],9,0),"") | L907: =IFERROR(VLOOKUP(Table49[[#This Row],[ITEM CODE]],Table2[[Item Code]:[Master Name]],8,0),"") | N907: =IFERROR(VLOOKUP(Table49[[#This Row],[ITEM CODE]],Table2[[#All],[Item Code]:[Unit Cost]],10,0),0) -> 0 | O907: =IFERROR(VLOOKUP(Table49[[#This Row],[ITEM CODE]],Table2[[#All],[Item Code]:[Unit Cost]],10,0),0) -> 0 | R907: =Table49[[#This Row],[QUANTITY]]*Table49[[#This Row],[INV Prices]] -> 0 | W907: =IFERROR(VLOOKUP(Table49[[#This Row],[ITEM CODE]],Table2[[Item Code]:[Category ]],6,0),"") | X907: =IFERROR(VLOOKUP(Table49[[#This Row],[ITEM CODE]],Table2[[Item Code]:[Sub Category]],7,0),"") | Y907: =Table49[[#This Row],[PO Number]]&COUNTIFS($E$5:E907,E907) -> 0
A908: =IF(Table49[[#This Row],[ITEM NAME]]="","",ROW()-4) | C908: =IFERROR(VLOOKUP(B908,Table14[],3,0),"") | D908: =IFERROR(VLOOKUP(B908,Table14[],2,0),"") | H908: =IFERROR(VLOOKUP(Table49[[#This Row],[ITEM CODE]],Table2[[Item Code]:[Master Name]],2,0),"") | J908: =IFERROR(VLOOKUP(Table49[[#This Row],[ITEM CODE]],Table2[[Item Code]:[Master Name]],3,0),"") | K908: =IFERROR(VLOOKUP(Table49[[#This Row],[ITEM CODE]],Table2[[Item Code]:[Master Name]],9,0),"") | L908: =IFERROR(VLOOKUP(Table49[[#This Row],[ITEM CODE]],Table2[[Item Code]:[Master Name]],8,0),"") | N908: =IFERROR(VLOOKUP(Table49[[#This Row],[ITEM CODE]],Table2[[#All],[Item Code]:[Unit Cost]],10,0),0) -> 0 | O908: =IFERROR(VLOOKUP(Table49[[#This Row],[ITEM CODE]],Table2[[#All],[Item Code]:[Unit Cost]],10,0),0) -> 0 | R908: =Table49[[#This Row],[QUANTITY]]*Table49[[#This Row],[INV Prices]] -> 0 | W908: =IFERROR(VLOOKUP(Table49[[#This Row],[ITEM CODE]],Table2[[Item Code]:[Category ]],6,0),"") | X908: =IFERROR(VLOOKUP(Table49[[#This Row],[ITEM CODE]],Table2[[Item Code]:[Sub Category]],7,0),"") | Y908: =Table49[[#This Row],[PO Number]]&COUNTIFS($E$5:E908,E908) -> 0
A909: =IF(Table49[[#This Row],[ITEM NAME]]="","",ROW()-4) | C909: =IFERROR(VLOOKUP(B909,Table14[],3,0),"") | D909: =IFERROR(VLOOKUP(B909,Table14[],2,0),"") | H909: =IFERROR(VLOOKUP(Table49[[#This Row],[ITEM CODE]],Table2[[Item Code]:[Master Name]],2,0),"") | J909: =IFERROR(VLOOKUP(Table49[[#This Row],[ITEM CODE]],Table2[[Item Code]:[Master Name]],3,0),"") | K909: =IFERROR(VLOOKUP(Table49[[#This Row],[ITEM CODE]],Table2[[Item Code]:[Master Name]],9,0),"") | L909: =IFERROR(VLOOKUP(Table49[[#This Row],[ITEM CODE]],Table2[[Item Code]:[Master Name]],8,0),"") | N909: =IFERROR(VLOOKUP(Table49[[#This Row],[ITEM CODE]],Table2[[#All],[Item Code]:[Unit Cost]],10,0),0) -> 0 | O909: =IFERROR(VLOOKUP(Table49[[#This Row],[ITEM CODE]],Table2[[#All],[Item Code]:[Unit Cost]],10,0),0) -> 0 | R909: =Table49[[#This Row],[QUANTITY]]*Table49[[#This Row],[INV Prices]] -> 0 | W909: =IFERROR(VLOOKUP(Table49[[#This Row],[ITEM CODE]],Table2[[Item Code]:[Category ]],6,0),"") | X909: =IFERROR(VLOOKUP(Table49[[#This Row],[ITEM CODE]],Table2[[Item Code]:[Sub Category]],7,0),"") | Y909: =Table49[[#This Row],[PO Number]]&COUNTIFS($E$5:E909,E909) -> 0
A910: =IF(Table49[[#This Row],[ITEM NAME]]="","",ROW()-4) | C910: =IFERROR(VLOOKUP(B910,Table14[],3,0),"") | D910: =IFERROR(VLOOKUP(B910,Table14[],2,0),"") | H910: =IFERROR(VLOOKUP(Table49[[#This Row],[ITEM CODE]],Table2[[Item Code]:[Master Name]],2,0),"") | J910: =IFERROR(VLOOKUP(Table49[[#This Row],[ITEM CODE]],Table2[[Item Code]:[Master Name]],3,0),"") | K910: =IFERROR(VLOOKUP(Table49[[#This Row],[ITEM CODE]],Table2[[Item Code]:[Master Name]],9,0),"") | L910: =IFERROR(VLOOKUP(Table49[[#This Row],[ITEM CODE]],Table2[[Item Code]:[Master Name]],8,0),"") | N910: =IFERROR(VLOOKUP(Table49[[#This Row],[ITEM CODE]],Table2[[#All],[Item Code]:[Unit Cost]],10,0),0) -> 0 | O910: =IFERROR(VLOOKUP(Table49[[#This Row],[ITEM CODE]],Table2[[#All],[Item Code]:[Unit Cost]],10,0),0) -> 0 | R910: =Table49[[#This Row],[QUANTITY]]*Table49[[#This Row],[INV Prices]] -> 0 | W910: =IFERROR(VLOOKUP(Table49[[#This Row],[ITEM CODE]],Table2[[Item Code]:[Category ]],6,0),"") | X910: =IFERROR(VLOOKUP(Table49[[#This Row],[ITEM CODE]],Table2[[Item Code]:[Sub Category]],7,0),"") | Y910: =Table49[[#This Row],[PO Number]]&COUNTIFS($E$5:E910,E910) -> 0
A911: =IF(Table49[[#This Row],[ITEM NAME]]="","",ROW()-4) | C911: =IFERROR(VLOOKUP(B911,Table14[],3,0),"") | D911: =IFERROR(VLOOKUP(B911,Table14[],2,0),"") | H911: =IFERROR(VLOOKUP(Table49[[#This Row],[ITEM CODE]],Table2[[Item Code]:[Master Name]],2,0),"") | J911: =IFERROR(VLOOKUP(Table49[[#This Row],[ITEM CODE]],Table2[[Item Code]:[Master Name]],3,0),"") | K911: =IFERROR(VLOOKUP(Table49[[#This Row],[ITEM CODE]],Table2[[Item Code]:[Master Name]],9,0),"") | L911: =IFERROR(VLOOKUP(Table49[[#This Row],[ITEM CODE]],Table2[[Item Code]:[Master Name]],8,0),"") | N911: =IFERROR(VLOOKUP(Table49[[#This Row],[ITEM CODE]],Table2[[#All],[Item Code]:[Unit Cost]],10,0),0) -> 0 | O911: =IFERROR(VLOOKUP(Table49[[#This Row],[ITEM CODE]],Table2[[#All],[Item Code]:[Unit Cost]],10,0),0) -> 0 | R911: =Table49[[#This Row],[QUANTITY]]*Table49[[#This Row],[INV Prices]] -> 0 | W911: =IFERROR(VLOOKUP(Table49[[#This Row],[ITEM CODE]],Table2[[Item Code]:[Category ]],6,0),"") | X911: =IFERROR(VLOOKUP(Table49[[#This Row],[ITEM CODE]],Table2[[Item Code]:[Sub Category]],7,0),"") | Y911: =Table49[[#This Row],[PO Number]]&COUNTIFS($E$5:E911,E911) -> 0
A912: =IF(Table49[[#This Row],[ITEM NAME]]="","",ROW()-4) | C912: =IFERROR(VLOOKUP(B912,Table14[],3,0),"") | D912: =IFERROR(VLOOKUP(B912,Table14[],2,0),"") | H912: =IFERROR(VLOOKUP(Table49[[#This Row],[ITEM CODE]],Table2[[Item Code]:[Master Name]],2,0),"") | J912: =IFERROR(VLOOKUP(Table49[[#This Row],[ITEM CODE]],Table2[[Item Code]:[Master Name]],3,0),"") | K912: =IFERROR(VLOOKUP(Table49[[#This Row],[ITEM CODE]],Table2[[Item Code]:[Master Name]],9,0),"") | L912: =IFERROR(VLOOKUP(Table49[[#This Row],[ITEM CODE]],Table2[[Item Code]:[Master Name]],8,0),"") | N912: =IFERROR(VLOOKUP(Table49[[#This Row],[ITEM CODE]],Table2[[#All],[Item Code]:[Unit Cost]],10,0),0) -> 0 | O912: =IFERROR(VLOOKUP(Table49[[#This Row],[ITEM CODE]],Table2[[#All],[Item Code]:[Unit Cost]],10,0),0) -> 0 | R912: =Table49[[#This Row],[QUANTITY]]*Table49[[#This Row],[INV Prices]] -> 0 | W912: =IFERROR(VLOOKUP(Table49[[#This Row],[ITEM CODE]],Table2[[Item Code]:[Category ]],6,0),"") | X912: =IFERROR(VLOOKUP(Table49[[#This Row],[ITEM CODE]],Table2[[Item Code]:[Sub Category]],7,0),"") | Y912: =Table49[[#This Row],[PO Number]]&COUNTIFS($E$5:E912,E912) -> 0
A913: =IF(Table49[[#This Row],[ITEM NAME]]="","",ROW()-4) | C913: =IFERROR(VLOOKUP(B913,Table14[],3,0),"") | D913: =IFERROR(VLOOKUP(B913,Table14[],2,0),"") | H913: =IFERROR(VLOOKUP(Table49[[#This Row],[ITEM CODE]],Table2[[Item Code]:[Master Name]],2,0),"") | J913: =IFERROR(VLOOKUP(Table49[[#This Row],[ITEM CODE]],Table2[[Item Code]:[Master Name]],3,0),"") | K913: =IFERROR(VLOOKUP(Table49[[#This Row],[ITEM CODE]],Table2[[Item Code]:[Master Name]],9,0),"") | L913: =IFERROR(VLOOKUP(Table49[[#This Row],[ITEM CODE]],Table2[[Item Code]:[Master Name]],8,0),"") | N913: =IFERROR(VLOOKUP(Table49[[#This Row],[ITEM CODE]],Table2[[#All],[Item Code]:[Unit Cost]],10,0),0) -> 0 | O913: =IFERROR(VLOOKUP(Table49[[#This Row],[ITEM CODE]],Table2[[#All],[Item Code]:[Unit Cost]],10,0),0) -> 0 | R913: =Table49[[#This Row],[QUANTITY]]*Table49[[#This Row],[INV Prices]] -> 0 | W913: =IFERROR(VLOOKUP(Table49[[#This Row],[ITEM CODE]],Table2[[Item Code]:[Category ]],6,0),"") | X913: =IFERROR(VLOOKUP(Table49[[#This Row],[ITEM CODE]],Table2[[Item Code]:[Sub Category]],7,0),"") | Y913: =Table49[[#This Row],[PO Number]]&COUNTIFS($E$5:E913,E913) -> 0
A914: =IF(Table49[[#This Row],[ITEM NAME]]="","",ROW()-4) | C914: =IFERROR(VLOOKUP(B914,Table14[],3,0),"") | D914: =IFERROR(VLOOKUP(B914,Table14[],2,0),"") | H914: =IFERROR(VLOOKUP(Table49[[#This Row],[ITEM CODE]],Table2[[Item Code]:[Master Name]],2,0),"") | J914: =IFERROR(VLOOKUP(Table49[[#This Row],[ITEM CODE]],Table2[[Item Code]:[Master Name]],3,0),"") | K914: =IFERROR(VLOOKUP(Table49[[#This Row],[ITEM CODE]],Table2[[Item Code]:[Master Name]],9,0),"") | L914: =IFERROR(VLOOKUP(Table49[[#This Row],[ITEM CODE]],Table2[[Item Code]:[Master Name]],8,0),"") | N914: =IFERROR(VLOOKUP(Table49[[#This Row],[ITEM CODE]],Table2[[#All],[Item Code]:[Unit Cost]],10,0),0) -> 0 | O914: =IFERROR(VLOOKUP(Table49[[#This Row],[ITEM CODE]],Table2[[#All],[Item Code]:[Unit Cost]],10,0),0) -> 0 | R914: =Table49[[#This Row],[QUANTITY]]*Table49[[#This Row],[INV Prices]] -> 0 | W914: =IFERROR(VLOOKUP(Table49[[#This Row],[ITEM CODE]],Table2[[Item Code]:[Category ]],6,0),"") | X914: =IFERROR(VLOOKUP(Table49[[#This Row],[ITEM CODE]],Table2[[Item Code]:[Sub Category]],7,0),"") | Y914: =Table49[[#This Row],[PO Number]]&COUNTIFS($E$5:E914,E914) -> 0
A915: =IF(Table49[[#This Row],[ITEM NAME]]="","",ROW()-4) | C915: =IFERROR(VLOOKUP(B915,Table14[],3,0),"") | D915: =IFERROR(VLOOKUP(B915,Table14[],2,0),"") | H915: =IFERROR(VLOOKUP(Table49[[#This Row],[ITEM CODE]],Table2[[Item Code]:[Master Name]],2,0),"") | J915: =IFERROR(VLOOKUP(Table49[[#This Row],[ITEM CODE]],Table2[[Item Code]:[Master Name]],3,0),"") | K915: =IFERROR(VLOOKUP(Table49[[#This Row],[ITEM CODE]],Table2[[Item Code]:[Master Name]],9,0),"") | L915: =IFERROR(VLOOKUP(Table49[[#This Row],[ITEM CODE]],Table2[[Item Code]:[Master Name]],8,0),"") | N915: =IFERROR(VLOOKUP(Table49[[#This Row],[ITEM CODE]],Table2[[#All],[Item Code]:[Unit Cost]],10,0),0) -> 0 | O915: =IFERROR(VLOOKUP(Table49[[#This Row],[ITEM CODE]],Table2[[#All],[Item Code]:[Unit Cost]],10,0),0) -> 0 | R915: =Table49[[#This Row],[QUANTITY]]*Table49[[#This Row],[INV Prices]] -> 0 | W915: =IFERROR(VLOOKUP(Table49[[#This Row],[ITEM CODE]],Table2[[Item Code]:[Category ]],6,0),"") | X915: =IFERROR(VLOOKUP(Table49[[#This Row],[ITEM CODE]],Table2[[Item Code]:[Sub Category]],7,0),"") | Y915: =Table49[[#This Row],[PO Number]]&COUNTIFS($E$5:E915,E915) -> 0
... A5711: =IF(Table49[[#This Row],[ITEM NAME]]="","",ROW()-4) | C5711: =IFERROR(VLOOKUP(B5711,Table14[],3,0),"") | D5711: =IFERROR(VLOOKUP(B5711,Table14[],2,0),"") | H5711: =IFERROR(VLOOKUP(Table49[[#This Row],[ITEM CODE]],Table2[[Item Code]:[Master Name]],2,0),"") | J5711: =IFERROR(VLOOKUP(Table49[[#This Row],[ITEM CODE]],Table2[[Item Code]:[Master Name]],3,0),"") | K5711: =IFERROR(VLOOKUP(Table49[[#This Row],[ITEM CODE]],Table2[[Item Code]:[Master Name]],9,0),"") | L5711: =IFERROR(VLOOKUP(Table49[[#This Row],[ITEM CODE]],Table2[[Item Code]:[Master Name]],8,0),"") | N5711: =IFERROR(VLOOKUP(Table49[[#This Row],[ITEM CODE]],Table2[[#All],[Item Code]:[Unit Cost]],10,0),0) -> 0 | O5711: =IFERROR(VLOOKUP(Table49[[#This Row],[ITEM CODE]],Table2[[#All],[Item Code]:[Unit Cost]],10,0),0) -> 0 | R5711: =Table49[[#This Row],[QUANTITY]]*Table49[[#This Row],[INV Prices]] -> 0 | W5711: =IFERROR(VLOOKUP(Table49[[#This Row],[ITEM CODE]],Table2[[Item Code]:[Category ]],6,0),"") | X5711: =IFERROR(VLOOKUP(Table49[[#This Row],[ITEM CODE]],Table2[[Item Code]:[Sub Category]],7,0),"") | Y5711: =Table49[[#This Row],[PO Number]]&COUNTIFS($E$5:E5711,E5711) -> 0
A5712: =IF(Table49[[#This Row],[ITEM NAME]]="","",ROW()-4) -> 5708 | C5712: =IFERROR(VLOOKUP(B5712,Table14[],3,0),"") | D5712: =IFERROR(VLOOKUP(B5712,Table14[],2,0),"") | E5712: NA01 | F5712: 03.09.25 | G5712: E-MART24 CAMKO | H5712: =IFERROR(VLOOKUP(Table49[[#This Row],[ITEM CODE]],Table2[[Item Code]:[Master Name]],2,0),"") -> 0 | I5712: I-0340 | J5712: =IFERROR(VLOOKUP(Table49[[#This Row],[ITEM CODE]],Table2[[Item Code]:[Master Name]],3,0),"") -> Cooking Oil 25LTR (ប្រេងឆា) | K5712: =IFERROR(VLOOKUP(Table49[[#This Row],[ITEM CODE]],Table2[[Item Code]:[Master Name]],9,0),"") -> 1GALLON*25LTR | L5712: =IFERROR(VLOOKUP(Table49[[#This Row],[ITEM CODE]],Table2[[Item Code]:[Master Name]],8,0),"") -> GALLON | M5712: 5 | N5712: =IFERROR(VLOOKUP(Table49[[#This Row],[ITEM CODE]],Table2[[#All],[Item Code]:[Unit Cost]],10,0),0) -> 50 | O5712: =IFERROR(VLOOKUP(Table49[[#This Row],[ITEM CODE]],Table2[[#All],[Item Code]:[Unit Cost]],10,0),0) -> 50 | R5712: =Table49[[#This Row],[QUANTITY]]*Table49[[#This Row],[INV Prices]] -> 250 | W5712: =IFERROR(VLOOKUP(Table49[[#This Row],[ITEM CODE]],Table2[[Item Code]:[Category ]],6,0),"") -> FOOD | X5712: =IFERROR(VLOOKUP(Table49[[#This Row],[ITEM CODE]],Table2[[Item Code]:[Sub Category]],7,0),"") -> Ingredients | Y5712: =Table49[[#This Row],[PO Number]]&COUNTIFS($E$5:E5712,E5712) -> NA011
A5713: =IF(Table49[[#This Row],[ITEM NAME]]="","",ROW()-4) -> 5709 | C5713: =IFERROR(VLOOKUP(B5713,Table14[],3,0),"") | D5713: =IFERROR(VLOOKUP(B5713,Table14[],2,0),"") | E5713: NA02 | F5713: 03.09.25 | G5713: E-MART24 BKK1 | H5713: =IFERROR(VLOOKUP(Table49[[#This Row],[ITEM CODE]],Table2[[Item Code]:[Master Name]],2,0),"") -> 43A52003 | I5713: P-0075 | J5713: =IFERROR(VLOOKUP(Table49[[#This Row],[ITEM CODE]],Table2[[Item Code]:[Master Name]],3,0),"") -> Set Plastic Spoon & Fork (ឈុតស្លាបព្រា សម) | K5713: =IFERROR(VLOOKUP(Table49[[#This Row],[ITEM CODE]],Table2[[Item Code]:[Master Name]],9,0),"") -> 1CTN*16PKT*50PCS | L5713: =IFERROR(VLOOKUP(Table49[[#This Row],[ITEM CODE]],Table2[[Item Code]:[Master Name]],8,0),"") -> PCS | M5713: 1600 | N5713: =IFERROR(VLOOKUP(Table49[[#This Row],[ITEM CODE]],Table2[[#All],[Item Code]:[Unit Cost]],10,0),0) -> 0.0675 | O5713: =IFERROR(VLOOKUP(Table49[[#This Row],[ITEM CODE]],Table2[[#All],[Item Code]:[Unit Cost]],10,0),0) -> 0.0675 | R5713: =Table49[[#This Row],[QUANTITY]]*Table49[[#This Row],[INV Prices]] -> 108 | W5713: =IFERROR(VLOOKUP(Table49[[#This Row],[ITEM CODE]],Table2[[Item Code]:[Category ]],6,0),"") -> NON-FOOD | X5713: =IFERROR(VLOOKUP(Table49[[#This Row],[ITEM CODE]],Table2[[Item Code]:[Sub Category]],7,0),"") -> NON-FOOD | Y5713: =Table49[[#This Row],[PO Number]]&COUNTIFS($E$5:E5713,E5713) -> NA021
A5714: =IF(Table49[[#This Row],[ITEM NAME]]="","",ROW()-4) | C5714: =IFERROR(VLOOKUP(B5714,Table14[],3,0),"") | D5714: =IFERROR(VLOOKUP(B5714,Table14[],2,0),"") | H5714: =IFERROR(VLOOKUP(Table49[[#This Row],[ITEM CODE]],Table2[[Item Code]:[Master Name]],2,0),"") | J5714: =IFERROR(VLOOKUP(Table49[[#This Row],[ITEM CODE]],Table2[[Item Code]:[Master Name]],3,0),"") | K5714: =IFERROR(VLOOKUP(Table49[[#This Row],[ITEM CODE]],Table2[[Item Code]:[Master Name]],9,0),"") | L5714: =IFERROR(VLOOKUP(Table49[[#This Row],[ITEM CODE]],Table2[[Item Code]:[Master Name]],8,0),"") | N5714: =IFERROR(VLOOKUP(Table49[[#This Row],[ITEM CODE]],Table2[[#All],[Item Code]:[Unit Cost]],10,0),0) -> 0 | O5714: =IFERROR(VLOOKUP(Table49[[#This Row],[ITEM CODE]],Table2[[#All],[Item Code]:[Unit Cost]],10,0),0) -> 0 | R5714: =Table49[[#This Row],[QUANTITY]]*Table49[[#This Row],[INV Prices]] -> 0 | W5714: =IFERROR(VLOOKUP(Table49[[#This Row],[ITEM CODE]],Table2[[Item Code]:[Category ]],6,0),"") | X5714: =IFERROR(VLOOKUP(Table49[[#This Row],[ITEM CODE]],Table2[[Item Code]:[Sub Category]],7,0),"") | Y5714: =Table49[[#This Row],[PO Number]]&COUNTIFS($E$5:E5714,E5714) -> 0
A5715: =IF(Table49[[#This Row],[ITEM NAME]]="","",ROW()-4) | C5715: =IFERROR(VLOOKUP(B5715,Table14[],3,0),"") | D5715: =IFERROR(VLOOKUP(B5715,Table14[],2,0),"") | H5715: =IFERROR(VLOOKUP(Table49[[#This Row],[ITEM CODE]],Table2[[Item Code]:[Master Name]],2,0),"") | J5715: =IFERROR(VLOOKUP(Table49[[#This Row],[ITEM CODE]],Table2[[Item Code]:[Master Name]],3,0),"") | K5715: =IFERROR(VLOOKUP(Table49[[#This Row],[ITEM CODE]],Table2[[Item Code]:[Master Name]],9,0),"") | L5715: =IFERROR(VLOOKUP(Table49[[#This Row],[ITEM CODE]],Table2[[Item Code]:[Master Name]],8,0),"") | N5715: =IFERROR(VLOOKUP(Table49[[#This Row],[ITEM CODE]],Table2[[#All],[Item Code]:[Unit Cost]],10,0),0) -> 0 | O5715: =IFERROR(VLOOKUP(Table49[[#This Row],[ITEM CODE]],Table2[[#All],[Item Code]:[Unit Cost]],10,0),0) -> 0 | R5715: =Table49[[#This Row],[QUANTITY]]*Table49[[#This Row],[INV Prices]] -> 0 | W5715: =IFERROR(VLOOKUP(Table49[[#This Row],[ITEM CODE]],Table2[[Item Code]:[Category ]],6,0),"") | X5715: =IFERROR(VLOOKUP(Table49[[#This Row],[ITEM CODE]],Table2[[Item Code]:[Sub Category]],7,0),"") | Y5715: =Table49[[#This Row],[PO Number]]&COUNTIFS($E$5:E5715,E5715) -> 0
A5716: =IF(Table49[[#This Row],[ITEM NAME]]="","",ROW()-4) | C5716: =IFERROR(VLOOKUP(B5716,Table14[],3,0),"") | D5716: =IFERROR(VLOOKUP(B5716,Table14[],2,0),"") | H5716: =IFERROR(VLOOKUP(Table49[[#This Row],[ITEM CODE]],Table2[[Item Code]:[Master Name]],2,0),"") | J5716: =IFERROR(VLOOKUP(Table49[[#This Row],[ITEM CODE]],Table2[[Item Code]:[Master Name]],3,0),"") | K5716: =IFERROR(VLOOKUP(Table49[[#This Row],[ITEM CODE]],Table2[[Item Code]:[Master Name]],9,0),"") | L5716: =IFERROR(VLOOKUP(Table49[[#This Row],[ITEM CODE]],Table2[[Item Code]:[Master Name]],8,0),"") | N5716: =IFERROR(VLOOKUP(Table49[[#This Row],[ITEM CODE]],Table2[[#All],[Item Code]:[Unit Cost]],10,0),0) -> 0 | O5716: =IFERROR(VLOOKUP(Table49[[#This Row],[ITEM CODE]],Table2[[#All],[Item Code]:[Unit Cost]],10,0),0) -> 0 | R5716: =Table49[[#This Row],[QUANTITY]]*Table49[[#This Row],[INV Prices]] -> 0 | W5716: =IFERROR(VLOOKUP(Table49[[#This Row],[ITEM CODE]],Table2[[Item Code]:[Category ]],6,0),"") | X5716: =IFERROR(VLOOKUP(Table49[[#This Row],[ITEM CODE]],Table2[[Item Code]:[Sub Category]],7,0),"") | Y5716: =Table49[[#This Row],[PO Number]]&COUNTIFS($E$5:E5716,E5716) -> 0
A5717: =IF(Table49[[#This Row],[ITEM NAME]]="","",ROW()-4) | C5717: =IFERROR(VLOOKUP(B5717,Table14[],3,0),"") | D5717: =IFERROR(VLOOKUP(B5717,Table14[],2,0),"") | H5717: =IFERROR(VLOOKUP(Table49[[#This Row],[ITEM CODE]],Table2[[Item Code]:[Master Name]],2,0),"") | J5717: =IFERROR(VLOOKUP(Table49[[#This Row],[ITEM CODE]],Table2[[Item Code]:[Master Name]],3,0),"") | K5717: =IFERROR(VLOOKUP(Table49[[#This Row],[ITEM CODE]],Table2[[Item Code]:[Master Name]],9,0),"") | L5717: =IFERROR(VLOOKUP(Table49[[#This Row],[ITEM CODE]],Table2[[Item Code]:[Master Name]],8,0),"") | N5717: =IFERROR(VLOOKUP(Table49[[#This Row],[ITEM CODE]],Table2[[#All],[Item Code]:[Unit Cost]],10,0),0) -> 0 | O5717: =IFERROR(VLOOKUP(Table49[[#This Row],[ITEM CODE]],Table2[[#All],[Item Code]:[Unit Cost]],10,0),0) -> 0 | R5717: =Table49[[#This Row],[QUANTITY]]*Table49[[#This Row],[INV Prices]] -> 0 | W5717: =IFERROR(VLOOKUP(Table49[[#This Row],[ITEM CODE]],Table2[[Item Code]:[Category ]],6,0),"") | X5717: =IFERROR(VLOOKUP(Table49[[#This Row],[ITEM CODE]],Table2[[Item Code]:[Sub Category]],7,0),"") | Y5717: =Table49[[#This Row],[PO Number]]&COUNTIFS($E$5:E5717,E5717) -> 0
A5718: =IF(Table49[[#This Row],[ITEM NAME]]="","",ROW()-4) | C5718: =IFERROR(VLOOKUP(B5718,Table14[],3,0),"") | D5718: =IFERROR(VLOOKUP(B5718,Table14[],2,0),"") | H5718: =IFERROR(VLOOKUP(Table49[[#This Row],[ITEM CODE]],Table2[[Item Code]:[Master Name]],2,0),"") | J5718: =IFERROR(VLOOKUP(Table49[[#This Row],[ITEM CODE]],Table2[[Item Code]:[Master Name]],3,0),"") | K5718: =IFERROR(VLOOKUP(Table49[[#This Row],[ITEM CODE]],Table2[[Item Code]:[Master Name]],9,0),"") | L5718: =IFERROR(VLOOKUP(Table49[[#This Row],[ITEM CODE]],Table2[[Item Code]:[Master Name]],8,0),"") | N5718: =IFERROR(VLOOKUP(Table49[[#This Row],[ITEM CODE]],Table2[[#All],[Item Code]:[Unit Cost]],10,0),0) -> 0 | O5718: =IFERROR(VLOOKUP(Table49[[#This Row],[ITEM CODE]],Table2[[#All],[Item Code]:[Unit Cost]],10,0),0) -> 0 | R5718: =Table49[[#This Row],[QUANTITY]]*Table49[[#This Row],[INV Prices]] -> 0 | W5718: =IFERROR(VLOOKUP(Table49[[#This Row],[ITEM CODE]],Table2[[Item Code]:[Category ]],6,0),"") | X5718: =IFERROR(VLOOKUP(Table49[[#This Row],[ITEM CODE]],Table2[[Item Code]:[Sub Category]],7,0),"") | Y5718: =Table49[[#This Row],[PO Number]]&COUNTIFS($E$5:E5718,E5718) -> 0
A5719: =IF(Table49[[#This Row],[ITEM NAME]]="","",ROW()-4) | C5719: =IFERROR(VLOOKUP(B5719,Table14[],3,0),"") | D5719: =IFERROR(VLOOKUP(B5719,Table14[],2,0),"") | H5719: =IFERROR(VLOOKUP(Table49[[#This Row],[ITEM CODE]],Table2[[Item Code]:[Master Name]],2,0),"") | J5719: =IFERROR(VLOOKUP(Table49[[#This Row],[ITEM CODE]],Table2[[Item Code]:[Master Name]],3,0),"") | K5719: =IFERROR(VLOOKUP(Table49[[#This Row],[ITEM CODE]],Table2[[Item Code]:[Master Name]],9,0),"") | L5719: =IFERROR(VLOOKUP(Table49[[#This Row],[ITEM CODE]],Table2[[Item Code]:[Master Name]],8,0),"") | N5719: =IFERROR(VLOOKUP(Table49[[#This Row],[ITEM CODE]],Table2[[#All],[Item Code]:[Unit Cost]],10,0),0) -> 0 | O5719: =IFERROR(VLOOKUP(Table49[[#This Row],[ITEM CODE]],Table2[[#All],[Item Code]:[Unit Cost]],10,0),0) -> 0 | R5719: =Table49[[#This Row],[QUANTITY]]*Table49[[#This Row],[INV Prices]] -> 0 | W5719: =IFERROR(VLOOKUP(Table49[[#This Row],[ITEM CODE]],Table2[[Item Code]:[Category ]],6,0),"") | X5719: =IFERROR(VLOOKUP(Table49[[#This Row],[ITEM CODE]],Table2[[Item Code]:[Sub Category]],7,0),"") | Y5719: =Table49[[#This Row],[PO Number]]&COUNTIFS($E$5:E5719,E5719) -> 0
A5720: =IF(Table49[[#This Row],[ITEM NAME]]="","",ROW()-4) | C5720: =IFERROR(VLOOKUP(B5720,Table14[],3,0),"") | D5720: =IFERROR(VLOOKUP(B5720,Table14[],2,0),"") | H5720: =IFERROR(VLOOKUP(Table49[[#This Row],[ITEM CODE]],Table2[[Item Code]:[Master Name]],2,0),"") | J5720: =IFERROR(VLOOKUP(Table49[[#This Row],[ITEM CODE]],Table2[[Item Code]:[Master Name]],3,0),"") | K5720: =IFERROR(VLOOKUP(Table49[[#This Row],[ITEM CODE]],Table2[[Item Code]:[Master Name]],9,0),"") | L5720: =IFERROR(VLOOKUP(Table49[[#This Row],[ITEM CODE]],Table2[[Item Code]:[Master Name]],8,0),"") | N5720: =IFERROR(VLOOKUP(Table49[[#This Row],[ITEM CODE]],Table2[[#All],[Item Code]:[Unit Cost]],10,0),0) -> 0 | O5720: =IFERROR(VLOOKUP(Table49[[#This Row],[ITEM CODE]],Table2[[#All],[Item Code]:[Unit Cost]],10,0),0) -> 0 | R5720: =Table49[[#This Row],[QUANTITY]]*Table49[[#This Row],[INV Prices]] -> 0 | W5720: =IFERROR(VLOOKUP(Table49[[#This Row],[ITEM CODE]],Table2[[Item Code]:[Category ]],6,0),"") | X5720: =IFERROR(VLOOKUP(Table49[[#This Row],[ITEM CODE]],Table2[[Item Code]:[Sub Category]],7,0),"") | Y5720: =Table49[[#This Row],[PO Number]]&COUNTIFS($E$5:E5720,E5720) -> 0
A5721: =IF(Table49[[#This Row],[ITEM NAME]]="","",ROW()-4) | C5721: =IFERROR(VLOOKUP(B5721,Table14[],3,0),"") | D5721: =IFERROR(VLOOKUP(B5721,Table14[],2,0),"") | H5721: =IFERROR(VLOOKUP(Table49[[#This Row],[ITEM CODE]],Table2[[Item Code]:[Master Name]],2,0),"") | J5721: =IFERROR(VLOOKUP(Table49[[#This Row],[ITEM CODE]],Table2[[Item Code]:[Master Name]],3,0),"") | K5721: =IFERROR(VLOOKUP(Table49[[#This Row],[ITEM CODE]],Table2[[Item Code]:[Master Name]],9,0),"") | L5721: =IFERROR(VLOOKUP(Table49[[#This Row],[ITEM CODE]],Table2[[Item Code]:[Master Name]],8,0),"") | N5721: =IFERROR(VLOOKUP(Table49[[#This Row],[ITEM CODE]],Table2[[#All],[Item Code]:[Unit Cost]],10,0),0) -> 0 | O5721: =IFERROR(VLOOKUP(Table49[[#This Row],[ITEM CODE]],Table2[[#All],[Item Code]:[Unit Cost]],10,0),0) -> 0 | R5721: =Table49[[#This Row],[QUANTITY]]*Table49[[#This Row],[INV Prices]] -> 0 | W5721: =IFERROR(VLOOKUP(Table49[[#This Row],[ITEM CODE]],Table2[[Item Code]:[Category ]],6,0),"") | X5721: =IFERROR(VLOOKUP(Table49[[#This Row],[ITEM CODE]],Table2[[Item Code]:[Sub Category]],7,0),"") | Y5721: =Table49[[#This Row],[PO Number]]&COUNTIFS($E$5:E5721,E5721) -> 0
A5722: =IF(Table49[[#This Row],[ITEM NAME]]="","",ROW()-4) | C5722: =IFERROR(VLOOKUP(B5722,Table14[],3,0),"") | D5722: =IFERROR(VLOOKUP(B5722,Table14[],2,0),"") | H5722: =IFERROR(VLOOKUP(Table49[[#This Row],[ITEM CODE]],Table2[[Item Code]:[Master Name]],2,0),"") | J5722: =IFERROR(VLOOKUP(Table49[[#This Row],[ITEM CODE]],Table2[[Item Code]:[Master Name]],3,0),"") | K5722: =IFERROR(VLOOKUP(Table49[[#This Row],[ITEM CODE]],Table2[[Item Code]:[Master Name]],9,0),"") | L5722: =IFERROR(VLOOKUP(Table49[[#This Row],[ITEM CODE]],Table2[[Item Code]:[Master Name]],8,0),"") | N5722: =IFERROR(VLOOKUP(Table49[[#This Row],[ITEM CODE]],Table2[[#All],[Item Code]:[Unit Cost]],10,0),0) -> 0 | O5722: =IFERROR(VLOOKUP(Table49[[#This Row],[ITEM CODE]],Table2[[#All],[Item Code]:[Unit Cost]],10,0),0) -> 0 | R5722: =Table49[[#This Row],[QUANTITY]]*Table49[[#This Row],[INV Prices]] -> 0 | W5722: =IFERROR(VLOOKUP(Table49[[#This Row],[ITEM CODE]],Table2[[Item Code]:[Category ]],6,0),"") | X5722: =IFERROR(VLOOKUP(Table49[[#This Row],[ITEM CODE]],Table2[[Item Code]:[Sub Category]],7,0),"") | Y5722: =Table49[[#This Row],[PO Number]]&COUNTIFS($E$5:E5722,E5722) -> 0
A5723: =IF(Table49[[#This Row],[ITEM NAME]]="","",ROW()-4) | C5723: =IFERROR(VLOOKUP(B5723,Table14[],3,0),"") | D5723: =IFERROR(VLOOKUP(B5723,Table14[],2,0),"") | H5723: =IFERROR(VLOOKUP(Table49[[#This Row],[ITEM CODE]],Table2[[Item Code]:[Master Name]],2,0),"") | J5723: =IFERROR(VLOOKUP(Table49[[#This Row],[ITEM CODE]],Table2[[Item Code]:[Master Name]],3,0),"") | K5723: =IFERROR(VLOOKUP(Table49[[#This Row],[ITEM CODE]],Table2[[Item Code]:[Master Name]],9,0),"") | L5723: =IFERROR(VLOOKUP(Table49[[#This Row],[ITEM CODE]],Table2[[Item Code]:[Master Name]],8,0),"") | N5723: =IFERROR(VLOOKUP(Table49[[#This Row],[ITEM CODE]],Table2[[#All],[Item Code]:[Unit Cost]],10,0),0) -> 0 | O5723: =IFERROR(VLOOKUP(Table49[[#This Row],[ITEM CODE]],Table2[[#All],[Item Code]:[Unit Cost]],10,0),0) -> 0 | R5723: =Table49[[#This Row],[QUANTITY]]*Table49[[#This Row],[INV Prices]] -> 0 | W5723: =IFERROR(VLOOKUP(Table49[[#This Row],[ITEM CODE]],Table2[[Item Code]:[Category ]],6,0),"") | X5723: =IFERROR(VLOOKUP(Table49[[#This Row],[ITEM CODE]],Table2[[Item Code]:[Sub Category]],7,0),"") | Y5723: =Table49[[#This Row],[PO Number]]&COUNTIFS($E$5:E5723,E5723) -> 0
A5724: =IF(Table49[[#This Row],[ITEM NAME]]="","",ROW()-4) | C5724: =IFERROR(VLOOKUP(B5724,Table14[],3,0),"") | D5724: =IFERROR(VLOOKUP(B5724,Table14[],2,0),"") | H5724: =IFERROR(VLOOKUP(Table49[[#This Row],[ITEM CODE]],Table2[[Item Code]:[Master Name]],2,0),"") | J5724: =IFERROR(VLOOKUP(Table49[[#This Row],[ITEM CODE]],Table2[[Item Code]:[Master Name]],3,0),"") | K5724: =IFERROR(VLOOKUP(Table49[[#This Row],[ITEM CODE]],Table2[[Item Code]:[Master Name]],9,0),"") | L5724: =IFERROR(VLOOKUP(Table49[[#This Row],[ITEM CODE]],Table2[[Item Code]:[Master Name]],8,0),"") | N5724: =IFERROR(VLOOKUP(Table49[[#This Row],[ITEM CODE]],Table2[[#All],[Item Code]:[Unit Cost]],10,0),0) -> 0 | O5724: =IFERROR(VLOOKUP(Table49[[#This Row],[ITEM CODE]],Table2[[#All],[Item Code]:[Unit Cost]],10,0),0) -> 0 | R5724: =Table49[[#This Row],[QUANTITY]]*Table49[[#This Row],[INV Prices]] -> 0 | W5724: =IFERROR(VLOOKUP(Table49[[#This Row],[ITEM CODE]],Table2[[Item Code]:[Category ]],6,0),"") | X5724: =IFERROR(VLOOKUP(Table49[[#This Row],[ITEM CODE]],Table2[[Item Code]:[Sub Category]],7,0),"") | Y5724: =Table49[[#This Row],[PO Number]]&COUNTIFS($E$5:E5724,E5724) -> 0
A5725: =IF(Table49[[#This Row],[ITEM NAME]]="","",ROW()-4) | C5725: =IFERROR(VLOOKUP(B5725,Table14[],3,0),"") | D5725: =IFERROR(VLOOKUP(B5725,Table14[],2,0),"") | H5725: =IFERROR(VLOOKUP(Table49[[#This Row],[ITEM CODE]],Table2[[Item Code]:[Master Name]],2,0),"") | J5725: =IFERROR(VLOOKUP(Table49[[#This Row],[ITEM CODE]],Table2[[Item Code]:[Master Name]],3,0),"") | K5725: =IFERROR(VLOOKUP(Table49[[#This Row],[ITEM CODE]],Table2[[Item Code]:[Master Name]],9,0),"") | L5725: =IFERROR(VLOOKUP(Table49[[#This Row],[ITEM CODE]],Table2[[Item Code]:[Master Name]],8,0),"") | N5725: =IFERROR(VLOOKUP(Table49[[#This Row],[ITEM CODE]],Table2[[#All],[Item Code]:[Unit Cost]],10,0),0) -> 0 | O5725: =IFERROR(VLOOKUP(Table49[[#This Row],[ITEM CODE]],Table2[[#All],[Item Code]:[Unit Cost]],10,0),0) -> 0 | R5725: =Table49[[#This Row],[QUANTITY]]*Table49[[#This Row],[INV Prices]] -> 0 | W5725: =IFERROR(VLOOKUP(Table49[[#This Row],[ITEM CODE]],Table2[[Item Code]:[Category ]],6,0),"") | X5725: =IFERROR(VLOOKUP(Table49[[#This Row],[ITEM CODE]],Table2[[Item Code]:[Sub Category]],7,0),"") | Y5725: =Table49[[#This Row],[PO Number]]&COUNTIFS($E$5:E5725,E5725) -> 0
... A5744: =IF(Table49[[#This Row],[ITEM NAME]]="","",ROW()-4) | C5744: =IFERROR(VLOOKUP(B5744,Table14[],3,0),"") | D5744: =IFERROR(VLOOKUP(B5744,Table14[],2,0),"") | H5744: =IFERROR(VLOOKUP(Table49[[#This Row],[ITEM CODE]],Table2[[Item Code]:[Master Name]],2,0),"") | J5744: =IFERROR(VLOOKUP(Table49[[#This Row],[ITEM CODE]],Table2[[Item Code]:[Master Name]],3,0),"") | K5744: =IFERROR(VLOOKUP(Table49[[#This Row],[ITEM CODE]],Table2[[Item Code]:[Master Name]],9,0),"") | L5744: =IFERROR(VLOOKUP(Table49[[#This Row],[ITEM CODE]],Table2[[Item Code]:[Master Name]],8,0),"") | N5744: =IFERROR(VLOOKUP(Table49[[#This Row],[ITEM CODE]],Table2[[#All],[Item Code]:[Unit Cost]],10,0),0) -> 0 | O5744: =IFERROR(VLOOKUP(Table49[[#This Row],[ITEM CODE]],Table2[[#All],[Item Code]:[Unit Cost]],10,0),0) -> 0 | R5744: =Table49[[#This Row],[QUANTITY]]*Table49[[#This Row],[INV Prices]] -> 0 | W5744: =IFERROR(VLOOKUP(Table49[[#This Row],[ITEM CODE]],Table2[[Item Code]:[Category ]],6,0),"") | X5744: =IFERROR(VLOOKUP(Table49[[#This Row],[ITEM CODE]],Table2[[Item Code]:[Sub Category]],7,0),"") | Y5744: =Table49[[#This Row],[PO Number]]&COUNTIFS($E$5:E5744,E5744) -> 0

Sheet Healthy Food
W1: Paid
W2: On Credit
G3: Search For | I3: Item Name | J3: Cambodia Jasmine Rice | K3: =IFERROR(INDEX(Table2[Item Code],MATCH('Healthy Food'!J3,Table2[[Item Name ]],0),0),"") -> O-0049 | P3: Invoice Value By Invoice | R3: =SUMIFS(Table4914[TOTAL PRICE (USD)],Table4914[Document Number],$Q$3) -> 0 | S3: TODAY | T3: Week 03
A4: Nº | B4: DATE | C4: Month | D4: Week Num2 | E4: PO Number | F4: Document Number | G4: Delivered From/To | H4: BARCODE | I4: ITEM CODE | J4: ITEM NAME | K4: PACKING SIZE | L4: PURCHASE Uom | M4: QUANTITY | N4: Master List Prices | O4: INV Prices | P4: PRICE (USD) | Q4: TOTAL PRICE (USD) | R4: LAST TOTAL PRICE (USD) | S4: EXPRIED DATE | T4: ALERT | U4: REMARK | V4: Transaction Type | W4: Category | X4: Sub Category | Y4: H1
A5: =IF(Table4914[[#This Row],[ITEM NAME]]="","",ROW()-4) -> 1 | B5: 45901 | C5: =IFERROR(VLOOKUP(B5,Table14[],3,0),"") -> 9 | D5: =IFERROR(VLOOKUP(B5,Table14[],2,0),"") -> Week 01 | G5: HEALTHY FOOD | H5: =IFERROR(VLOOKUP(Table4914[[#This Row],[ITEM CODE]],Table2[[Item Code]:[Master Name]],2,0),"") -> 0 | I5: REV-FOOD | J5: =IFERROR(VLOOKUP(Table4914[[#This Row],[ITEM CODE]],Table2[[Item Code]:[Master Name]],3,0),"") -> Revenue Food | K5: =IFERROR(VLOOKUP(Table4914[[#This Row],[ITEM CODE]],Table2[[Item Code]:[Master Name]],9,0),"") -> 0 | L5: =IFERROR(VLOOKUP(Table4914[[#This Row],[ITEM CODE]],Table2[[Item Code]:[Master Name]],8,0),"") -> 0 | M5: 1 | N5: =IFERROR(VLOOKUP(Table4914[[#This Row],[ITEM CODE]],Table2[[#All],[Item Code]:[Unit Cost]],10,0),0) -> 0 | O5: 173.38 | R5: =Table4914[[#This Row],[QUANTITY]]*Table4914[[#This Row],[INV Prices]] -> 173.38 | V5: Sold | W5: =IFERROR(VLOOKUP(Table4914[[#This Row],[ITEM CODE]],Table2[[Item Code]:[Category ]],6,0),"") -> FOOD | X5: =IFERROR(VLOOKUP(Table4914[[#This Row],[ITEM CODE]],Table2[[Item Code]:[Sub Category]],7,0),"") -> FOOD | Y5: =Table4914[[#This Row],[PO Number]]&COUNTIFS($E$5:E5,E5) -> 0
A6: =IF(Table4914[[#This Row],[ITEM NAME]]="","",ROW()-4) -> 2 | B6: 45901 | C6: =IFERROR(VLOOKUP(B6,Table14[],3,0),"") -> 9 | D6: =IFERROR(VLOOKUP(B6,Table14[],2,0),"") -> Week 01 | G6: HEALTHY FOOD | H6: =IFERROR(VLOOKUP(Table4914[[#This Row],[ITEM CODE]],Table2[[Item Code]:[Master Name]],2,0),"") -> 0 | I6: REV-NON ALCOHOL | J6: =IFERROR(VLOOKUP(Table4914[[#This Row],[ITEM CODE]],Table2[[Item Code]:[Master Name]],3,0),"") -> Revenue Non Alcohol | K6: =IFERROR(VLOOKUP(Table4914[[#This Row],[ITEM CODE]],Table2[[Item Code]:[Master Name]],9,0),"") -> 0 | L6: =IFERROR(VLOOKUP(Table4914[[#This Row],[ITEM CODE]],Table2[[Item Code]:[Master Name]],8,0),"") -> 0 | M6: 1 | N6: =IFERROR(VLOOKUP(Table4914[[#This Row],[ITEM CODE]],Table2[[#All],[Item Code]:[Unit Cost]],10,0),0) -> 0 | O6: 39.47 | R6: =Table4914[[#This Row],[QUANTITY]]*Table4914[[#This Row],[INV Prices]] -> 39.47 | V6: Sold | W6: =IFERROR(VLOOKUP(Table4914[[#This Row],[ITEM CODE]],Table2[[Item Code]:[Category ]],6,0),"") -> BEVERAGE NON-ALOCOHOL | X6: =IFERROR(VLOOKUP(Table4914[[#This Row],[ITEM CODE]],Table2[[Item Code]:[Sub Category]],7,0),"") -> BEVERAGE NON-ALOCOHOL | Y6: =Table4914[[#This Row],[PO Number]]&COUNTIFS($E$5:E66,E6) -> 0
A7: =IF(Table4914[[#This Row],[ITEM NAME]]="","",ROW()-4) -> 3 | B7: 45902 | C7: =IFERROR(VLOOKUP(B7,Table14[],3,0),"") -> 9 | D7: =IFERROR(VLOOKUP(B7,Table14[],2,0),"") -> Week 01 | G7: HEALTHY FOOD | H7: =IFERROR(VLOOKUP(Table4914[[#This Row],[ITEM CODE]],Table2[[Item Code]:[Master Name]],2,0),"") -> 0 | I7: REV-FOOD | J7: =IFERROR(VLOOKUP(Table4914[[#This Row],[ITEM CODE]],Table2[[Item Code]:[Master Name]],3,0),"") -> Revenue Food | K7: =IFERROR(VLOOKUP(Table4914[[#This Row],[ITEM CODE]],Table2[[Item Code]:[Master Name]],9,0),"") -> 0 | L7: =IFERROR(VLOOKUP(Table4914[[#This Row],[ITEM CODE]],Table2[[Item Code]:[Master Name]],8,0),"") -> 0 | M7: 1 | N7: =IFERROR(VLOOKUP(Table4914[[#This Row],[ITEM CODE]],Table2[[#All],[Item Code]:[Unit Cost]],10,0),0) -> 0 | O7: =89.35+25.4 -> 114.75 | R7: =Table4914[[#This Row],[QUANTITY]]*Table4914[[#This Row],[INV Prices]] -> 114.75 | V7: Sold | W7: =IFERROR(VLOOKUP(Table4914[[#This Row],[ITEM CODE]],Table2[[Item Code]:[Category ]],6,0),"") -> FOOD | X7: =IFERROR(VLOOKUP(Table4914[[#This Row],[ITEM CODE]],Table2[[Item Code]:[Sub Category]],7,0),"") -> FOOD | Y7: =Table4914[[#This Row],[PO Number]]&COUNTIFS($E$5:E66,E7) -> 0
A8: =IF(Table4914[[#This Row],[ITEM NAME]]="","",ROW()-4) -> 4 | B8: 45902 | C8: =IFERROR(VLOOKUP(B8,Table14[],3,0),"") -> 9 | D8: =IFERROR(VLOOKUP(B8,Table14[],2,0),"") -> Week 01 | G8: HEALTHY FOOD | H8: =IFERROR(VLOOKUP(Table4914[[#This Row],[ITEM CODE]],Table2[[Item Code]:[Master Name]],2,0),"") -> 0 | I8: REV-NON ALCOHOL | J8: =IFERROR(VLOOKUP(Table4914[[#This Row],[ITEM CODE]],Table2[[Item Code]:[Master Name]],3,0),"") -> Revenue Non Alcohol | K8: =IFERROR(VLOOKUP(Table4914[[#This Row],[ITEM CODE]],Table2[[Item Code]:[Master Name]],9,0),"") -> 0 | L8: =IFERROR(VLOOKUP(Table4914[[#This Row],[ITEM CODE]],Table2[[Item Code]:[Master Name]],8,0),"") -> 0 | M8: 1 | N8: =IFERROR(VLOOKUP(Table4914[[#This Row],[ITEM CODE]],Table2[[#All],[Item Code]:[Unit Cost]],10,0),0) -> 0 | O8: 42 | R8: =Table4914[[#This Row],[QUANTITY]]*Table4914[[#This Row],[INV Prices]] -> 42 | V8: Sold | W8: =IFERROR(VLOOKUP(Table4914[[#This Row],[ITEM CODE]],Table2[[Item Code]:[Category ]],6,0),"") -> BEVERAGE NON-ALOCOHOL | X8: =IFERROR(VLOOKUP(Table4914[[#This Row],[ITEM CODE]],Table2[[Item Code]:[Sub Category]],7,0),"") -> BEVERAGE NON-ALOCOHOL | Y8: =Table4914[[#This Row],[PO Number]]&COUNTIFS($E$5:E66,E8) -> 0
A9: =IF(Table4914[[#This Row],[ITEM NAME]]="","",ROW()-4) -> 5 | B9: 45903 | C9: =IFERROR(VLOOKUP(B9,Table14[],3,0),"") -> 9 | D9: =IFERROR(VLOOKUP(B9,Table14[],2,0),"") -> Week 01 | G9: HEALTHY FOOD | H9: =IFERROR(VLOOKUP(Table4914[[#This Row],[ITEM CODE]],Table2[[Item Code]:[Master Name]],2,0),"") -> 0 | I9: REV-FOOD | J9: =IFERROR(VLOOKUP(Table4914[[#This Row],[ITEM CODE]],Table2[[Item Code]:[Master Name]],3,0),"") -> Revenue Food | K9: =IFERROR(VLOOKUP(Table4914[[#This Row],[ITEM CODE]],Table2[[Item Code]:[Master Name]],9,0),"") -> 0 | L9: =IFERROR(VLOOKUP(Table4914[[#This Row],[ITEM CODE]],Table2[[Item Code]:[Master Name]],8,0),"") -> 0 | M9: 1 | N9: =IFERROR(VLOOKUP(Table4914[[#This Row],[ITEM CODE]],Table2[[#All],[Item Code]:[Unit Cost]],10,0),0) -> 0 | O9: 74.37 | R9: =Table4914[[#This Row],[QUANTITY]]*Table4914[[#This Row],[INV Prices]] -> 74.37 | V9: Sold | W9: =IFERROR(VLOOKUP(Table4914[[#This Row],[ITEM CODE]],Table2[[Item Code]:[Category ]],6,0),"") -> FOOD | X9: =IFERROR(VLOOKUP(Table4914[[#This Row],[ITEM CODE]],Table2[[Item Code]:[Sub Category]],7,0),"") -> FOOD | Y9: =Table4914[[#This Row],[PO Number]]&COUNTIFS($E$5:E66,E9) -> 0
A10: =IF(Table4914[[#This Row],[ITEM NAME]]="","",ROW()-4) -> 6 | B10: 45903 | C10: =IFERROR(VLOOKUP(B10,Table14[],3,0),"") -> 9 | D10: =IFERROR(VLOOKUP(B10,Table14[],2,0),"") -> Week 01 | G10: HEALTHY FOOD | H10: =IFERROR(VLOOKUP(Table4914[[#This Row],[ITEM CODE]],Table2[[Item Code]:[Master Name]],2,0),"") -> 0 | I10: REV-NON ALCOHOL | J10: =IFERROR(VLOOKUP(Table4914[[#This Row],[ITEM CODE]],Table2[[Item Code]:[Master Name]],3,0),"") -> Revenue Non Alcohol | K10: =IFERROR(VLOOKUP(Table4914[[#This Row],[ITEM CODE]],Table2[[Item Code]:[Master Name]],9,0),"") -> 0 | L10: =IFERROR(VLOOKUP(Table4914[[#This Row],[ITEM CODE]],Table2[[Item Code]:[Master Name]],8,0),"") -> 0 | M10: 1 | N10: =IFERROR(VLOOKUP(Table4914[[#This Row],[ITEM CODE]],Table2[[#All],[Item Code]:[Unit Cost]],10,0),0) -> 0 | O10: 57.07 | R10: =Table4914[[#This Row],[QUANTITY]]*Table4914[[#This Row],[INV Prices]] -> 57.07 | V10: Sold | W10: =IFERROR(VLOOKUP(Table4914[[#This Row],[ITEM CODE]],Table2[[Item Code]:[Category ]],6,0),"") -> BEVERAGE NON-ALOCOHOL | X10: =IFERROR(VLOOKUP(Table4914[[#This Row],[ITEM CODE]],Table2[[Item Code]:[Sub Category]],7,0),"") -> BEVERAGE NON-ALOCOHOL | Y10: =Table4914[[#This Row],[PO Number]]&COUNTIFS($E$5:E66,E10) -> 0
A11: =IF(Table4914[[#This Row],[ITEM NAME]]="","",ROW()-4) -> 7 | C11: =IFERROR(VLOOKUP(B11,Table14[],3,0),"") | D11: =IFERROR(VLOOKUP(B11,Table14[],2,0),"") | G11: HEALTHY FOOD | H11: =IFERROR(VLOOKUP(Table4914[[#This Row],[ITEM CODE]],Table2[[Item Code]:[Master Name]],2,0),"") -> 0 | I11: REV-FOOD | J11: =IFERROR(VLOOKUP(Table4914[[#This Row],[ITEM CODE]],Table2[[Item Code]:[Master Name]],3,0),"") -> Revenue Food | K11: =IFERROR(VLOOKUP(Table4914[[#This Row],[ITEM CODE]],Table2[[Item Code]:[Master Name]],9,0),"") -> 0 | L11: =IFERROR(VLOOKUP(Table4914[[#This Row],[ITEM CODE]],Table2[[Item Code]:[Master Name]],8,0),"") -> 0 | M11: 1 | N11: =IFERROR(VLOOKUP(Table4914[[#This Row],[ITEM CODE]],Table2[[#All],[Item Code]:[Unit Cost]],10,0),0) -> 0 | R11: =Table4914[[#This Row],[QUANTITY]]*Table4914[[#This Row],[INV Prices]] -> 0 | V11: Sold | W11: =IFERROR(VLOOKUP(Table4914[[#This Row],[ITEM CODE]],Table2[[Item Code]:[Category ]],6,0),"") -> FOOD | X11: =IFERROR(VLOOKUP(Table4914[[#This Row],[ITEM CODE]],Table2[[Item Code]:[Sub Category]],7,0),"") -> FOOD | Y11: =Table4914[[#This Row],[PO Number]]&COUNTIFS($E$5:E66,E11) -> 0
A12: =IF(Table4914[[#This Row],[ITEM NAME]]="","",ROW()-4) -> 8 | C12: =IFERROR(VLOOKUP(B12,Table14[],3,0),"") | D12: =IFERROR(VLOOKUP(B12,Table14[],2,0),"") | G12: HEALTHY FOOD | H12: =IFERROR(VLOOKUP(Table4914[[#This Row],[ITEM CODE]],Table2[[Item Code]:[Master Name]],2,0),"") -> 0 | I12: REV-NON ALCOHOL | J12: =IFERROR(VLOOKUP(Table4914[[#This Row],[ITEM CODE]],Table2[[Item Code]:[Master Name]],3,0),"") -> Revenue Non Alcohol | K12: =IFERROR(VLOOKUP(Table4914[[#This Row],[ITEM CODE]],Table2[[Item Code]:[Master Name]],9,0),"") -> 0 | L12: =IFERROR(VLOOKUP(Table4914[[#This Row],[ITEM CODE]],Table2[[Item Code]:[Master Name]],8,0),"") -> 0 | M12: 1 | N12: =IFERROR(VLOOKUP(Table4914[[#This Row],[ITEM CODE]],Table2[[#All],[Item Code]:[Unit Cost]],10,0),0) -> 0 | R12: =Table4914[[#This Row],[QUANTITY]]*Table4914[[#This Row],[INV Prices]] -> 0 | V12: Sold | W12: =IFERROR(VLOOKUP(Table4914[[#This Row],[ITEM CODE]],Table2[[Item Code]:[Category ]],6,0),"") -> BEVERAGE NON-ALOCOHOL | X12: =IFERROR(VLOOKUP(Table4914[[#This Row],[ITEM CODE]],Table2[[Item Code]:[Sub Category]],7,0),"") -> BEVERAGE NON-ALOCOHOL | Y12: =Table4914[[#This Row],[PO Number]]&COUNTIFS($E$5:E66,E12) -> 0
A13: =IF(Table4914[[#This Row],[ITEM NAME]]="","",ROW()-4) -> 9 | C13: =IFERROR(VLOOKUP(B13,Table14[],3,0),"") | D13: =IFERROR(VLOOKUP(B13,Table14[],2,0),"") | G13: HEALTHY FOOD | H13: =IFERROR(VLOOKUP(Table4914[[#This Row],[ITEM CODE]],Table2[[Item Code]:[Master Name]],2,0),"") -> 0 | I13: REV-FOOD | J13: =IFERROR(VLOOKUP(Table4914[[#This Row],[ITEM CODE]],Table2[[Item Code]:[Master Name]],3,0),"") -> Revenue Food | K13: =IFERROR(VLOOKUP(Table4914[[#This Row],[ITEM CODE]],Table2[[Item Code]:[Master Name]],9,0),"") -> 0 | L13: =IFERROR(VLOOKUP(Table4914[[#This Row],[ITEM CODE]],Table2[[Item Code]:[Master Name]],8,0),"") -> 0 | M13: 1 | N13: =IFERROR(VLOOKUP(Table4914[[#This Row],[ITEM CODE]],Table2[[#All],[Item Code]:[Unit Cost]],10,0),0) -> 0 | R13: =Table4914[[#This Row],[QUANTITY]]*Table4914[[#This Row],[INV Prices]] -> 0 | V13: Sold | W13: =IFERROR(VLOOKUP(Table4914[[#This Row],[ITEM CODE]],Table2[[Item Code]:[Category ]],6,0),"") -> FOOD | X13: =IFERROR(VLOOKUP(Table4914[[#This Row],[ITEM CODE]],Table2[[Item Code]:[Sub Category]],7,0),"") -> FOOD | Y13: =Table4914[[#This Row],[PO Number]]&COUNTIFS($E$5:E66,E13) -> 0
A14: =IF(Table4914[[#This Row],[ITEM NAME]]="","",ROW()-4) -> 10 | C14: =IFERROR(VLOOKUP(B14,Table14[],3,0),"") | D14: =IFERROR(VLOOKUP(B14,Table14[],2,0),"") | G14: HEALTHY FOOD | H14: =IFERROR(VLOOKUP(Table4914[[#This Row],[ITEM CODE]],Table2[[Item Code]:[Master Name]],2,0),"") -> 0 | I14: REV-NON ALCOHOL | J14: =IFERROR(VLOOKUP(Table4914[[#This Row],[ITEM CODE]],Table2[[Item Code]:[Master Name]],3,0),"") -> Revenue Non Alcohol | K14: =IFERROR(VLOOKUP(Table4914[[#This Row],[ITEM CODE]],Table2[[Item Code]:[Master Name]],9,0),"") -> 0 | L14: =IFERROR(VLOOKUP(Table4914[[#This Row],[ITEM CODE]],Table2[[Item Code]:[Master Name]],8,0),"") -> 0 | M14: 1 | N14: =IFERROR(VLOOKUP(Table4914[[#This Row],[ITEM CODE]],Table2[[#All],[Item Code]:[Unit Cost]],10,0),0) -> 0 | R14: =Table4914[[#This Row],[QUANTITY]]*Table4914[[#This Row],[INV Prices]] -> 0 | V14: Sold | W14: =IFERROR(VLOOKUP(Table4914[[#This Row],[ITEM CODE]],Table2[[Item Code]:[Category ]],6,0),"") -> BEVERAGE NON-ALOCOHOL | X14: =IFERROR(VLOOKUP(Table4914[[#This Row],[ITEM CODE]],Table2[[Item Code]:[Sub Category]],7,0),"") -> BEVERAGE NON-ALOCOHOL | Y14: =Table4914[[#This Row],[PO Number]]&COUNTIFS($E$5:E66,E14) -> 0
A15: =IF(Table4914[[#This Row],[ITEM NAME]]="","",ROW()-4) -> 11 | C15: =IFERROR(VLOOKUP(B15,Table14[],3,0),"") | D15: =IFERROR(VLOOKUP(B15,Table14[],2,0),"") | G15: HEALTHY FOOD | H15: =IFERROR(VLOOKUP(Table4914[[#This Row],[ITEM CODE]],Table2[[Item Code]:[Master Name]],2,0),"") -> 0 | I15: REV-FOOD | J15: =IFERROR(VLOOKUP(Table4914[[#This Row],[ITEM CODE]],Table2[[Item Code]:[Master Name]],3,0),"") -> Revenue Food | K15: =IFERROR(VLOOKUP(Table4914[[#This Row],[ITEM CODE]],Table2[[Item Code]:[Master Name]],9,0),"") -> 0 | L15: =IFERROR(VLOOKUP(Table4914[[#This Row],[ITEM CODE]],Table2[[Item Code]:[Master Name]],8,0),"") -> 0 | M15: 1 | N15: =IFERROR(VLOOKUP(Table4914[[#This Row],[ITEM CODE]],Table2[[#All],[Item Code]:[Unit Cost]],10,0),0) -> 0 | R15: =Table4914[[#This Row],[QUANTITY]]*Table4914[[#This Row],[INV Prices]] -> 0 | V15: Sold | W15: =IFERROR(VLOOKUP(Table4914[[#This Row],[ITEM CODE]],Table2[[Item Code]:[Category ]],6,0),"") -> FOOD | X15: =IFERROR(VLOOKUP(Table4914[[#This Row],[ITEM CODE]],Table2[[Item Code]:[Sub Category]],7,0),"") -> FOOD | Y15: =Table4914[[#This Row],[PO Number]]&COUNTIFS($E$5:E66,E15) -> 0
A16: =IF(Table4914[[#This Row],[ITEM NAME]]="","",ROW()-4) -> 12 | C16: =IFERROR(VLOOKUP(B16,Table14[],3,0),"") | D16: =IFERROR(VLOOKUP(B16,Table14[],2,0),"") | G16: HEALTHY FOOD | H16: =IFERROR(VLOOKUP(Table4914[[#This Row],[ITEM CODE]],Table2[[Item Code]:[Master Name]],2,0),"") -> 0 | I16: REV-NON ALCOHOL | J16: =IFERROR(VLOOKUP(Table4914[[#This Row],[ITEM CODE]],Table2[[Item Code]:[Master Name]],3,0),"") -> Revenue Non Alcohol | K16: =IFERROR(VLOOKUP(Table4914[[#This Row],[ITEM CODE]],Table2[[Item Code]:[Master Name]],9,0),"") -> 0 | L16: =IFERROR(VLOOKUP(Table4914[[#This Row],[ITEM CODE]],Table2[[Item Code]:[Master Name]],8,0),"") -> 0 | M16: 1 | N16: =IFERROR(VLOOKUP(Table4914[[#This Row],[ITEM CODE]],Table2[[#All],[Item Code]:[Unit Cost]],10,0),0) -> 0 | R16: =Table4914[[#This Row],[QUANTITY]]*Table4914[[#This Row],[INV Prices]] -> 0 | V16: Sold | W16: =IFERROR(VLOOKUP(Table4914[[#This Row],[ITEM CODE]],Table2[[Item Code]:[Category ]],6,0),"") -> BEVERAGE NON-ALOCOHOL | X16: =IFERROR(VLOOKUP(Table4914[[#This Row],[ITEM CODE]],Table2[[Item Code]:[Sub Category]],7,0),"") -> BEVERAGE NON-ALOCOHOL | Y16: =Table4914[[#This Row],[PO Number]]&COUNTIFS($E$5:E66,E16) -> 0
